Workbook

Sheet Raw_Data
A1: Sr.NO | B1: shortName | C1: industry | D1: ebitdaMargins | E1: profitMargins | F1: grossMargins | G1: operatingCashflow | H1: revenueGrowth | I1: operatingMargins | J1: ebitda | K1: grossProfits | L1: freeCashflow | M1: currentPrice | N1: earningsGrowth | O1: currentRatio | P1: returnOnAssets | Q1: debtToEquity | R1: returnOnEquity | S1: totalCash | T1: totalDebt | U1: totalRevenue | V1: totalCashPerShare | W1: financialCurrency | X1: revenuePerShare | Y1: quickRatio | Z1: quoteType | AA1: symbol | AB1: enterpriseToRevenue | AC1: enterpriseToEbitda | AD1: forwardEps | AE1: sharesOutstanding | AF1: bookValue | AG1: trailingEps | AH1: priceToBook | AI1: heldPercentInsiders | AJ1: enterpriseValue | AK1: earningsQuarterlyGrowth | AL1: pegRatio | AM1: forwardPE | AN1: marketCap
A2: 0 | B2: Apple Inc. | C2: Consumer Electronics | D2: 0.33890998 | E2: 0.26579002 | F2: 0.43019 | G2: 112241000448 | H2: 0.112 | I2: 0.309 | J2: 128217997312 | K2: 152836000000 | L2: 80153247744 | M2: 174.72 | N2: 0.25 | O2: 1.038 | P2: 0.19875 | Q2: 170.714 | R2: 1.45567 | S2: 63913000960 | T2: 122797998080 | U2: 378323009536 | V2: 3.916 | W2: USD | X2: 22.838 | Y2: 0.875 | Z2: EQUITY | AA2: AAPL | AB2: 7.692 | AC2: 22.697 | AD2: 6.56 | AE2: 16319399936 | AF2: 4.402 | AG2: 6.015 | AH2: 39.69105 | AI2: 0.0007 | AJ2: 2910217830400 | AK2: 0.204 | AL2: 1.9 | AM2: 26.634148 | AN2: 2851325607936
A3: 1 | B3: Microsoft Corporation | C3: Software—Infrastructure | D3: 0.49123 | E3: 0.38498002 | F3: 0.68825996 | G3: 83909001216 | H3: 0.201 | I3: 0.42523998 | J3: 90829996032 | K3: 115856000000 | L3: 46479876096 | M3: 303.68 | N3: 0.222 | O3: 2.247 | P3: 0.15248999 | Q3: 50.217 | R3: 0.49051 | S3: 125348003840 | T3: 80353001472 | U3: 184902991872 | V3: 16.72 | W3: USD | X3: 24.585 | Y3: 2.05 | Z3: EQUITY | AA3: MSFT | AB3: 12.069 | AC3: 24.57 | AD3: 10.75 | AE3: 7496869888 | AF3: 21.335 | AG3: 9.389 | AH3: 14.233889 | AI3: 0.00059 | AJ3: 2231653367808 | AK3: 0.214 | AL3: 1.87 | AM3: 28.249302 | AN3: 2276649336832
A4: 2 | B4: Alphabet Inc. | C4: Internet Content & Information | D4: 0.35377 | E4: 0.29512 | F4: 0.5694 | G4: 91651997696 | H4: 0.324 | I4: 0.30552 | J4: 91144003584 | K4: 146698000000 | L4: 49490001920 | M4: 2830.43 | N4: 0.377 | O4: 2.928 | P4: 0.14493 | Q4: 11.329 | R4: 0.32069 | S4: 139649007616 | T4: 28508000256 | U4: 257637007360 | V4: 211.278 | W4: USD | X4: 385.886 | Y4: 2.8 | Z4: EQUITY | AA4: GOOG | AB4: 6.83 | AC4: 19.307 | AD4: 136.06 | AE4: 315639008 | AF4: 380.044 | AG4: 112.197 | AH4: 7.4476376 | AI4: 0.00034000003 | AJ4: 1759692062720 | AK4: 0.356 | AL4: 1.22 | AM4: 20.802807 | AN4: 1872632217600
A5: 3 | B5: Alphabet Inc. | C5: Internet Content & Information | D5: 0.35377 | E5: 0.29512 | F5: 0.5694 | G5: 91651997696 | H5: 0.324 | I5: 0.30552 | J5: 91144003584 | K5: 146698000000 | L5: 49490001920 | M5: 2833.46 | N5: 0.377 | O5: 2.928 | P5: 0.14493 | Q5: 11.329 | R5: 0.32069 | S5: 139649007616 | T5: 28508000256 | U5: 257637007360 | V5: 211.278 | W5: USD | X5: 385.886 | Y5: 2.8 | Z5: EQUITY | AA5: GOOGL | AB5: 6.838 | AC5: 19.329 | AD5: 135.95 | AE5: 300755008 | AF5: 380.044 | AG5: 112.197 | AH5: 7.4556103 | AI5: 0.077020004 | AJ5: 1761694842880 | AK5: 0.356 | AL5: 1.22 | AM5: 20.841927 | AN5: 1871194226688
A6: 4 | B6: Amazon.com, Inc. | C6: Internet Retail | D6: 0.12595001 | E6: 0.07101 | F6: 0.42032 | G6: 46327001088 | H6: 0.094 | I6: 0.052950002 | J6: 59174998016 | K6: 197478000000 | L6: -787249984 | M6: 3295.47 | N6: 0.975 | O6: 1.136 | P6: 0.041929998 | Q6: 100.864 | R6: 0.28806 | S6: 96048996352 | T6: 139438997504 | U6: 469822013440 | V6: 188.759 | W6: USD | X6: 928.502 | Y6: 0.905 | Z6: EQUITY | AA6: AMZN | AB6: 3.662 | AC6: 29.071 | AD6: 72.85 | AE6: 508844000 | AF6: 271.601 | AG6: 64.81 | AH6: 12.133496 | AI6: 0.09884 | AJ6: 1720271503360 | AK6: 0.983 | AL6: 1.93 | AM6: 45.236378 | AN6: 1676880117760
A7: 5 | B7: Tesla, Inc. | C7: Auto Manufacturers | D7: 0.15512 | E7: 0.07403 | F7: 0.23107 | G7: 9930999808 | H7: 0.568 | I7: 0.09789 | J7: 7266999808 | K7: 6630000000 | L7: 4644624896 | M7: 1010.64 | N7: 4.333 | O7: 1.385 | P7: 0.055370003 | Q7: 35.65 | R7: 0.15641 | S7: 16094999552 | T7: 10158000128 | U7: 46848000000 | V7: 16.027 | W7: USD | X7: 48.272 | Y7: 1.002 | Z7: EQUITY | AA7: TSLA | AB7: 24.547 | AC7: 158.249 | AD7: 8.76 | AE7: 1004259968 | AF7: 26.945 | AG7: 3.062 | AH7: 37.507515 | AI7: 0.19959 | AJ7: 1149996892160 | AK7: 3.888 | AL7: 2.52 | AM7: 115.36987 | AN7: 1014945284096
A8: 7 | B8: NVIDIA Corporation | C8: Semiconductors | D8: 0.40203 | E8: 0.33806 | F8: 0.64398 | G8: 8142000128 | H8: 0.503 | I8: 0.35454 | J8: 9758999552 | K8: 10557000000 | L8: 5935249920 | M8: 276.92 | N8: 0.83 | O8: 7.145 | P8: 0.15934 | Q8: 49.697 | R8: 0.41939998 | S8: 19298000896 | T8: 11827000320 | U8: 24273999872 | V8: 7.719 | W8: USD | X8: 9.75 | Y8: 6.437 | Z8: EQUITY | AA8: NVDA | AB8: 29.858 | AC8: 74.268 | AD8: 5.21 | AE8: 2492000000 | AF8: 9.512 | AG8: 3.243 | AH8: 29.112701 | AI8: 0.04079 | AJ8: 724779008000 | AK8: 0.844 | AL8: 1.71 | AM8: 53.151634 | AN8: 690084642816
A9: 8 | B9: Meta Platforms, Inc. | C9: Internet Content & Information | D9: 0.46401 | E9: 0.33383998 | F9: 0.80794 | G9: 57683001344 | H9: 0.199 | I9: 0.39645 | J9: 54720000000 | K9: 95280000000 | L9: 28807624704 | M9: 221.82 | N9: -0.052 | O9: 3.154 | P9: 0.17965001 | Q9: 11.574 | R9: 0.31102 | S9: 47998001152 | T9: 14453999616 | U9: 117929000960 | V9: 17.634 | W9: USD | X9: 41.893 | Y9: 2.935 | Z9: EQUITY | AA9: FB | AB9: 4.586 | AC9: 9.884 | AD9: 14.23 | AE9: 2366279936 | AF9: 47.748 | AG9: 13.974 | AH9: 4.6456394 | AI9: 0.0053100004 | AJ9: 540867395584 | AK9: -0.083 | AL9: 1.13 | AM9: 15.588195 | AN9: 617050013696
A10: 9 | B10: UnitedHealth Group Incorporated | C10: Healthcare Plans | D10: 0.086619996 | E10: 0.05523 | F10: 0.24284 | G10: 25226000384 | H10: 0.111 | I10: 0.07857 | J10: 24195999744 | K10: 67000000000 | L10: 24690499584 | M10: 513.03 | N10: 0.297 | O10: 0.72 | P10: 0.0679 | Q10: 62.929 | R10: 0.21985 | S10: 23871000576 | T10: 46964998144 | U10: 279320985600 | V10: 25.345 | W10: USD | X10: 295.5 | Y10: 0.655 | Z10: EQUITY | AA10: UNH | AB10: 1.754 | AC10: 20.243 | AD10: 21.65 | AE10: 941851008 | AF10: 74.605 | AG10: 16.111 | AH10: 6.876617 | AI10: 0.00548 | AJ10: 489802792960 | AK10: 0.288 | AL10: 1.84 | AM10: 23.696537 | AN10: 483197845504
A11: 10 | B11: Visa Inc. | C11: Credit Services | D11: 0.69612 | E11: 0.51592 | F11: 0.97068 | G11: 15946000384 | H11: 0.241 | I11: 0.66452 | J11: 17735000064 | K11: 23375000000 | L11: 12081874944 | M11: 218.43 | N11: 0.291 | O11: 1.395 | P11: 0.13035 | Q11: 57.8 | R11: 0.35584998 | S11: 15921000448 | T11: 20920000512 | U11: 25476999168 | V11: 7.591 | W11: USD | X11: 12.01 | Y11: 1.07 | Z11: EQUITY | AA11: V | AB11: 18.203 | AC11: 26.149 | AI11: 0.0013600001 | AJ11: 463753445376 | AK11: 0.266
A12: 11 | B12: Johnson & Johnson | C12: Drug Manufacturers—General | D12: 0.34803 | E12: 0.22264 | F12: 0.6827 | G12: 23409999872 | H12: 0.104 | I12: 0.26923 | J12: 32636999680 | K12: 64020000000 | L12: 18816999424 | M12: 176.92 | N12: 1.723 | O12: 1.348 | P12: 0.08842 | Q12: 46.946 | R12: 0.30412 | S12: 31608000512 | T12: 34751000576 | U12: 93775003648 | V12: 12.022 | W12: USD | X12: 35.627 | Y12: 1.037 | Z12: EQUITY | AA12: JNJ | AB12: 4.467 | AC12: 12.836 | AD12: 10.38 | AE12: 2632600064 | AF12: 26.694 | AG12: 6.691 | AH12: 6.6277065 | AI12: 0.00086000003 | AJ12: 418935472128 | AK12: 1.725 | AL12: 2.13 | AM12: 17.044315 | AN12: 465759600640
A13: 13 | B13: Walmart Inc. | C13: Discount Stores | D13: 0.0639 | E13: 0.02387 | F13: 0.25099 | G13: 24181000192 | H13: 0.005 | I13: 0.045289997 | J13: 36600000512 | K13: 143754000000 | L13: 13358499840 | M13: 143.45 | O13: 0.928 | P13: 0.0652 | Q13: 62.382 | R13: 0.15539 | S13: 14759999488 | T13: 57322999808 | U13: 572753969152 | V13: 5.33 | W13: USD | X13: 205.141 | Y13: 0.264 | Z13: EQUITY | AA13: WMT | AB13: 0.743 | AC13: 11.625 | AD13: 6.72 | AE13: 2773880064 | AF13: 29.616 | AG13: 2.84 | AH13: 4.8436656 | AI13: 0.47501 | AJ13: 425459023872 | AL13: 2.73 | AM13: 21.346725 | AN13: 397913096192
A14: 14 | B14: Procter & Gamble Company (The) | C14: Household & Personal Products | D14: 0.27021998 | E14: 0.1852 | F14: 0.49445 | G14: 17972000768 | H14: 0.061 | I14: 0.23464 | J14: 21170999296 | K14: 39144000000 | L14: 11721624576 | M14: 152.83 | N14: 0.126 | O14: 0.672 | P14: 0.09514 | Q14: 79.418 | R14: 0.31092 | S14: 11544000512 | T14: 35653001216 | U14: 78346002432 | V14: 4.816 | W14: USD | X14: 32.166 | Y14: 0.441 | Z14: EQUITY | AA14: PG | AB14: 4.965 | AC14: 18.375 | AD14: 6.36 | AE14: 2419950080 | AF14: 18.7 | AG14: 5.472 | AH14: 8.172727 | AI14: 0.0011100001 | AJ14: 389018681344 | AK14: 0.096 | AL14: 3.98 | AM14: 24.029875 | AN14: 369840979968
A15: 15 | B15: Exxon Mobil Corporation | C15: Oil & Gas Integrated | D15: 0.16555999 | E15: 0.08259 | F15: 0.32276002 | G15: 48128999424 | H15: 0.794 | I15: 0.09599 | J15: 46186999808 | K15: 90045000000 | L15: 28528625664 | M15: 85.2 | O15: 1.044 | P15: 0.049840003 | Q15: 30.184 | R15: 0.13889 | S15: 6801999872 | T15: 53028999168 | U15: 278980984832 | V15: 1.607 | W15: USD | X15: 65.259 | Y15: 0.692 | Z15: EQUITY | AA15: XOM | AB15: 1.341 | AC15: 8.103 | AD15: 5.88 | AE15: 4233540096 | AF15: 37.932 | AG15: -1.386 | AH15: 2.2461245 | AI15: 0.00102 | AJ15: 374239297536 | AL15: 13.11 | AM15: 14.489795 | AN15: 363009933312
A16: 17 | B16: Mastercard Incorporated | C16: Credit Services | D16: 0.58217996 | E16: 0.46001998 | F16: 1 | G16: 9463000064 | H16: 0.266 | I16: 0.54374003 | J16: 10993999872 | K16: 18884000000 | L16: 8458124800 | M16: 349.02 | N16: 0.355 | O16: 1.288 | P16: 0.18013 | Q16: 197.963 | R16: 1.2473301 | S16: 7894000128 | T16: 14673000448 | U16: 18883999744 | V16: 8.076 | W16: USD | X16: 19.113 | Y16: 0.928 | Z16: EQUITY | AA16: MA | AB16: 19.041 | AC16: 32.706 | AD16: 10.53 | AE16: 974708992 | AF16: 6.814 | AG16: 8.13 | AH16: 51.221012 | AI16: 0.10855 | AJ16: 359572045824 | AK16: 0.333 | AL16: 1.73 | AM16: 33.145298 | AN16: 342932029440
A17: 18 | B17: Home Depot, Inc. (The) | C17: Home Improvement Retail | D17: 0.17396 | E17: 0.10791001 | F17: 0.33718 | G17: 14810000384 | H17: 0.098 | I17: 0.15505 | J17: 25693999104 | K17: 44853000000 | L17: 9990124544 | M17: 310.68 | N17: 0.233 | O17: 1.132 | P17: 0.20454 | Q17: 4373.43 | R17: 12.403111 | S17: 5066999808 | T17: 45264998400 | U17: 147699007488 | V17: 4.852 | W17: USD | X17: 138.978 | Y17: 0.32 | Z17: EQUITY | AA17: HD | AB17: 3.191 | AC17: 18.343 | AD17: 16.19 | AE17: 1044240000 | AF17: 0.989 | AG17: 14.955 | AH17: 314.13547 | AI17: 0.00061 | AJ17: 471301718016 | AK17: 0.203 | AL17: 1.95 | AM17: 19.189623 | AN17: 324424466432
A18: 19 | B18: Chevron Corporation | C18: Oil & Gas Integrated | D18: 0.21459 | E18: 0.10041001 | F18: 0.42565 | G18: 29199998976 | H18: 0.846 | I18: 0.09956 | J18: 33392001024 | K18: 66234000000 | M18: 169.31 | Q18: 27.316 | R18: 0.11645 | S18: 6032000000 | T18: 37347000320 | U18: 155606007808 | V18: 3.129 | W18: USD | X18: 81.214 | Z18: EQUITY | AA18: CVX | AB18: 1.877 | AC18: 8.748 | AD18: 9.51 | AE18: 1927689984 | AF18: 70.479 | AG18: 5.173 | AH18: 2.402276 | AI18: 0.00037 | AJ18: 292123443200 | AL18: -2.98 | AM18: 17.803364 | AN18: 326377177088
A19: 20 | B19: Pfizer, Inc. | C19: Drug Manufacturers—General | D19: 0.39382 | E19: 0.28684 | F19: 0.65414 | G19: 32291000320 | H19: 1.344 | I19: 0.32139 | J19: 27306000384 | K19: 33334000000 | L19: 42431250432 | M19: 52.78 | N19: 4.468 | O19: 1.385 | P19: 0.07777 | Q19: 52.496 | R19: 0.27747 | S19: 29702000640 | T19: 39879000064 | U19: 69336997888 | V19: 5.292 | W19: USD | X19: 12.407 | Y19: 1.088 | Z19: EQUITY | AA19: PFE | AB19: 4.565 | AC19: 11.592 | AD19: 49.43 | AE19: 5612870144 | AF19: 13.49 | AG19: 3.501 | AH19: 3.9125278 | AI19: 0.00037999998 | AJ19: 316521611264 | AK19: 4.545 | AL19: 0.01 | AM19: 1.0677726 | AN19: 296247263232
A20: 21 | B20: AbbVie Inc. | C20: Drug Manufacturers—General | D20: 0.50286996 | E20: 0.20538001 | F20: 0.69338 | H20: 0.074 | I20: 0.34765 | J20: 28259663872 | K20: 38966000000 | M20: 161.33 | N20: 248.779 | Q20: 594.66 | R20: 0.86594003 | S20: 12248999936 | T20: 80737001472 | U20: 56197001216 | V20: 6.929 | W20: USD | X20: 31.625 | Z20: EQUITY | AA20: ABBV | AB20: 5.808 | AC20: 11.55 | AD20: 13.97 | AE20: 1767879936 | AF20: 7.665 | AG20: 4.196 | AH20: 21.047619 | AI20: 0.00107 | AJ20: 326395723776 | AK20: 111.333 | AL20: 2.38 | AM20: 11.548318 | AN20: 285212082176
A21: 22 | B21: Eli Lilly and Company | C21: Drug Manufacturers—General | D21: 0.34789002 | E21: 0.21515 | F21: 0.76413 | G21: 6919399936 | H21: 0.18 | I21: 0.29496 | J21: 9656999936 | K21: 19056500000 | L21: 3820699904 | M21: 289.02 | N21: -0.083 | O21: 1.302 | P21: 0.11108 | Q21: 215.45 | R21: 0.92237 | S21: 3852499968 | T21: 17137099776 | U21: 27758499840 | V21: 4.249 | W21: USD | X21: 30.578 | Y21: 0.793 | Z21: EQUITY | AA21: LLY | AB21: 8.955 | AC21: 25.742 | AD21: 7.49 | AE21: 956592000 | AF21: 8.552 | AG21: 6.55 | AH21: 33.7956 | AI21: 0.0015199999 | AJ21: 248588304384 | AK21: -0.081 | AL21: 5.2 | AM21: 38.58745 | AN21: 276474200064
A22: 23 | B22: Coca-Cola Company (The) | C22: Beverages—Non-Alcoholic | D22: 0.35199 | E22: 0.23313999 | F22: 0.60723996 | G22: 12855000064 | H22: 0.161 | I22: 0.31123 | J22: 13306000384 | K22: 19581000000 | L22: 7007374848 | M22: 61.53 | N22: 0.425 | O22: 1.516 | P22: 0.07831 | Q22: 172.826 | R22: 0.39722002 | S22: 14871000064 | T22: 41707999232 | U22: 37802000384 | V22: 3.443 | W22: USD | X22: 8.771 | Y22: 1.173 | Z22: EQUITY | AA22: KO | AB22: 7.651 | AC22: 21.735 | AD22: 2.43 | AE22: 4319419904 | AF22: 5.135 | AG22: 2.031 | AH22: 11.982472 | AI22: 0.00636 | AJ22: 289208860672 | AK22: 0.423 | AL22: 2.72 | AM22: 25.320986 | AN22: 265773907968
A23: 24 | B23: Broadcom Inc. | C23: Semiconductors | D23: 0.53639 | E23: 0.24539 | F23: 0.73908997 | G23: 13763999744 | H23: 0.145 | I23: 0.31632 | J23: 14723999744 | K23: 20288000000 | L23: 11868749824 | M23: 628.87 | N23: 0.521 | O23: 2.641 | P23: 0.07164 | Q23: 161.163 | R23: 0.27556 | S23: 12163000320 | T23: 40272998400 | U23: 27449999360 | V23: 29.459 | W23: USD | X23: 66.951 | Y23: 2.266 | Z23: EQUITY | AA23: AVGO | AB23: 9.65 | AC23: 17.99 | AD23: 36.05 | AE23: 412873984 | AF23: 60.441 | AG23: 15 | AH23: 10.404692 | AI23: 0.02391 | AJ23: 264887189504 | AK23: 0.502 | AL23: 1.38 | AM23: 17.444384 | AN23: 259644063744
A24: 25 | B24: Walt Disney Company (The) | C24: Entertainment | D24: 0.12761 | E24: 0.029590001 | F24: 0.33058 | G24: 5567000064 | H24: 0.26 | I24: 0.051799998 | J24: 8602999808 | K24: 22287000000 | L24: 7388250112 | M24: 139.14 | O24: 1.083 | P24: 0.01077 | Q24: 57.044 | R24: 0.025390001 | S24: 15959000064 | T24: 58312998912 | U24: 67418001408 | V24: 8.78 | W24: USD | X24: 37.124 | Y24: 0.944 | Z24: EQUITY | AA24: DIS | AB24: 5.03 | AC24: 39.415 | AD24: 5.06 | AE24: 1817660032 | AF24: 48.709 | AG24: 1.094 | AH24: 2.8565562 | AI24: 0.00099 | AJ24: 339088572416 | AL24: 1.07 | AM24: 27.498024 | AN24: 252909207552
A25: 26 | B25: Costco Wholesale Corporation | C25: Discount Stores | D25: 0.046350002 | E25: 0.02543 | F25: 0.12755999 | G25: 9569000448 | H25: 0.166 | I25: 0.03744 | J25: 9413000192 | K25: 25245000000 | L25: 687625024 | M25: 555.71 | N25: 0.137 | O25: 1.015 | P25: 0.07643 | Q25: 53.237 | R25: 0.30563 | S25: 13475999744 | T25: 10115000320 | U25: 203084005376 | V25: 30.39 | W25: USD | X25: 458.227 | Y25: 0.462 | Z25: EQUITY | AA25: COST | AB25: 1.105 | AC25: 23.838 | AD25: 13.96 | AE25: 443432000 | AF25: 41.636 | AG25: 11.63 | AH25: 13.346864 | AI25: 0.00204 | AJ25: 224390807552 | AK25: 0.136 | AL25: 4.42 | AM25: 39.80731 | AN25: 246419603456
A26: 27 | B26: Pepsico, Inc. | C26: Beverages—Non-Alcoholic | D26: 0.18109 | E26: 0.10617 | F26: 0.53927 | G26: 11123999744 | H26: 0.116 | I26: 0.15435 | J26: 13886000128 | K26: 38637000000 | L26: 4287749888 | M26: 165.24 | N26: -0.03 | O26: 0.945 | P26: 0.079840004 | Q26: 258.017 | R26: 0.55412996 | S26: 6849999872 | T26: 41257000960 | U26: 76681003008 | V26: 4.954 | W26: USD | X26: 55.546 | Y26: 0.654 | Z26: EQUITY | AA26: PEP | AB26: 3.574 | AC26: 19.735 | AD26: 6.74 | AE26: 1382649984 | AF26: 11.484 | AG26: 5.87 | AH26: 14.388715 | AI26: 0.00135 | AJ26: 274041962496 | AK26: -0.029 | AL26: 2.85 | AM26: 24.516321 | AN26: 228469096448
A27: 28 | B27: Cisco Systems, Inc. | C27: Communication Equipment | D27: 0.31235 | E27: 0.2244 | F27: 0.63726 | G27: 14785000448 | H27: 0.081 | I27: 0.27665 | J27: 15864000512 | K27: 31894000000 | L27: 10929999872 | M27: 54.97 | N27: 0.373 | O27: 1.618 | P27: 0.09196 | Q27: 25.032 | R27: 0.28190002 | S27: 23352000512 | T27: 10689000448 | U27: 50788999168 | V27: 5.537 | W27: USD | X27: 12.038 | Y27: 1.408 | Z27: EQUITY | AA27: CSCO | AB27: 4.227 | AC27: 13.532 | AD27: 3.68 | AE27: 4217609984 | AF27: 10.126 | AG27: 2.69 | AH27: 5.4285994 | AI27: 0.0007 | AJ27: 214665986048 | AK27: 0.371 | AL27: 2.73 | AM27: 14.9375 | AN27: 231842021376
A28: 29 | B28: Thermo Fisher Scientific Inc | C28: Diagnostics & Research | D28: 0.32687 | E28: 0.19701 | F28: 0.51603 | G28: 9543000064 | H28: 0.014 | I28: 0.26077 | J28: 12817000448 | K28: 20234000000 | L28: 5478624768 | M28: 574.29 | N28: -0.331 | O28: 1.504 | P28: 0.07801 | Q28: 85.097 | R28: 0.20476 | S28: 4477000192 | T28: 34870001664 | U28: 39210999808 | V28: 11.363 | W28: USD | X28: 99.52 | Y28: 0.933 | Z28: EQUITY | AA28: TMO | AB28: 6.206 | AC28: 18.986 | AD28: 21.73 | AE28: 394048000 | AF28: 98.237 | AG28: 21.544 | AH28: 5.845964 | AI28: 0.00207 | AJ28: 243341983744 | AK28: -0.336 | AL28: 2.23 | AM28: 26.42844 | AN28: 226297823232
A29: 30 | B29: Oracle Corporation | C29: Software—Infrastructure | D29: 0.44465 | E29: 0.24788 | F29: 0.79958 | G29: 10254999552 | H29: 0.057 | I29: 0.38564 | J29: 18407999488 | K29: 32624000000 | L29: 9675875328 | M29: 81.73 | O29: 1.646 | P29: 0.092 | S29: 22837999616 | T29: 78431002624 | U29: 41399001088 | V29: 8.552 | W29: USD | X29: 14.754 | Y29: 1.446 | Z29: EQUITY | AA29: ORCL | AB29: 6.288 | AC29: 14.141 | AD29: 5.26 | AE29: 2670449920 | AF29: -3.782 | AG29: 3.543 | AI29: 0.41914 | AJ29: 260298489856 | AL29: 1.91 | AM29: 15.538023 | AN29: 218255884288
A30: 31 | B30: Accenture plc | C30: Information Technology Services | D30: 0.16804 | E30: 0.11533 | F30: 0.32348 | G30: 7903174144 | H30: 0.272 | I30: 0.15195 | J30: 9030121472 | K30: 16364128000 | L30: 6319962112 | M30: 327.71 | N30: 0.197 | O30: 1.223 | P30: 0.12456001 | Q30: 16.607 | R30: 0.31948 | S30: 5644085248 | T30: 3477277952 | U30: 53736357888 | V30: 8.931 | W30: USD | X30: 84.725 | Y30: 1.101 | Z30: EQUITY | AA30: ACN | AB30: 4.198 | AC30: 24.983 | AD30: 10.45 | AE30: 632001024 | AF30: 32.2 | AG30: 9.613 | AH30: 10.177329 | AI30: 0.00123 | AJ30: 225603960832 | AK30: 0.194 | AL30: 3.82 | AM30: 31.359808 | AN30: 207279521792
A31: 32 | B31: Verizon Communications Inc. | C31: Telecom Services | D31: 0.37467 | E31: 0.16419001 | F31: 0.58188 | G31: 40457998336 | H31: 0.043 | I31: 0.25285998 | J31: 50295001088 | K31: 77091000000 | L31: -24466874368 | M31: 51.28 | N31: 0.473 | O31: 0.974 | P31: 0.06523 | Q31: 228.038 | R31: 0.31167 | S31: 10152999936 | T31: 178984992768 | U31: 134238003200 | V31: 2.452 | W31: USD | X31: 32.413 | Y31: 0.799 | Z31: EQUITY | AA31: VZ | AB31: 2.918 | AC31: 7.787 | AD31: 5.4 | AE31: 4197760000 | AF31: 18.609 | AG31: 5.32 | AH31: 2.755656 | AI31: 0.00016000001 | AJ31: 391651557376 | AK31: 0.471 | AL31: 2.62 | AM31: 9.496296 | AN31: 215261134848
A32: 33 | B32: Salesforce.com Inc | C32: Software—Application | D32: 0.13629 | E32: 0.06961 | F32: 0.74017996 | G32: 6192000000 | H32: 0.266 | I32: 0.03887 | J32: 3404999936 | K32: 15814000000 | L32: 8601624576 | M32: 211.03 | N32: -0.591 | O32: 1.061 | P32: 0.00828 | Q32: 25.131 | R32: 0.035720002 | S32: 9390999552 | T32: 14337999872 | U32: 24982999040 | V32: 9.534 | W32: USD | X32: 26.634 | Y32: 0.892 | Z32: EQUITY | AA32: CRM | AB32: 8.395 | AC32: 61.594 | AD32: 4.71 | AE32: 985000000 | AF32: 57.982 | AG32: 1.818 | AH32: 3.6395779 | AI32: 0.03408 | AJ32: 209728503808 | AK32: -0.567 | AL32: 5.29 | AM32: 44.80467 | AN32: 207864545280
A33: 34 | B33: Comcast Corporation | C33: Entertainment | D33: 0.2935 | E33: 0.12731 | F33: 0.66587996 | G33: 26499000320 | H33: 0.187 | I33: 0.17506 | J33: 33387999232 | K33: 70443000000 | L33: 10249124864 | M33: 47.13 | N33: 0.955 | O33: 1.026 | P33: 0.04559 | Q33: 104.661 | R33: 0.15312 | S33: 11806000128 | T33: 102385999872 | U33: 113757003776 | V33: 2.584 | W33: USD | X33: 24.781 | Y33: 0.889 | Z33: EQUITY | AA33: CMCSA | AB33: 2.868 | AC33: 9.772 | AD33: 3.69 | AE33: 4559479808 | AF33: 20.964 | AG33: 3.109 | AH33: 2.2481396 | AI33: 0.00676 | AJ33: 326278709248 | AK33: 0.999 | AL33: 0.87 | AM33: 12.772358 | AN33: 215333208064
A34: 35 | B34: Intel Corporation | C34: Semiconductors | D34: 0.42865002 | E34: 0.25142 | F34: 0.55445 | G34: 29991000064 | H34: 0.028 | I34: 0.27943 | J34: 33873999872 | K34: 43815000000 | L34: 1480125056 | M34: 51.83 | N34: -0.209 | O34: 2.102 | P34: 0.08586001 | Q34: 40.508 | R34: 0.22522 | S34: 28412999680 | T34: 38641000448 | U34: 79023996928 | V34: 6.978 | W34: USD | X34: 19.469 | Y34: 1.38 | Z34: EQUITY | AA34: INTC | AB34: 2.584 | AC34: 6.028 | AD34: 3.7 | AE34: 4067000064 | AF34: 22.151 | AG34: 5.158 | AH34: 2.3398495 | AI34: 0.0007 | AJ34: 204177358848 | AK34: -0.211 | AL34: 3.18 | AM34: 14.008108 | AN34: 210792628224
A35: 36 | B35: Abbott Laboratories | C35: Medical Devices | D35: 0.29229 | E35: 0.17122 | F35: 0.5685 | G35: 11264000000 | H35: 0.234 | I35: 0.20906 | J35: 12366000128 | K35: 19611000000 | L35: 8126875136 | M35: 118.95 | N35: 0.696 | O35: 1.826 | P35: 0.0774 | Q35: 53.112 | R35: 0.21862 | S35: 9692000256 | T35: 18396999680 | U35: 42308001792 | V35: 5.481 | W35: USD | X35: 23.815 | Y35: 1.251 | Z35: EQUITY | AA35: ABT | AB35: 5.885 | AC35: 20.136 | AD35: 4.76 | AE35: 1768290048 | AF35: 19.466 | AG35: 4.03 | AH35: 6.1106544 | AI35: 0.00728 | AJ35: 249001328640 | AK35: 0.705 | AL35: 2.03 | AM35: 24.989494 | AN35: 210338103296
A36: 37 | B36: Nike, Inc. | C36: Footwear & Accessories | D36: 0.17238002 | E36: 0.13322 | F36: 0.45981 | G36: 7169999872 | H36: 0.01 | I36: 0.15739 | J36: 7982000128 | K36: 20001000000 | L36: 4678624768 | M36: 133.7 | N36: 0.064 | O36: 3.068 | P36: 0.12352 | Q36: 85.252 | R36: 0.48263 | S36: 15102999552 | T36: 12723000320 | U36: 46306000896 | V36: 9.551 | W36: USD | X36: 29.3 | Y36: 2.128 | Z36: EQUITY | AA36: NKE | AB36: 4.736 | AC36: 27.473 | AD36: 4.82 | AE36: 1277810048 | AF36: 9.431 | AG36: 3.81 | AH36: 14.176652 | AI36: 0.012209999 | AJ36: 219285979136 | AK36: 0.069 | AL36: 2.89 | AM36: 27.738588 | AN36: 211623018496
A37: 38 | B37: Danaher Corporation | C37: Diagnostics & Research | D37: 0.35092998 | E37: 0.21841 | F37: 0.61304003 | G37: 8358000128 | H37: 0.205 | I37: 0.27732 | J37: 10336000000 | K37: 18056000000 | L37: 5476250112 | M37: 287.53 | N37: 0.444 | O37: 1.431 | P37: 0.06407 | Q37: 51.513 | R37: 0.14942001 | S37: 2585999872 | T37: 23271999488 | U37: 29453000704 | V37: 3.615 | W37: USD | X37: 41.216 | Y37: 0.887 | Z37: EQUITY | AA37: DHR | AB37: 7.202 | AC37: 20.522 | AD37: 10.14 | AE37: 714577024 | AF37: 56.239 | AG37: 7.882 | AH37: 5.112644 | AI37: 0.11138 | AJ37: 212116029440 | AK37: 0.441 | AL37: 1.46 | AM37: 28.356014 | AN37: 205462323200
A38: 39 | B38: Adobe Inc. | C38: Software—Infrastructure | D38: 0.41681 | E38: 0.30548 | F38: 0.88185 | H38: 0.2 | I38: 0.36756 | J38: 6579333120 | K38: 13920000000 | M38: 431.62 | N38: -0.445 | O38: 1.248 | P38: 0.14076 | Q38: 31.581 | R38: 0.34368 | S38: 5798000128 | T38: 4672999936 | U38: 15784999936 | V38: 12.181 | W38: USD | X38: 33.092 | Y38: 1.107 | Z38: EQUITY | AA38: ADBE | AB38: 15.908 | AC38: 38.165 | AD38: 16.25 | AE38: 475800000 | AF38: 31.086 | AG38: 10.02 | AH38: 13.884707 | AI38: 0.00312 | AJ38: 251102642176 | AK38: -0.452 | AL38: 2.62 | AM38: 26.56123 | AN38: 205364789248
A39: 40 | B39: Merck & Company, Inc. | C39: Drug Manufacturers—General | D39: 0.40027002 | E39: 0.13681 | F39: 0.72669 | G39: 13084000256 | H39: 0.204 | I39: 0.33821 | J39: 21056999424 | K39: 34572000000 | L39: 9870499840 | M39: 81.34 | N39: 0.548 | O39: 1.309 | P39: 0.12133 | Q39: 73.728 | R39: 0.26036 | S39: 10042000384 | T39: 26441000960 | U39: 52607000576 | V39: 3.976 | W39: USD | X39: 20.787 | Y39: 0.869 | Z39: EQUITY | AA39: MRK | AB39: 4.011 | AC39: 10.02 | AD39: 7.2 | AE39: 2525939968 | AF39: 14.174 | AG39: 2.834 | AH39: 5.738676 | AI39: 0.00072999997 | AJ39: 210990940160 | AK39: 0.553 | AL39: 0.87 | AM39: 11.297222 | AN39: 205459947520
A40: 42 | B40: United Parcel Service, Inc. | C40: Integrated Freight & Logistics | D40: 0.11517999 | E40: 0.06832 | F40: 0.19872 | G40: 12936999936 | H40: 0.092 | I40: 0.08434 | J40: 10874000384 | K40: 11490000000 | L40: 3207875072 | M40: 215.35 | N40: 0.183 | O40: 1.476 | P40: 0.07768 | Q40: 212.383 | R40: 0.73033994 | S40: 10560000000 | T40: 25607000064 | U40: 94411997184 | V40: 12.15 | W40: USD | X40: 108.147 | Y40: 1.381 | Z40: EQUITY | AA40: UPS | AB40: 2.16 | AC40: 18.753 | AD40: 12.1 | AE40: 729158016 | AF40: 13.856 | AG40: 7.355 | AH40: 15.542004 | AI40: 7e-05 | AJ40: 203918901248 | AK40: 0.19 | AL40: 1.07 | AM40: 17.79752 | AN40: 187169734656
A41: 43 | B41: McDonald's Corporation | C41: Restaurants | D41: 0.50558996 | E41: 0.32490003 | F41: 0.54172003 | G41: 9141499904 | H41: 0.131 | I41: 0.42515 | J41: 11741200384 | K41: 12580200000 | L41: 5830362624 | M41: 241.58 | N41: 0.189 | O41: 1.778 | P41: 0.1159 | S41: 4709499904 | T41: 49353199616 | U41: 23222900736 | V41: 6.334 | W41: USD | X41: 31.117 | Y41: 1.72 | Z41: EQUITY | AA41: MCD | AB41: 9.105 | AC41: 18.009 | AD41: 10.14 | AE41: 747244992 | AF41: -7.595 | AG41: 9.7 | AI41: 0.00054000004 | AJ41: 211452067840 | AK41: 0.19 | AL41: 1.32 | AM41: 23.824457 | AN41: 180519452672
A42: 44 | B42: QUALCOMM Incorporated | C42: Semiconductors | D42: 0.35384 | E42: 0.27714002 | F42: 0.58164 | G42: 9418000384 | H42: 0.3 | I42: 0.30877 | J42: 12750999552 | K42: 19304000000 | L42: 8092250112 | M42: 157.97 | N42: 0.406 | O42: 1.648 | P42: 0.17321 | Q42: 138.975 | R42: 1.06739 | S42: 11310000128 | T42: 15749999616 | U42: 36036001792 | V42: 10.035 | W42: USD | X42: 31.933 | Y42: 1.25 | Z42: EQUITY | AA42: QCOM | AB42: 4.817 | AC42: 13.615 | AD42: 11.64 | AE42: 1120000000 | AF42: 8.844 | AG42: 7.87 | AH42: 17.861828 | AI42: 0.00154 | AJ42: 173602701312 | AK42: 0.385 | AL42: 0.68 | AM42: 13.571305 | AN42: 176926408704
A43: 45 | B43: Union Pacific Corporation | C43: Railroads | D43: 0.53068 | E43: 0.29916 | F43: 0.58462 | G43: 9031999488 | H43: 0.115 | I43: 0.42942002 | J43: 11571000320 | K43: 12747000000 | L43: 4763749888 | M43: 273.38 | N43: 0.299 | O43: 0.618 | P43: 0.092939995 | Q43: 222.357 | R43: 0.41923 | S43: 1006000000 | T43: 31488000000 | U43: 21803999232 | V43: 1.58 | W43: USD | X43: 33.35 | Y43: 0.475 | Z43: EQUITY | AA43: UNP | AB43: 8.469 | AC43: 15.96 | AD43: 11.38 | AE43: 642876032 | AF43: 21.597 | AG43: 9.335 | AH43: 12.658239 | AI43: 0.0023 | AJ43: 184668864512 | AK43: 0.24 | AL43: 1.52 | AM43: 24.022848 | AN43: 175749447680
A44: 47 | B44: Texas Instruments Incorporated | C44: Semiconductors | D44: 0.54072 | E44: 0.42352 | F44: 0.67466 | G44: 8755999744 | H44: 0.185 | I44: 0.49181998 | J44: 9918999552 | K44: 12376000000 | L44: 4189750016 | M44: 184.9 | N44: 0.26 | O44: 5.327 | P44: 0.25615 | Q44: 61.547 | R44: 0.68996 | S44: 9738999808 | T44: 8206000128 | U44: 18343999488 | V44: 10.545 | W44: USD | X44: 19.874 | Y44: 4.453 | Z44: EQUITY | AA44: TXN | AB44: 8.474 | AC44: 15.672 | AD44: 8.23 | AE44: 923526016 | AF44: 13.159 | AG44: 7.788 | AH44: 14.051219 | AI44: 0.0019200001 | AJ44: 155451523072 | AK44: 0.267 | AL44: 2.41 | AM44: 22.466587 | AN44: 170759962624
A45: 48 | B45: AT&T Inc. | C45: Telecom Services | D45: 0.30548 | E45: 0.0066500003 | F45: 0.52233005 | G45: 40784998400 | H45: -0.057 | I45: 0.18632 | J45: 53029998592 | K45: 91840000000 | L45: 41733750784 | M45: 23.84 | N45: 1.114 | O45: 0.701 | P45: 0.03724 | Q45: 115.572 | R45: 0.01368 | S45: 21334999040 | T45: 209535991808 | U45: 173596999680 | V45: 2.988 | W45: USD | X45: 24.238 | Y45: 0.511 | Z45: EQUITY | AA45: T | AB45: 2.263 | AC45: 7.409 | AD45: 3.21 | AE45: 7141000192 | AF45: 22.937 | AG45: 0.129 | AH45: 1.0393687 | AI45: 0.00093000004 | AJ45: 392898609152 | AK45: 1.102 | AL45: 2.17 | AM45: 7.426791 | AN45: 170241441792
A46: 49 | B46: Netflix, Inc. | C46: Entertainment | D46: 0.23376 | E46: 0.17639999 | F46: 0.43218 | G46: 658211968 | H46: 0.163 | I46: 0.22760001 | J46: 6693351936 | K46: 9719737000 | L46: 14542671872 | M46: 373.85 | N46: 0.833 | O46: 1.17 | P46: 0.10012 | Q46: 117.578 | R46: 0.39387 | S46: 7526681088 | T46: 18006607872 | U46: 28632967168 | V46: 16.992 | W46: USD | X46: 64.657 | Y46: 1.032 | Z46: EQUITY | AA46: NFLX | AB46: 9.511 | AC46: 40.687 | AD46: 13.09 | AE46: 442952000 | AF46: 34.574 | AG46: 11.091 | AH46: 10.813039 | AI46: 0.01497 | AJ46: 272331112448 | AK46: 0.834 | AL46: 1.29 | AM46: 28.559969 | AN46: 165597609984
A47: 51 | B47: NextEra Energy, Inc. | C47: Utilities—Regulated Electric | D47: 0.42733002 | E47: 0.14399 | F47: 0.50493 | G47: 7587999744 | H47: -0.087 | I47: 0.17243 | J47: 7016000000 | K47: 10707000000 | L47: -10548374528 | M47: 83.94 | N47: -0.633 | O47: 0.468 | P47: 0.01333 | Q47: 123.733 | R47: 0.03873 | S47: 692000000 | T47: 55340998656 | U47: 16417999872 | V47: 0.353 | W47: USD | X47: 8.369 | Y47: 0.222 | Z47: EQUITY | AA47: NEE | AB47: 14.071 | AC47: 32.927 | AD47: 2.74 | AE47: 1962140032 | AF47: 18.678 | AG47: 0.614 | AH47: 4.4940577 | AI47: 0.0015700001 | AJ47: 231018496000 | AK47: -0.636 | AL47: 3.6 | AM47: 30.635036 | AN47: 164702044160
A48: 52 | B48: Linde plc | C48: Specialty Chemicals | D48: 0.32959 | E48: 0.12425 | F48: 0.43028998 | G48: 9724999680 | H48: 0.141 | I48: 0.17907 | J48: 10149000192 | K48: 13250000000 | L48: 6089124864 | M48: 318.74 | N48: 0.364 | O48: 0.745 | P48: 0.04058 | Q48: 31.265 | R48: 0.08326 | S48: 2823000064 | T48: 14206999552 | U48: 30793000960 | V48: 5.522 | W48: USD | X48: 59.573 | Y48: 0.547 | Z48: EQUITY | AA48: LIN | AB48: 5.309 | AC48: 16.107 | AD48: 10.32 | AE48: 512555008 | AF48: 86.475 | AG48: 6.796 | AH48: 3.6859207 | AI48: 0.00206 | AJ48: 163466002432 | AK48: 0.332 | AM48: 30.885658 | AN48: 163371778048
A49: 53 | B49: Bristol-Myers Squibb Company | C49: Drug Manufacturers—General | D49: 0.44366002 | E49: 0.15078 | F49: 0.79871005 | G49: 16206999552 | H49: 0.083 | I49: 0.21174999 | J49: 20579000320 | K49: 37048000000 | L49: 13574250496 | M49: 73.28 | O49: 1.521 | P49: 0.0539 | Q49: 126.634 | R49: 0.18985 | S49: 17220999168 | T49: 45596000256 | U49: 46385000448 | V49: 7.901 | W49: USD | X49: 20.885 | Y49: 1.36 | Z49: EQUITY | AA49: BMY | AB49: 3.79 | AC49: 8.542 | AD49: 7.84 | AE49: 2219640064 | AF49: 16.765 | AG49: -2.42 | AH49: 4.3710113 | AI49: 0.00068999996 | AJ49: 175783591936 | AL49: 1.39 | AM49: 9.346938 | AN49: 162655223808
A50: 54 | B50: T-Mobile US, Inc. | C50: Telecom Services | D50: 0.32923 | E50: 0.03774 | F50: 0.56848997 | G50: 13916999680 | H50: 0.022 | I50: 0.12474 | J50: 26377000960 | K50: 45546000000 | L50: -246000000 | M50: 124.29 | N50: -0.428 | O50: 0.889 | P50: 0.03071 | Q50: 157.473 | R50: 0.04498 | S50: 6631000064 | T50: 108816998400 | U50: 80117997568 | V50: 5.308 | W50: USD | X50: 64.241 | Y50: 0.672 | Z50: EQUITY | AA50: TMUS | AB50: 3.197 | AC50: 9.711 | AD50: 3.24 | AE50: 1249049984 | AF50: 54.784 | AG50: 2.66 | AH50: 2.268728 | AI50: 0.52609 | AJ50: 256136003584 | AK50: -0.437 | AL50: 1.15 | AM50: 38.36111 | AN50: 155244429312
A51: 55 | B51: Raytheon Technologies Corporati | C51: Aerospace & Defense | D51: 0.17265 | E51: 0.051960003 | F51: 0.18392 | G51: 5288999936 | H51: 0.099 | I51: 0.10105 | J51: 11009000448 | K51: 9017000000 | L51: 4755749888 | M51: 102.43 | N51: 4.298 | O51: 1.23 | P51: 0.02508 | Q51: 44.935 | R51: 0.05017 | S51: 7475999744 | T51: 32789000192 | U51: 63763001344 | V51: 4.991 | W51: USD | X51: 42.422 | Y51: 0.818 | Z51: EQUITY | AA51: RTX | AB51: 2.538 | AC51: 14.698 | AD51: 4.99 | AE51: 1496780032 | AF51: 47.605 | AG51: 2.2 | AH51: 2.1516647 | AI51: 0.00112 | AJ51: 161814953984 | AK51: 4.277 | AL51: 0.94 | AM51: 20.527056 | AN51: 153315180544
A52: 56 | B52: Lowe's Companies, Inc. | C52: Home Improvement Retail | D52: 0.15587 | E52: 0.08625 | F52: 0.33075002 | G52: 8743000064 | H52: 0.027 | I52: 0.13666001 | J52: 14842000384 | K52: 29582000000 | L52: 5926374912 | M52: 212.92 | N52: 2 | O52: 1.193 | P52: 0.16221 | R52: 6.57829 | S52: 6706999808 | T52: 30948999168 | U52: 95221997568 | V52: 9.955 | W52: USD | X52: 133.88 | Y52: 0.342 | Z52: EQUITY | AA52: LOW | AB52: 2.093 | AC52: 13.427 | AD52: 12.9 | AE52: 673747008 | AF52: -2.297 | AG52: 11.467 | AI52: 0.00055 | AJ52: 199288258560 | AK52: 1.74 | AL52: 1.3 | AM52: 16.505426 | AN52: 143454208000
A53: 57 | B53: Advanced Micro Devices, Inc. | C53: Semiconductors | D53: 0.24674 | E53: 0.19240999 | F53: 0.48248002 | G53: 3520999936 | H53: 0.488 | I53: 0.22198 | J53: 4055000064 | K53: 7929000000 | L53: 3122749952 | M53: 119.67 | N53: -0.454 | O53: 2.024 | P53: 0.21327 | Q53: 9.764 | R53: 0.47428 | S53: 3608000000 | T53: 732000000 | U53: 16433999872 | V53: 3.008 | W53: USD | X53: 13.548 | Y53: 1.49 | Z53: EQUITY | AA53: AMD | AB53: 8.085 | AC53: 32.765 | AD53: 3.34 | AE53: 1207609984 | AF53: 5.888 | AG53: 3.242 | AH53: 20.324389 | AI53: 0.00426 | AJ53: 132861157376 | AK53: -0.453 | AL53: 1.55 | AM53: 35.82934 | AN53: 144514678784
A54: 58 | B54: Philip Morris International Inc | C54: Tobacco | D54: 0.45734 | E54: 0.29247 | F54: 0.68141 | G54: 11096999936 | H54: 0.091 | I54: 0.42511 | J54: 14060999680 | K54: 19125000000 | L54: 8760999936 | M54: 93.45 | N54: 0.049 | O54: 0.998 | P54: 0.2024 | S54: 4490999808 | T54: 29105000448 | U54: 30744999936 | V54: 2.885 | W54: USD | X54: 19.737 | Y54: 0.485 | Z54: EQUITY | AA54: PM | AB54: 5.741 | AC54: 12.554 | AD54: 6.43 | AE54: 1556829952 | AF54: -6.773 | AG54: 5.74 | AI54: 0.00191 | AJ54: 176517775360 | AK54: 0.052 | AL54: 1.44 | AM54: 14.533437 | AN54: 145485758464
A55: 60 | B55: Medtronic plc. | C55: Medical Devices | D55: 0.30181 | E55: 0.14793 | F55: 0.67627 | G55: 7161999872 | H55: 0.026 | I55: 0.21662001 | J55: 9596999680 | K55: 19762000000 | L55: 5072875008 | M55: 108.46 | N55: 1.694 | O55: 2.913 | P55: 0.045879997 | Q55: 49.125 | R55: 0.09233 | S55: 10668999680 | T55: 25622999040 | U55: 31797999616 | V55: 7.935 | W55: USD | X55: 23.628 | Y55: 2.071 | Z55: EQUITY | AA55: MDT | AB55: 4.958 | AC55: 16.428 | AD55: 6.16 | AE55: 1344560000 | AF55: 38.659 | AG55: 3.468 | AH55: 2.8055563 | AI55: 0.00234 | AJ55: 157658562560 | AK55: 1.681 | AL55: 1.63 | AM55: 17.607143 | AN55: 145830969344
A56: 61 | B56: CVS Health Corporation | C56: Healthcare Plans | D56: 0.06276 | E56: 0.02668 | F56: 0.17351 | G56: 17827000320 | H56: 0.1 | I56: 0.04679 | J56: 17824000000 | K56: 48248000000 | L56: 14704874496 | M56: 108.56 | N56: 0.29 | O56: 0.94 | P56: 0.03551 | Q56: 105.414 | R56: 0.10556 | S56: 12840999936 | T56: 78658002944 | U56: 283980988416 | V56: 9.721 | W56: USD | X56: 215.709 | Y56: 0.589 | Z56: EQUITY | AA56: CVS | AB56: 0.718 | AC56: 11.439 | AD56: 8.27 | AE56: 1320060032 | AF56: 56.251 | AG56: 5.729 | AH56: 1.9299213 | AI56: 0.00159 | AJ56: 203894095872 | AK56: 0.306 | AL56: 2.27 | AM56: 13.126964 | AN56: 143305719808
A57: 62 | B57: S&P Global Inc. | C57: Financial Data & Stock Exchanges | D57: 0.56767 | E57: 0.36446998 | F57: 0.73544997 | G57: 3598000128 | H57: 0.118 | I57: 0.54622 | J57: 4710000128 | K57: 6102000000 | L57: 2827249920 | M57: 413.47 | N57: 0.487 | O57: 2.309 | P57: 0.20552999 | Q57: 89.812 | R57: 0.73425 | S57: 6508000256 | T57: 4972000256 | U57: 8296999936 | V57: 26.993 | W57: USD | X57: 34.456 | Y57: 2.138 | Z57: EQUITY | AA57: SPGI | AB57: 11.443 | AC57: 20.158 | AD57: 14.63 | AE57: 241000000 | AF57: 7.656 | AG57: 11.599 | AH57: 54.00601 | AI57: 0.00169 | AJ57: 94945804288 | AK57: 0.487 | AL57: 3.61 | AM57: 28.261791 | AN57: 99646267392
A58: 63 | B58: ConocoPhillips | C58: Oil & Gas E&P | D58: 0.42903998 | E58: 0.17315 | F58: 0.49155998 | G58: 16995999744 | H58: 1.771 | I58: 0.27435 | J58: 20018999296 | K58: 22936000000 | L58: 10509124608 | M58: 107.5 | O58: 1.335 | P58: 0.10439 | Q58: 45.371 | R58: 0.21471001 | S58: 6591000064 | T58: 20600999936 | U58: 46660001792 | V58: 5.072 | W58: USD | X58: 35.237 | Y58: 1.103 | Z58: EQUITY | AA58: COP | AB58: 2.744 | AC58: 6.395 | AD58: 7.8 | AE58: 1318950016 | AF58: 33.447 | AG58: 3.687 | AH58: 3.2140403 | AI58: 0.00089 | AJ58: 128017498112 | AL58: -7.27 | AM58: 13.782051 | AN58: 141787119616
A59: 64 | B59: PayPal Holdings, Inc. | C59: Credit Services | D59: 0.21124001 | E59: 0.20086001 | F59: 0.47824 | G59: 5923999744 | H59: 0.132 | I59: 0.17388001 | J59: 5190000128 | K59: 10001000000 | L59: 3478000128 | M59: 113.76 | N59: 0.07 | O59: 1.298 | P59: 0.038110003 | Q59: 43.902 | R59: 0.24299999 | S59: 13292000256 | T59: 9697999872 | U59: 24568999936 | V59: 11.313 | W59: USD | X59: 20.932 | Y59: 0.337 | Z59: EQUITY | AA59: PYPL | AB59: 8.994 | AC59: 42.578 | AD59: 5.27 | AE59: 1174930048 | AF59: 18.816 | AG59: 4.159 | AH59: 6.0459185 | AI59: 0.0012899999 | AJ59: 220982149120 | AK59: 0.065 | AL59: 2.02 | AM59: 21.586338 | AN59: 133660041216
A60: 65 | B60: Honeywell International Inc. | C60: Conglomerates | D60: 0.25206 | E60: 0.15802 | F60: 0.3234 | G60: 6157000192 | H60: 0.087 | I60: 0.21779 | J60: 8730000384 | K60: 10468000000 | L60: 4935000064 | M60: 197.79 | N60: 0.682 | O60: 1.288 | P60: 0.073860005 | Q60: 122.846 | R60: 0.30444 | S60: 12135999488 | T60: 22261000192 | U60: 34635001856 | V60: 17.629 | W60: USD | X60: 49.784 | Y60: 0.967 | Z60: EQUITY | AA60: HON | AB60: 4.455 | AC60: 17.673 | AD60: 8.98 | AE60: 688422976 | AF60: 25.917 | AG60: 7.77 | AH60: 7.63167 | AI60: 0.00087 | AJ60: 154284408832 | AK60: 0.658 | AL60: 2.27 | AM60: 22.025614 | AN60: 136163172352
A61: 66 | B61: Amgen Inc. | C61: Drug Manufacturers—General | D61: 0.47642 | E61: 0.21767999 | F61: 0.75421995 | G61: 8606000128 | H61: 0.044 | I61: 0.34998 | J61: 12275999744 | K61: 19265000000 | L61: 7394749952 | M61: 238.79 | N61: -0.035 | O61: 1.643 | P61: 0.08696 | Q61: 457.332 | R61: 0.585 | S61: 12920999936 | T61: 37579001856 | U61: 25767000064 | V61: 22.939 | W61: USD | X61: 44.89 | Y61: 1.192 | Z61: EQUITY | AA61: AMGN | AB61: 6.068 | AC61: 12.738 | AD61: 17.95 | AE61: 563265984 | AF61: 14.543 | AG61: 9.701 | AH61: 16.419582 | AI61: 0.00214 | AJ61: 156366471168 | AK61: -0.068 | AL61: 2.28 | AM61: 13.303063 | AN61: 134502277120
A62: 67 | B62: Deere & Company | C62: Farm & Heavy Construction Machinery | D62: 0.20566 | E62: 0.13566 | F62: 0.27728 | G62: 7726000128 | H62: 0.16 | I62: 0.18414 | J62: 9040000000 | K62: 12188000000 | L62: 1230499968 | M62: 436.45 | N62: 0.724 | O62: 2.192 | P62: 0.06355 | Q62: 264.864 | R62: 0.3802 | S62: 7434999808 | T62: 48824999936 | U62: 43955998720 | V62: 24.186 | W62: USD | X62: 141.065 | Y62: 1.94 | Z62: EQUITY | AA62: DE | AB62: 3.673 | AC62: 17.86 | AD62: 25.12 | AE62: 307407008 | AF62: 59.828 | AG62: 18.99 | AH62: 7.2950797 | AI62: 0.00139 | AJ62: 161453981696 | AK62: 0.693 | AL62: 1.34 | AM62: 17.374601 | AN62: 134167789568
A63: 68 | B63: Intuit Inc. | C63: Software—Application | D63: 0.28012 | E63: 0.20277001 | F63: 0.82689005 | G63: 3350000128 | H63: 0.517 | I63: 0.24396999 | J63: 2889999872 | K63: 8000000000 | L63: 2693625088 | M63: 459.35 | N63: 0.093 | O63: 2.099 | P63: 0.12802 | Q63: 25.758 | R63: 0.27934 | S63: 3249999872 | T63: 2507000064 | U63: 10316999680 | V63: 11.477 | W63: USD | X63: 37.861 | Y63: 1.764 | Z63: EQUITY | AA63: INTU | AB63: 16.899 | AC63: 60.327 | AD63: 13.64 | AE63: 283167008 | AF63: 35.623 | AG63: 7.581 | AH63: 12.894759 | AI63: 0.02809 | AJ63: 174345699328 | AK63: 0.152 | AL63: 3.04 | AM63: 33.676685 | AN63: 130072764416
A64: 69 | B64: Applied Materials, Inc. | C64: Semiconductor Equipment & Materials | D64: 0.33174 | E64: 0.25530002 | F64: 0.47374 | G64: 5441999872 | H64: 0.306 | I64: 0.31465998 | J64: 7650999808 | K64: 10926000000 | L64: 3319124992 | M64: 137.06 | N64: 0.533 | O64: 2.539 | P64: 0.18829 | Q64: 46.975 | R64: 0.51593 | S64: 5458999808 | T64: 5752999936 | U64: 23062999040 | V64: 6.144 | W64: USD | X64: 25.344 | Y64: 1.673 | Z64: EQUITY | AA64: AMAT | AB64: 5.936 | AC64: 17.892 | AD64: 8.85 | AE64: 888513024 | AF64: 13.73 | AG64: 6.4 | AH64: 9.98252 | AI64: 0.00241 | AJ64: 136894029824 | AK64: 0.514 | AL64: 1.17 | AM64: 15.487004 | AN64: 121779593216
A65: 70 | B65: Anthem, Inc. | C65: Healthcare Plans | D65: 0.06538 | E65: 0.041220002 | F65: 0.25909 | G65: 10504999936 | H65: 0.15 | I65: 0.05925 | J65: 8753000448 | K65: 33823000000 | L65: 7365374976 | M65: 480.76 | N65: 6.046 | O65: 1.476 | P65: 0.05371 | Q65: 66.276 | R65: 0.15835 | S65: 33956999168 | T65: 23732000768 | U65: 133883002880 | V65: 139.905 | W65: USD | X65: 546.238 | Y65: 1.327 | Z65: EQUITY | AA65: ANTM | AB65: 0.755 | AC65: 11.545 | AD65: 28.65 | AE65: 242715008 | AF65: 147.158 | AG65: 22.228 | AH65: 3.2669647 | AI65: 0.0020299999 | AJ65: 101050580992 | AK65: 5.797 | AL65: 1.31 | AM65: 16.780455 | AN65: 116687667200
A66: 71 | B66: Lockheed Martin Corporation | C66: Aerospace & Defense | D66: 0.13439 | E66: 0.094189994 | F66: 0.13569 | G66: 9221000192 | H66: 0.041 | I66: 0.11665 | J66: 9009999872 | K66: 9097000000 | L66: 4841500160 | M66: 453.66 | N66: 0.171 | O66: 1.416 | P66: 0.09624 | Q66: 119.555 | R66: 0.74307 | S66: 3604000000 | T66: 13102000128 | U66: 67043999744 | V66: 13.234 | W66: USD | X66: 242.562 | Y66: 1.154 | Z66: EQUITY | AA66: LMT | AB66: 2.035 | AC66: 15.144 | AD66: 26.28 | AE66: 275785984 | AF66: 35.15 | AG66: 21.709 | AH66: 12.906401 | AI66: 0.00081 | AJ66: 136443199488 | AK66: 0.143 | AL66: 3.22 | AM66: 17.262556 | AN66: 125113073664
A67: 72 | B67: Caterpillar, Inc. | C67: Farm & Heavy Construction Machinery | D67: 0.18108 | E67: 0.12731 | F67: 0.29434 | G67: 7198000128 | H67: 0.228 | I67: 0.13494 | J67: 9230000128 | K67: 15003000000 | L67: 5983750144 | M67: 223.36 | N67: 1.764 | O67: 1.456 | P67: 0.05336 | Q67: 228.802 | R67: 0.40715998 | S67: 9253999616 | T67: 37788999680 | U67: 50971000832 | V67: 17.178 | W67: USD | X67: 93.697 | Y67: 0.892 | Z67: EQUITY | AA67: CAT | AB67: 2.713 | AC67: 14.98 | AD67: 10.9 | AE67: 540942016 | AF67: 30.807 | AG67: 9.348 | AH67: 7.2503004 | AI67: 0.00196 | AJ67: 138267869184 | AK67: 1.718 | AL67: 0.65 | AM67: 20.491743 | AN67: 120824807424
A68: 73 | B68: International Business Machines | C68: Information Technology Services | D68: 0.21030001 | E68: 0.06401 | F68: 0.48443002 | G68: 16112000000 | H68: 0.003 | I68: 0.11985 | J68: 15658999808 | K68: 35575000000 | L68: 12530875392 | M68: 131.35 | N68: -0.338 | O68: 0.836 | P68: 0.03739 | Q68: 263.801 | R68: 0.21405001 | S68: 8055000064 | T68: 58978000896 | U68: 74461003776 | V68: 8.982 | W68: USD | X68: 83.234 | Y68: 0.65 | Z68: EQUITY | AA68: IBM | AB68: 2.348 | AC68: 11.165 | AD68: 10.3 | AE68: 896320000 | AF68: 24.786 | AG68: 5.283 | AH68: 5.299363 | AI68: 0.00133 | AJ68: 174828388352 | AK68: -0.335 | AL68: 2.07 | AM68: 12.752427 | AN68: 117731639296
A69: 74 | B69: ServiceNow, Inc. | C69: Software—Application | D69: 0.12277 | E69: 0.03986 | F69: 0.7726 | G69: 2032599040 | H69: 0.312 | I69: 0.04336 | J69: 679244032 | K69: 3532371000 | L69: 2109631104 | M69: 561.87 | N69: 4.167 | O69: 1.131 | P69: 0.01745 | Q69: 63.016 | R69: 0.071040004 | S69: 3031000064 | T69: 2227000064 | U69: 5532484096 | V69: 15.232 | W69: USD | X69: 28.162 | Y69: 1.004 | Z69: EQUITY | AA69: NOW | AB69: 21.577 | AC69: 175.75 | AD69: 7.22 | AE69: 199000000 | AF69: 17.759 | AG69: 1.091 | AH69: 31.638603 | AI69: 0.0038400001 | AJ69: 119377043456 | AK69: 3.846 | AL69: 3.88 | AM69: 77.821335 | AN69: 111812132864
A70: 75 | B70: Prologis, Inc. | C70: REIT—Industrial | D70: 0.68964 | E70: 0.40218 | F70: 0.75181 | G70: 2883645952 | H70: 0.102 | I70: 0.36385 | J70: 3383100928 | K70: 3566001000 | L70: 4072106752 | M70: 157.33 | N70: 1.415 | O70: 0.848 | P70: 0.01978 | Q70: 47.759 | R70: 0.05886 | S70: 585070976 | T70: 17554874368 | U70: 4905615872 | V70: 0.791 | W70: USD | X70: 6.637 | Y70: 0.403 | Z70: EQUITY | AA70: PLD | AB70: 28.603 | AC70: 41.476 | AD70: 2.31 | AE70: 739326976 | AF70: 43.881 | AG70: 2.644 | AH70: 3.5853786 | AI70: 0.00504 | AJ70: 140316753920 | AK70: 1.39 | AL70: -11.62 | AM70: 68.10823 | AN70: 116318314496
A71: 77 | B71: BlackRock, Inc. | C71: Asset Management | D71: 0.41139 | E71: 0.30972 | F71: 0.50816 | G71: 5006000128 | H71: 0.156 | I71: 0.38963002 | J71: 7712000000 | K71: 8266000000 | L71: 5881375232 | M71: 741.04 | N71: 0.228 | O71: 1.427 | P71: 0.02727 | Q71: 21.949 | R71: 0.16974 | S71: 7157000192 | T71: 8421000192 | U71: 18745999360 | V71: 47.111 | W71: USD | X71: 122.998 | Y71: 0.625 | Z71: EQUITY | AA71: BLK | AB71: 7.583 | AC71: 18.433 | AD71: 42.25 | AE71: 151916992 | AF71: 242.236 | AG71: 37.607 | AH71: 3.0591655 | AI71: 0.01071 | AJ71: 142154465280 | AK71: 0.232 | AL71: 1.8 | AM71: 17.539408 | AN71: 112576561152
A72: 79 | B72: Boeing Company (The) | C72: Aerospace & Defense | D72: 0.02631 | E72: -0.06746 | F72: 0.08625 | G72: -3416000000 | H72: -0.033 | I72: -0.00811 | J72: 1639000064 | K72: 5372000000 | L72: -622875008 | M72: 188.95 | O72: 1.325 | P72: -0.00217 | S72: 16243999744 | T72: 59640999936 | U72: 62286000128 | V72: 27.863 | W72: USD | X72: 105.929 | Y72: 0.337 | Z72: EQUITY | AA72: BA | AB72: 2.683 | AC72: 101.952 | AD72: 4.76 | AE72: 587699008 | AF72: -24.58 | AG72: -14.511 | AI72: 0.00095 | AJ72: 167099318272 | AL72: -5.13 | AM72: 39.695377 | AN72: 111045722112
A73: 80 | B73: American Tower Corporation (REI | C73: REIT—Specialty | D73: 0.63285 | E73: 0.27445 | F73: 0.72116 | G73: 5273299968 | H73: 0.219 | I73: 0.39266 | J73: 5717300224 | K73: 5814300000 | L73: 5150612480 | M73: 240.69 | N73: 0.519 | O73: 0.773 | P73: 0.04348 | Q73: 434.983 | R73: 0.34478 | S73: 3277199872 | T73: 42142900224 | U73: 9034200064 | V73: 7.196 | W73: USD | X73: 20.135 | Y73: 0.668 | Z73: EQUITY | AA73: AMT | AB73: 19.03 | AC73: 30.07 | AD73: 5.46 | AE73: 455414016 | AF73: 11.882 | AG73: 5.507 | AH73: 20.256691 | AI73: 0.00306 | AJ73: 171920228352 | AK73: 0.557 | AL73: 2.96 | AM73: 44.082417 | AN73: 109613596672
A74: 81 | B74: Charter Communications, Inc. | C74: Entertainment | D74: 0.39200002 | E74: 0.08396 | F74: 0.44784 | G74: 16161999872 | H74: 0.092 | I74: 0.20658001 | J74: 20028999680 | K74: 21198000000 | L74: 6336875008 | M74: 558.26 | N74: 0.667 | O74: 0.286 | P74: 0.04602 | Q74: 417.43 | R74: 0.17694001 | S74: 466000000 | T74: 89856000000 | U74: 51093999616 | V74: 2.599 | W74: USD | X74: 270.338 | Y74: 0.254 | Z74: EQUITY | AA74: CHTR | AB74: 4.03 | AC74: 10.281 | AD74: 31.27 | AE74: 179291008 | AF74: 94.985 | AG74: 21.943 | AH74: 5.877349 | AI74: 0.3186 | AJ74: 205917814784 | AK74: 0.495 | AL74: 0.77 | AM74: 17.852894 | AN74: 100091002880
A75: 82 | B75: General Electric Company | C75: Specialty Industrial Machinery | D75: 0.09193 | E75: -0.00052 | F75: 0.18652001 | G75: 4557000192 | H75: -0.005 | I75: 0.022550002 | J75: 7228000256 | K75: 13514000000 | L75: 7676375040 | M75: 94.02 | O75: 1.796 | P75: 0.00451 | Q75: 169.123 | R75: 0.048779998 | S75: 20795000832 | T75: 65891999744 | U75: 78621999104 | V75: 18.937 | W75: USD | X75: 71.711 | Y75: 0.855 | Z75: EQUITY | AA75: GE | AB75: 1.98 | AC75: 21.542 | AD75: 3.97 | AE75: 1098140032 | AF75: 34.122 | AG75: -0.419 | AH75: 2.7554069 | AI75: 0.00242 | AJ75: 155708882944 | AL75: 6.96 | AM75: 23.68262 | AN75: 103247118336
A76: 83 | B76: Intuitive Surgical, Inc. | C76: Medical Instruments & Supplies | D76: 0.37273997 | E76: 0.29852 | F76: 0.69324994 | G76: 2089400064 | H76: 0.167 | I76: 0.31891 | J76: 2128400000 | K76: 3958500000 | L76: 1597325056 | M76: 286.87 | N76: 0.024 | O76: 5.083 | P76: 0.09207 | Q76: 0.728 | R76: 0.15919 | S76: 4230899968 | T76: 87000000 | U76: 5710099968 | V76: 11.827 | W76: USD | X76: 16.035 | Y76: 4.456 | Z76: EQUITY | AA76: ISRG | AB76: 17.62 | AC76: 47.272 | AD76: 5.57 | AE76: 357236992 | AF76: 31.945 | AG76: 4.638 | AH76: 8.980122 | AI76: 0.0101 | AJ76: 100614602752 | AK76: 0.042 | AL76: 4.15 | AM76: 51.50269 | AN76: 102480576512
A77: 84 | B77: Target Corporation | C77: Discount Stores | D77: 0.10804 | E77: 0.06562 | F77: 0.29459 | G77: 9077999616 | H77: 0.133 | I77: 0.08299 | J77: 11166000128 | K77: 27384000000 | L77: 5191249920 | M77: 218.61 | N77: 0.512 | O77: 0.967 | P77: 0.10204001 | Q77: 112.287 | R77: 0.50011003 | S77: 5765000192 | T77: 15498999808 | U77: 103348002816 | V77: 12.032 | W77: USD | X77: 209.08 | Y77: 0.247 | Z77: EQUITY | AA77: TGT | AB77: 0.982 | AC77: 9.091 | AD77: 13.38 | AE77: 479124000 | AF77: 28.702 | AG77: 13.587 | AH77: 7.6165423 | AI77: 0.0018099999 | AJ77: 101510184960 | AK77: 0.467 | AL77: 1.19 | AM77: 16.338566 | AN77: 104741298176
A78: 85 | B78: Starbucks Corporation | C78: Restaurants | D78: 0.21246 | E78: 0.14468999 | F78: 0.2874 | G78: 6024300032 | H78: 0.193 | I78: 0.16233 | J78: 6450699776 | K78: 8435400000 | L78: 4055624960 | M78: 87.45 | N78: 0.303 | O78: 0.813 | P78: 0.10477 | S78: 4056800000 | T78: 23747500032 | U78: 30361600000 | V78: 3.527 | W78: USD | X78: 25.812 | Y78: 0.584 | Z78: EQUITY | AA78: SBUX | AB78: 4.06 | AC78: 19.108 | AI78: 0.00174 | AJ78: 123259109376 | AK78: 0.311
A79: 86 | B79: Estee Lauder Companies, Inc. (T | C79: Household & Personal Products | D79: 0.23202999 | E79: 0.17829001 | F79: 0.76198 | G79: 3192000000 | H79: 0.233 | I79: 0.19226 | J79: 3955000064 | K79: 12391000000 | L79: 2091874944 | M79: 274.89 | N79: 0.324 | O79: 1.783 | P79: 0.10375 | Q79: 114.934 | R79: 0.53243 | S79: 4004000000 | T79: 7996000256 | U79: 17045000192 | V79: 11.124 | W79: USD | X79: 46.966 | Y79: 1.179 | Z79: EQUITY | AA79: EL | AB79: 8.138 | AC79: 35.074 | AD79: 8.53 | AE79: 231704992 | AF79: 16.861 | AG79: 8.248 | AH79: 16.303305 | AI79: 0.00737 | AJ79: 138718035968 | AK79: 0.323 | AL79: 3.39 | AM79: 32.22626 | AN79: 98945835008
A80: 87 | B80: Stryker Corporation | C80: Medical Devices | D80: 0.278 | E80: 0.11398 | F80: 0.65672994 | G80: 3500000000 | H80: 0.113 | I80: 0.21951 | J80: 4633999872 | K80: 9158000000 | L80: 3139749888 | M80: 266 | N80: -0.301 | O80: 2.126 | P80: 0.06885 | Q80: 92.093 | R80: 0.13989 | S80: 2639000064 | T80: 13057000448 | U80: 16668999680 | V80: 6.996 | W80: USD | X80: 44.259 | Y80: 1.226 | Z80: EQUITY | AA80: SYK | AB80: 6.911 | AC80: 24.861 | AD80: 10.17 | AE80: 377240000 | AF80: 37.584 | AG80: 4.968 | AH80: 7.07748 | AI80: 0.07317 | AJ80: 115203940352 | AK80: -0.295 | AL80: 2.29 | AM80: 26.15536 | AN80: 100345839616
A81: 88 | B81: Altria Group, Inc. | C81: Tobacco | D81: 0.5759 | E81: 0.13164 | F81: 0.65674 | G81: 8282999808 | H81: -0.026 | I81: 0.56380004 | J81: 12140000256 | K81: 13488000000 | L81: 6223374848 | M81: 53.62 | O81: 0.742 | P81: 0.17232001 | R81: 2.7119799 | S81: 2956999936 | T81: 28127000576 | U81: 21080000512 | V81: 1.61 | W81: USD | X81: 11.387 | Y81: 0.369 | Z81: EQUITY | AA81: MO | AB81: 5.593 | AC81: 9.712 | AD81: 4.83 | AE81: 1836989952 | AF81: -0.689 | AG81: 1.494 | AI81: 0.001 | AJ81: 117905457152 | AL81: 2.06 | AM81: 11.101449 | AN81: 98499395584
A82: 89 | B82: Booking Holdings Inc. Common St | C82: Travel Services | D82: 0.22017999 | E82: 0.04145 | F82: 0.74974996 | G82: 1964000000 | H82: 0.771 | I82: 0.17276 | J82: 2028999936 | K82: 4852000000 | L82: 2417874944 | M82: 2247.93 | N82: -0.046 | O82: 2.483 | P82: 0.04375 | Q82: 208.007 | R82: 0.07305 | S82: 12165000192 | T82: 11534000128 | U82: 9214999552 | V82: 296.249 | W82: USD | X82: 224.697 | Y82: 2.374 | Z82: EQUITY | AA82: BKNG | AB82: 10.916 | AC82: 49.575 | AD82: 100.38 | AE82: 41059800 | AF82: 135.035 | AG82: 9.25 | AH82: 16.647017 | AI82: 0.0023999999 | AJ82: 100587618304 | AK82: -0.04 | AL82: 0.27 | AM82: 22.394201 | AN82: 92299550720
A83: 90 | B83: Automatic Data Processing, Inc. | C83: Staffing & Employment Services | D83: 0.26082 | E83: 0.1748 | F83: 0.4493 | G83: 3120600064 | H83: 0.089 | I83: 0.22843 | J83: 4094000128 | K83: 6768100000 | L83: 3923987456 | M83: 219.04 | N83: 0.093 | O83: 1.041 | P83: 0.04133 | Q83: 68.328 | R83: 0.50117 | S83: 1764700032 | T83: 3450299904 | U83: 15696600064 | V83: 4.201 | W83: USD | X83: 37.143 | Y83: 0.092 | Z83: EQUITY | AA83: ADP | AB83: 5.671 | AC83: 21.742 | AD83: 7.47 | AE83: 421384000 | AF83: 12.679 | AG83: 6.32 | AH83: 17.27581 | AI83: 0.00102 | AJ83: 89013010432 | AK83: 0.072 | AL83: 2.58 | AM83: 29.322624 | AN83: 92299952128
A84: 91 | B84: Chubb Limited | C84: Insurance—Property & Casualty | D84: 0.20179 | E84: 0.21836 | F84: 0.28234 | G84: 11093000192 | H84: 0.14 | I84: 0.19464001 | J84: 8146999808 | K84: 7110000000 | L84: 12054750208 | M84: 217.78 | N84: 0.589 | O84: 0.342 | P84: 0.025390001 | Q84: 32.666 | R84: 0.15235 | S84: 5149000192 | T84: 19377000448 | U84: 40372998144 | V84: 11.954 | W84: USD | X84: 90.617 | Y84: 0.152 | Z84: EQUITY | AA84: CB | AB84: 2.567 | AC84: 12.719 | AD84: 14.45 | AE84: 430740992 | AF84: 137.668 | AG84: 19.67 | AH84: 1.5819217 | AI84: 0.00472 | AJ84: 103619739648 | AK84: 0.535 | AL84: 0.52 | AM84: 15.071281 | AN84: 93806772224
A85: 92 | B85: Zoetis Inc. | C85: Drug Manufacturers—Specialty & Generic | D85: 0.41242 | E85: 0.26196 | F85: 0.70486 | G85: 2212999936 | H85: 0.089 | I85: 0.36150002 | J85: 3207000064 | K85: 5481000000 | L85: 1407874944 | M85: 189.43 | N85: 0.159 | O85: 3.856 | P85: 0.12773 | Q85: 149.472 | R85: 0.48911998 | S85: 3496999936 | T85: 6792000000 | U85: 7776000000 | V85: 7.409 | W85: USD | X85: 16.393 | Y85: 2.577 | Z85: EQUITY | AA85: ZTS | AB85: 12.371 | AC85: 29.996 | AD85: 5.19 | AE85: 473126016 | AF85: 9.884 | AG85: 4.149 | AH85: 19.165318 | AI85: 0.00236 | AJ85: 96198688768 | AK85: 0.153 | AL85: 3.84 | AM85: 36.499035 | AN85: 89624256512
A86: 93 | B86: CME Group Inc. | C86: Financial Data & Stock Exchanges | D86: 0.64274 | E86: 0.52596 | F86: 1 | G86: 2394400000 | H86: 0.028 | I86: 0.55389 | J86: 2975899904 | K86: 4870300000 | L86: 1755924992 | M86: 247.72 | N86: 1.243 | O86: 1.008 | P86: 0.01026 | Q86: 14.81 | R86: 0.08975001 | S86: 1569699968 | T86: 4040499968 | U86: 4630000128 | V86: 4.368 | W86: USD | X86: 12.926 | Y86: 0.014 | Z86: EQUITY | AA86: CME | AB86: 18.054 | AC86: 28.089 | AD86: 7.33 | AE86: 359396000 | AF86: 76.084 | AG86: 6.78 | AH86: 3.255875 | AI86: 0.0044 | AJ86: 83590815744 | AK86: 1.25 | AL86: 6.61 | AM86: 33.79536 | AN86: 89030320128
A87: 94 | B87: Micron Technology, Inc. | C87: Semiconductors | D87: 0.50606 | E87: 0.24861999 | F87: 0.41531 | G87: 14439000064 | H87: 0.332 | I87: 0.29005 | J87: 14988999680 | K87: 10472000000 | L87: 1410875008 | M87: 78.1 | N87: 1.873 | O87: 3.101 | P87: 0.093430005 | Q87: 16.561 | R87: 0.17163 | S87: 9580000256 | T87: 7602999808 | U87: 29618999296 | V87: 8.555 | W87: USD | X87: 26.422 | Y87: 2.277 | Z87: EQUITY | AA87: MU | AB87: 2.795 | AC87: 5.523 | AD87: 11.51 | AE87: 1120169984 | AF87: 41.026 | AG87: 6.461 | AH87: 1.9036708 | AI87: 0.00193 | AJ87: 82790129664 | AK87: 1.872 | AL87: 0.45 | AM87: 6.7854037 | AN87: 87485276160
A88: 95 | B88: Analog Devices, Inc. | C88: Semiconductors | D88: 0.38916 | E88: 0.18999 | F88: 0.61831003 | G88: 2735068928 | H88: 0.533 | I88: 0.24232 | J88: 2848005888 | K88: 4525012000 | L88: 1119481856 | M88: 165.63 | N88: -0.855 | O88: 1.941 | P88: 0.03004 | Q88: 18.736 | R88: 0.055630002 | S88: 1977964032 | T88: 7118233088 | U88: 7318285824 | V88: 3.765 | W88: USD | X88: 18.413 | Y88: 1.241 | Z88: EQUITY | AA88: ADI | AB88: 12.89 | AC88: 33.122 | AD88: 8.51 | AE88: 525331008 | AF88: 72.321 | AG88: 3.46 | AH88: 2.2902062 | AI88: 0.0021 | AJ88: 94330912768 | AK88: -0.804 | AL88: 1.57 | AM88: 19.462984 | AN88: 87010574336
A89: 96 | B89: Mondelez International, Inc. | C89: Confectioners | D89: 0.21834 | E89: 0.15702 | F89: 0.3982 | G89: 4368999936 | H89: 0.078 | I89: 0.17813998 | J89: 6192000000 | K89: 10446000000 | L89: 3557750016 | M89: 61.52 | N89: 0.141 | O89: 0.733 | P89: 0.047280002 | Q89: 73.834 | R89: 0.16312 | S89: 3400999936 | T89: 20491999232 | U89: 28359999488 | V89: 2.438 | W89: USD | X89: 20.092 | Y89: 0.472 | Z89: EQUITY | AA89: MDLZ | AB89: 3.873 | AC89: 17.739 | AD89: 3.1 | AE89: 1394969984 | AF89: 19.857 | AG89: 3.141 | AH89: 3.0981517 | AI89: 0.00121 | AJ89: 109842898944 | AK89: 0.124 | AL89: 2.62 | AM89: 19.845161 | AN89: 85818556416
A90: 97 | B90: 3M Company | C90: Conglomerates | D90: 0.28613 | E90: 0.16764 | F90: 0.48024 | G90: 7964000256 | H90: 0.071 | I90: 0.23218 | J90: 10108000256 | K90: 15685000000 | L90: 5780874752 | M90: 150.46 | N90: 0 | O90: 1.705 | P90: 0.10945 | Q90: 130.812 | R90: 0.44799998 | S90: 5734000128 | T90: 19007000576 | U90: 35326001152 | V90: 9.95 | W90: USD | X90: 60.915 | Y90: 1.105 | Z90: EQUITY | AA90: MMM | AB90: 3.318 | AC90: 11.595 | AD90: 10.37 | AE90: 576252992 | AF90: 25.093 | AG90: 10.111 | AH90: 5.9960947 | AI90: 0.00119 | AJ90: 117201043456 | AK90: 0.003 | AL90: 2.37 | AM90: 14.509162 | AN90: 86703030272
A91: 99 | B91: Duke Energy Corporation (Holdin | C91: Utilities—Regulated Electric | D91: 0.47160998 | E91: 0.12795 | F91: 0.50060004 | G91: 9317000192 | H91: 0.034 | I91: 0.24066 | J91: 11422999552 | K91: 11596000000 | L91: -2255249920 | M91: 109.13 | N91: 0.031 | O91: 0.607 | P91: 0.02219 | Q91: 128.981 | R91: 0.05598 | S91: 552000000 | T91: 66090000384 | U91: 24220999680 | V91: 0.717 | W91: USD | X91: 31.765 | Y91: 0.256 | Z91: EQUITY | AA91: DUK | AB91: 6.151 | AC91: 13.043 | AD91: 5.47 | AE91: 769342976 | AF91: 61.567 | AG91: 3.91 | AH91: 1.7725405 | AI91: 0.00106 | AJ91: 148990803968 | AK91: 0.077 | AL91: 7.89 | AM91: 19.95064 | AN91: 83958398976
A92: 100 | B92: Marsh & McLennan Companies, Inc | C92: Insurance Brokers | D92: 0.27745 | E92: 0.15858 | F92: 0.43945998 | G92: 3516000000 | H92: 0.163 | I92: 0.23976 | J92: 5498999808 | K92: 8710000000 | L92: 3870500096 | M92: 166.11 | N92: 1.145 | O92: 1.242 | P92: 0.08808 | Q92: 117.287 | R92: 0.30993 | S92: 1752000000 | T92: 13162000384 | U92: 19819999232 | V92: 3.485 | W92: USD | X92: 39.093 | Y92: 1.146 | Z92: EQUITY | AA92: MMC | AB92: 4.437 | AC92: 15.993 | AD92: 6.73 | AE92: 504895008 | AF92: 19.257 | AG92: 5.29 | AH92: 8.625955 | AI92: 0.00122 | AJ92: 87947853824 | AK92: 1.147 | AL92: 2.11 | AM92: 24.68202 | AN92: 83868106752
A93: 102 | B93: CSX Corporation | C93: Railroads | D93: 0.54723 | E93: 0.3026 | F93: 0.54723 | G93: 4953999872 | H93: 0.243 | I93: 0.42918998 | J93: 6522999808 | K93: 5795000000 | L93: 2324624896 | M93: 36.92 | N93: 0.344 | O93: 1.718 | P93: 0.080369994 | Q93: 128.113 | R93: 0.27854002 | S93: 2179000064 | T93: 16874999808 | U93: 11920000000 | V93: 0.982 | W93: USD | X93: 5.254 | Y93: 1.545 | Z93: EQUITY | AA93: CSX | AB93: 8.2 | AC93: 14.985 | AD93: 1.78 | AE93: 2217979904 | AF93: 5.935 | AG93: 1.589 | AH93: 6.220724 | AI93: 0.00125 | AJ93: 97746296832 | AK93: 0.315 | AL93: 1.38 | AM93: 20.741571 | AN93: 81887813632
A94: 103 | B94: HCA Healthcare, Inc. | C94: Medical Care Facilities | D94: 0.21505 | E94: 0.11328 | F94: 0.3859 | G94: 2932999936 | H94: 0.148 | I94: 0.16699 | J94: 12469000192 | K94: 19230000000 | L94: -2138125056 | M94: 260.08 | N94: 2.59 | O94: 1.377 | P94: 0.12033 | Q94: 1866.301 | R94: 4.74392 | S94: 1139000064 | T94: 34059999232 | U94: 57981001728 | V94: 3.662 | W94: USD | X94: 175.292 | Y94: 0.995 | Z94: EQUITY | AA94: HCA | AB94: 2.007 | AC94: 9.334 | AD94: 18.7 | AE94: 311023008 | AF94: -2.217 | AG94: 19.533 | AI94: 0.22935 | AJ94: 116390903808 | AK94: 2.397 | AL94: 0.93 | AM94: 13.90802 | AN94: 80890863616
A95: 105 | B95: Lam Research Corporation | C95: Semiconductor Equipment & Materials | D95: 0.33055001 | E95: 0.27072 | F95: 0.46186 | G95: 3403175936 | H95: 0.355 | I95: 0.31061 | J95: 5207305216 | K95: 6805306000 | L95: 1959992704 | M95: 554.82 | N95: 0.479 | O95: 3.269 | P95: 0.19974001 | Q95: 85.83 | R95: 0.7589 | S95: 4611622912 | T95: 4995332096 | U95: 15753535488 | V95: 32.753 | W95: USD | X95: 110.375 | Y95: 2.349 | Z95: EQUITY | AA95: LRCX | AB95: 6.388 | AC95: 19.325 | AD95: 36.65 | AE95: 140799008 | AF95: 41.332 | AG95: 29.588 | AH95: 13.423497 | AI95: 0.00209 | AJ95: 100632379392 | AK95: 0.433 | AL95: 1.28 | AM95: 15.138335 | AN95: 78118109184
A96: 106 | B96: Cigna Corporation | C96: Healthcare Plans | D96: 0.0596 | E96: 0.049200002 | F96: 0.13713 | G96: 7209999872 | H96: 0.082 | I96: 0.04848 | J96: 10154999808 | K96: 24356000000 | L96: 9887625216 | M96: 243.58 | N96: 0.27 | O96: 0.7 | P96: 0.03285 | Q96: 73.536 | R96: 0.17627001 | S96: 4816999936 | T96: 34916999168 | U96: 170397007872 | V96: 14.534 | W96: USD | X96: 493.034 | Y96: 0.58 | Z96: EQUITY | AA96: CI | AB96: 0.624 | AC96: 10.478 | AD96: 22.46 | AE96: 331428000 | AF96: 143.075 | AG96: 24.027 | AH96: 1.7024637 | AI96: 0.01501 | AJ96: 106403020800 | AK96: 0.168 | AL96: 1.04 | AM96: 10.845058 | AN96: 80729235456
A97: 107 | B97: Intercontinental Exchange Inc. | C97: Financial Data & Stock Exchanges | D97: 0.60728 | E97: 0.43815 | F97: 1 | G97: 3196000000 | H97: 0.277 | I97: 0.48889 | J97: 4236999936 | K97: 6036000000 | L97: 2654249984 | M97: 135.26 | N97: 0.577 | O97: 1.006 | P97: 0.0153 | Q97: 66.88 | R97: 0.1503 | S97: 1319000064 | T97: 14499000320 | U97: 6976999936 | V97: 2.341 | W97: USD | X97: 12.404 | Y97: 0.024 | Z97: EQUITY | AA97: ICE | AB97: 12.733 | AC97: 20.967 | AD97: 5.55 | AE97: 563404032 | AF97: 38.361 | AG97: 5.421 | AH97: 3.5259767 | AI97: 0.01333 | AJ97: 88835620864 | AK97: 0.623 | AL97: 2.3 | AM97: 24.37117 | AN97: 76206022656
A98: 108 | B98: Crown Castle International Corp | C98: REIT—Specialty | D98: 0.56987 | E98: 0.17287001 | F98: 0.68565005 | G98: 2727000064 | H98: 0.108 | I98: 0.31909 | J98: 3612999936 | K98: 4347000000 | L98: 1362749952 | M98: 177.58 | N98: -0.299 | O98: 0.619 | P98: 0.0325 | Q98: 327.065 | R98: 0.13071 | S98: 292000000 | T98: 27008999424 | U98: 6339999744 | V98: 0.676 | W98: USD | X98: 14.676 | Y98: 0.458 | Z98: EQUITY | AA98: CCI | AB98: 16.202 | AC98: 28.43 | AD98: 3.31 | AE98: 432203008 | AF98: 19.704 | AG98: 2.871 | AH98: 9.012383 | AI98: 0.00489 | AJ98: 102717612032 | AK98: -0.305 | AL98: 4.34 | AM98: 53.649548 | AN98: 76750610432
A99: 109 | B99: Becton, Dickinson and Company | C99: Medical Instruments & Supplies | D99: 0.27864 | E99: 0.10331999 | F99: 0.47294 | G99: 4647000064 | H99: 0.073 | I99: 0.16639 | J99: 5641999872 | K99: 9576000000 | L99: 3650500096 | M99: 265.67 | N99: 1.406 | O99: 1.334 | P99: 0.03904 | Q99: 76.361 | R99: 0.088190004 | S99: 2295000064 | T99: 18080000000 | U99: 20248000512 | V99: 8.08 | W99: USD | X99: 69.993 | Y99: 0.723 | Z99: EQUITY | AA99: BDX | AB99: 4.479 | AC99: 16.073 | AD99: 13.68 | AE99: 285043008 | AF99: 83.223 | AG99: 6.85 | AH99: 3.1922667 | AI99: 0.00773 | AJ99: 90681180160 | AK99: 1.07 | AL99: 2.23 | AM99: 19.420322 | AN99: 75727380480
A100: 110 | B100: Freeport-McMoRan, Inc. | C100: Copper | D100: 0.45992002 | E100: 0.18849 | F100: 0.47332 | G100: 7714999808 | H100: 0.371 | I100: 0.36301 | J100: 10506999808 | K100: 10813000000 | L100: 6041874944 | M100: 51.93 | N100: 0.538 | O100: 2.517 | P100: 0.11497 | Q100: 42.439 | R100: 0.25739 | S100: 8182000128 | T100: 9768999936 | U100: 22844999680 | V100: 5.624 | W100: USD | X100: 15.583 | Y100: 1.684 | Z100: EQUITY | AA100: FCX | AB100: 3.455 | AC100: 7.512 | AD100: 3.55 | AE100: 1468470016 | AF100: 9.096 | AG100: 2.641 | AH100: 5.709103 | AI100: 0.00696 | AJ100: 78927970304 | AK100: 0.562 | AL100: 0.48 | AM100: 14.628169 | AN100: 76257648640
...

Sheet Clean_Data
A1: Sr.NO | B1: Company | C1: Industry | D1: Profit Margin | E1: Revenue Growth | F1: Current Price | G1: Current Ratio | H1: ROA | I1: Debt-to-Equity | J1: ROE | K1: Stock ticker | L1: EV/Revenue | M1: EV/EBITDA | N1: Price-to-Book | O1: PEG Ratio | P1: Forward P/E | Q1: Market Cap
A2: 1 | B2: Apple Inc. | C2: Consumer Electronics | D2: 0.26579002 | E2: 0.112 | F2: 174.72 | G2: 1.038 | H2: 0.19875 | I2: 170.714 | J2: 1.45567 | K2: AAPL | L2: 7.692 | M2: 22.697 | N2: 39.69105 | O2: 1.9 | P2: 26.634148 | Q2: 2851325607936
A3: 2 | B3: Microsoft Corporation | C3: Software—Infrastructure | D3: 0.38498002 | E3: 0.201 | F3: 303.68 | G3: 2.247 | H3: 0.15248999 | I3: 50.217 | J3: 0.49051 | K3: MSFT | L3: 12.069 | M3: 24.57 | N3: 14.233889 | O3: 1.87 | P3: 28.249302 | Q3: 2276649336832
A4: 3 | B4: Alphabet Inc. | C4: Internet Content & Information | D4: 0.29512 | E4: 0.324 | F4: 2830.43 | G4: 2.928 | H4: 0.14493 | I4: 11.329 | J4: 0.32069 | K4: GOOG | L4: 6.83 | M4: 19.307 | N4: 7.4476376 | O4: 1.22 | P4: 20.802807 | Q4: 1872632217600
A5: 4 | B5: Alphabet Inc. | C5: Internet Content & Information | D5: 0.29512 | E5: 0.324 | F5: 2833.46 | G5: 2.928 | H5: 0.14493 | I5: 11.329 | J5: 0.32069 | K5: GOOGL | L5: 6.838 | M5: 19.329 | N5: 7.4556103 | O5: 1.22 | P5: 20.841927 | Q5: 1871194226688
A6: 5 | B6: Amazon.com, Inc. | C6: Internet Retail | D6: 0.07101 | E6: 0.094 | F6: 3295.47 | G6: 1.136 | H6: 0.041929998 | I6: 100.864 | J6: 0.28806 | K6: AMZN | L6: 3.662 | M6: 29.071 | N6: 12.133496 | O6: 1.93 | P6: 45.236378 | Q6: 1676880117760
A7: 7 | B7: Tesla, Inc. | C7: Auto Manufacturers | D7: 0.07403 | E7: 0.568 | F7: 1010.64 | G7: 1.385 | H7: 0.055370003 | I7: 35.65 | J7: 0.15641 | K7: TSLA | L7: 24.547 | M7: 158.249 | N7: 37.507515 | O7: 2.52 | P7: 115.36987 | Q7: 1014945284096
A8: 8 | B8: NVIDIA Corporation | C8: Semiconductors | D8: 0.33806 | E8: 0.503 | F8: 276.92 | G8: 7.145 | H8: 0.15934 | I8: 49.697 | J8: 0.41939998 | K8: NVDA | L8: 29.858 | M8: 74.268 | N8: 29.112701 | O8: 1.71 | P8: 53.151634 | Q8: 690084642816
A9: 9 | B9: Meta Platforms, Inc. | C9: Internet Content & Information | D9: 0.33383998 | E9: 0.199 | F9: 221.82 | G9: 3.154 | H9: 0.17965001 | I9: 11.574 | J9: 0.31102 | K9: FB | L9: 4.586 | M9: 9.884 | N9: 4.6456394 | O9: 1.13 | P9: 15.588195 | Q9: 617050013696
A10: 10 | B10: UnitedHealth Group Incorporated | C10: Healthcare Plans | D10: 0.05523 | E10: 0.111 | F10: 513.03 | G10: 0.72 | H10: 0.0679 | I10: 62.929 | J10: 0.21985 | K10: UNH | L10: 1.754 | M10: 20.243 | N10: 6.876617 | O10: 1.84 | P10: 23.696537 | Q10: 483197845504
A11: 11 | B11: Visa Inc. | C11: Credit Services | D11: 0.51592 | E11: 0.241 | F11: 218.43 | G11: 1.395 | H11: 0.13035 | I11: 57.8 | J11: 0.35584998 | K11: V | L11: 18.203 | M11: 26.149
A12: 13 | B12: Johnson & Johnson | C12: Drug Manufacturers—General | D12: 0.22264 | E12: 0.104 | F12: 176.92 | G12: 1.348 | H12: 0.08842 | I12: 46.946 | J12: 0.30412 | K12: JNJ | L12: 4.467 | M12: 12.836 | N12: 6.6277065 | O12: 2.13 | P12: 17.044315 | Q12: 465759600640
A13: 14 | B13: Walmart Inc. | C13: Discount Stores | D13: 0.02387 | E13: 0.005 | F13: 143.45 | G13: 0.928 | H13: 0.0652 | I13: 62.382 | J13: 0.15539 | K13: WMT | L13: 0.743 | M13: 11.625 | N13: 4.8436656 | O13: 2.73 | P13: 21.346725 | Q13: 397913096192
A14: 15 | B14: Procter & Gamble Company (The) | C14: Household & Personal Products | D14: 0.1852 | E14: 0.061 | F14: 152.83 | G14: 0.672 | H14: 0.09514 | I14: 79.418 | J14: 0.31092 | K14: PG | L14: 4.965 | M14: 18.375 | N14: 8.172727 | O14: 3.98 | P14: 24.029875 | Q14: 369840979968
A15: 17 | B15: Exxon Mobil Corporation | C15: Oil & Gas Integrated | D15: 0.08259 | E15: 0.794 | F15: 85.2 | G15: 1.044 | H15: 0.049840003 | I15: 30.184 | J15: 0.13889 | K15: XOM | L15: 1.341 | M15: 8.103 | N15: 2.2461245 | O15: 13.11 | P15: 14.489795 | Q15: 363009933312
A16: 18 | B16: Mastercard Incorporated | C16: Credit Services | D16: 0.46001998 | E16: 0.266 | F16: 349.02 | G16: 1.288 | H16: 0.18013 | I16: 197.963 | J16: 1.2473301 | K16: MA | L16: 19.041 | M16: 32.706 | N16: 51.221012 | O16: 1.73 | P16: 33.145298 | Q16: 342932029440
A17: 19 | B17: Home Depot, Inc. (The) | C17: Home Improvement Retail | D17: 0.10791001 | E17: 0.098 | F17: 310.68 | G17: 1.132 | H17: 0.20454 | I17: 4373.43 | J17: 12.403111 | K17: HD | L17: 3.191 | M17: 18.343 | N17: 314.13547 | O17: 1.95 | P17: 19.189623 | Q17: 324424466432
A18: 20 | B18: Chevron Corporation | C18: Oil & Gas Integrated | D18: 0.10041001 | E18: 0.846 | F18: 169.31 | I18: 27.316 | J18: 0.11645 | K18: CVX | L18: 1.877 | M18: 8.748 | N18: 2.402276 | O18: -2.98 | P18: 17.803364 | Q18: 326377177088
A19: 21 | B19: Pfizer, Inc. | C19: Drug Manufacturers—General | D19: 0.28684 | E19: 1.344 | F19: 52.78 | G19: 1.385 | H19: 0.07777 | I19: 52.496 | J19: 0.27747 | K19: PFE | L19: 4.565 | M19: 11.592 | N19: 3.9125278 | O19: 0.01 | P19: 1.0677726 | Q19: 296247263232
A20: 22 | B20: AbbVie Inc. | C20: Drug Manufacturers—General | D20: 0.20538001 | E20: 0.074 | F20: 161.33 | I20: 594.66 | J20: 0.86594003 | K20: ABBV | L20: 5.808 | M20: 11.55 | N20: 21.047619 | O20: 2.38 | P20: 11.548318 | Q20: 285212082176
A21: 23 | B21: Eli Lilly and Company | C21: Drug Manufacturers—General | D21: 0.21515 | E21: 0.18 | F21: 289.02 | G21: 1.302 | H21: 0.11108 | I21: 215.45 | J21: 0.92237 | K21: LLY | L21: 8.955 | M21: 25.742 | N21: 33.7956 | O21: 5.2 | P21: 38.58745 | Q21: 276474200064
A22: 24 | B22: Coca-Cola Company (The) | C22: Beverages—Non-Alcoholic | D22: 0.23313999 | E22: 0.161 | F22: 61.53 | G22: 1.516 | H22: 0.07831 | I22: 172.826 | J22: 0.39722002 | K22: KO | L22: 7.651 | M22: 21.735 | N22: 11.982472 | O22: 2.72 | P22: 25.320986 | Q22: 265773907968
A23: 25 | B23: Broadcom Inc. | C23: Semiconductors | D23: 0.24539 | E23: 0.145 | F23: 628.87 | G23: 2.641 | H23: 0.07164 | I23: 161.163 | J23: 0.27556 | K23: AVGO | L23: 9.65 | M23: 17.99 | N23: 10.404692 | O23: 1.38 | P23: 17.444384 | Q23: 259644063744
A24: 26 | B24: Walt Disney Company (The) | C24: Entertainment | D24: 0.029590001 | E24: 0.26 | F24: 139.14 | G24: 1.083 | H24: 0.01077 | I24: 57.044 | J24: 0.025390001 | K24: DIS | L24: 5.03 | M24: 39.415 | N24: 2.8565562 | O24: 1.07 | P24: 27.498024 | Q24: 252909207552
A25: 27 | B25: Costco Wholesale Corporation | C25: Discount Stores | D25: 0.02543 | E25: 0.166 | F25: 555.71 | G25: 1.015 | H25: 0.07643 | I25: 53.237 | J25: 0.30563 | K25: COST | L25: 1.105 | M25: 23.838 | N25: 13.346864 | O25: 4.42 | P25: 39.80731 | Q25: 246419603456
A26: 28 | B26: Pepsico, Inc. | C26: Beverages—Non-Alcoholic | D26: 0.10617 | E26: 0.116 | F26: 165.24 | G26: 0.945 | H26: 0.079840004 | I26: 258.017 | J26: 0.55412996 | K26: PEP | L26: 3.574 | M26: 19.735 | N26: 14.388715 | O26: 2.85 | P26: 24.516321 | Q26: 228469096448
A27: 29 | B27: Cisco Systems, Inc. | C27: Communication Equipment | D27: 0.2244 | E27: 0.081 | F27: 54.97 | G27: 1.618 | H27: 0.09196 | I27: 25.032 | J27: 0.28190002 | K27: CSCO | L27: 4.227 | M27: 13.532 | N27: 5.4285994 | O27: 2.73 | P27: 14.9375 | Q27: 231842021376
A28: 30 | B28: Thermo Fisher Scientific Inc | C28: Diagnostics & Research | D28: 0.19701 | E28: 0.014 | F28: 574.29 | G28: 1.504 | H28: 0.07801 | I28: 85.097 | J28: 0.20476 | K28: TMO | L28: 6.206 | M28: 18.986 | N28: 5.845964 | O28: 2.23 | P28: 26.42844 | Q28: 226297823232
A29: 31 | B29: Oracle Corporation | C29: Software—Infrastructure | D29: 0.24788 | E29: 0.057 | F29: 81.73 | G29: 1.646 | H29: 0.092 | I29: 0 | K29: ORCL | L29: 6.288 | M29: 14.141 | O29: 1.91 | P29: 15.538023 | Q29: 218255884288
A30: 32 | B30: Accenture plc | C30: Information Technology Services | D30: 0.11533 | E30: 0.272 | F30: 327.71 | G30: 1.223 | H30: 0.12456001 | I30: 16.607 | J30: 0.31948 | K30: ACN | L30: 4.198 | M30: 24.983 | N30: 10.177329 | O30: 3.82 | P30: 31.359808 | Q30: 207279521792
A31: 33 | B31: Verizon Communications Inc. | C31: Telecom Services | D31: 0.16419001 | E31: 0.043 | F31: 51.28 | G31: 0.974 | H31: 0.06523 | I31: 228.038 | J31: 0.31167 | K31: VZ | L31: 2.918 | M31: 7.787 | N31: 2.755656 | O31: 2.62 | P31: 9.496296 | Q31: 215261134848
A32: 34 | B32: Salesforce.com Inc | C32: Software—Application | D32: 0.06961 | E32: 0.266 | F32: 211.03 | G32: 1.061 | H32: 0.00828 | I32: 25.131 | J32: 0.035720002 | K32: CRM | L32: 8.395 | M32: 61.594 | N32: 3.6395779 | O32: 5.29 | P32: 44.80467 | Q32: 207864545280
A33: 35 | B33: Comcast Corporation | C33: Entertainment | D33: 0.12731 | E33: 0.187 | F33: 47.13 | G33: 1.026 | H33: 0.04559 | I33: 104.661 | J33: 0.15312 | K33: CMCSA | L33: 2.868 | M33: 9.772 | N33: 2.2481396 | O33: 0.87 | P33: 12.772358 | Q33: 215333208064
A34: 36 | B34: Intel Corporation | C34: Semiconductors | D34: 0.25142 | E34: 0.028 | F34: 51.83 | G34: 2.102 | H34: 0.08586001 | I34: 40.508 | J34: 0.22522 | K34: INTC | L34: 2.584 | M34: 6.028 | N34: 2.3398495 | O34: 3.18 | P34: 14.008108 | Q34: 210792628224
A35: 37 | B35: Abbott Laboratories | C35: Medical Devices | D35: 0.17122 | E35: 0.234 | F35: 118.95 | G35: 1.826 | H35: 0.0774 | I35: 53.112 | J35: 0.21862 | K35: ABT | L35: 5.885 | M35: 20.136 | N35: 6.1106544 | O35: 2.03 | P35: 24.989494 | Q35: 210338103296
A36: 38 | B36: Nike, Inc. | C36: Footwear & Accessories | D36: 0.13322 | E36: 0.01 | F36: 133.7 | G36: 3.068 | H36: 0.12352 | I36: 85.252 | J36: 0.48263 | K36: NKE | L36: 4.736 | M36: 27.473 | N36: 14.176652 | O36: 2.89 | P36: 27.738588 | Q36: 211623018496
A37: 39 | B37: Danaher Corporation | C37: Diagnostics & Research | D37: 0.21841 | E37: 0.205 | F37: 287.53 | G37: 1.431 | H37: 0.06407 | I37: 51.513 | J37: 0.14942001 | K37: DHR | L37: 7.202 | M37: 20.522 | N37: 5.112644 | O37: 1.46 | P37: 28.356014 | Q37: 205462323200
A38: 40 | B38: Adobe Inc. | C38: Software—Infrastructure | D38: 0.30548 | E38: 0.2 | F38: 431.62 | G38: 1.248 | H38: 0.14076 | I38: 31.581 | J38: 0.34368 | K38: ADBE | L38: 15.908 | M38: 38.165 | N38: 13.884707 | O38: 2.62 | P38: 26.56123 | Q38: 205364789248
A39: 42 | B39: Merck & Company, Inc. | C39: Drug Manufacturers—General | D39: 0.13681 | E39: 0.204 | F39: 81.34 | G39: 1.309 | H39: 0.12133 | I39: 73.728 | J39: 0.26036 | K39: MRK | L39: 4.011 | M39: 10.02 | N39: 5.738676 | O39: 0.87 | P39: 11.297222 | Q39: 205459947520
A40: 43 | B40: United Parcel Service, Inc. | C40: Integrated Freight & Logistics | D40: 0.06832 | E40: 0.092 | F40: 215.35 | G40: 1.476 | H40: 0.07768 | I40: 212.383 | J40: 0.73033994 | K40: UPS | L40: 2.16 | M40: 18.753 | N40: 15.542004 | O40: 1.07 | P40: 17.79752 | Q40: 187169734656
A41: 44 | B41: McDonald's Corporation | C41: Restaurants | D41: 0.32490003 | E41: 0.131 | F41: 241.58 | G41: 1.778 | H41: 0.1159 | I41: 0 | K41: MCD | L41: 9.105 | M41: 18.009 | O41: 1.32 | P41: 23.824457 | Q41: 180519452672
A42: 45 | B42: QUALCOMM Incorporated | C42: Semiconductors | D42: 0.27714002 | E42: 0.3 | F42: 157.97 | G42: 1.648 | H42: 0.17321 | I42: 138.975 | J42: 1.06739 | K42: QCOM | L42: 4.817 | M42: 13.615 | N42: 17.861828 | O42: 0.68 | P42: 13.571305 | Q42: 176926408704
A43: 47 | B43: Union Pacific Corporation | C43: Railroads | D43: 0.29916 | E43: 0.115 | F43: 273.38 | G43: 0.618 | H43: 0.092939995 | I43: 222.357 | J43: 0.41923 | K43: UNP | L43: 8.469 | M43: 15.96 | N43: 12.658239 | O43: 1.52 | P43: 24.022848 | Q43: 175749447680
A44: 48 | B44: Texas Instruments Incorporated | C44: Semiconductors | D44: 0.42352 | E44: 0.185 | F44: 184.9 | G44: 5.327 | H44: 0.25615 | I44: 61.547 | J44: 0.68996 | K44: TXN | L44: 8.474 | M44: 15.672 | N44: 14.051219 | O44: 2.41 | P44: 22.466587 | Q44: 170759962624
A45: 49 | B45: AT&T Inc. | C45: Telecom Services | D45: 0.0066500003 | E45: -0.057 | F45: 23.84 | G45: 0.701 | H45: 0.03724 | I45: 115.572 | J45: 0.01368 | K45: T | L45: 2.263 | M45: 7.409 | N45: 1.0393687 | O45: 2.17 | P45: 7.426791 | Q45: 170241441792
A46: 51 | B46: Netflix, Inc. | C46: Entertainment | D46: 0.17639999 | E46: 0.163 | F46: 373.85 | G46: 1.17 | H46: 0.10012 | I46: 117.578 | J46: 0.39387 | K46: NFLX | L46: 9.511 | M46: 40.687 | N46: 10.813039 | O46: 1.29 | P46: 28.559969 | Q46: 165597609984
A47: 52 | B47: NextEra Energy, Inc. | C47: Utilities—Regulated Electric | D47: 0.14399 | E47: -0.087 | F47: 83.94 | G47: 0.468 | H47: 0.01333 | I47: 123.733 | J47: 0.03873 | K47: NEE | L47: 14.071 | M47: 32.927 | N47: 4.4940577 | O47: 3.6 | P47: 30.635036 | Q47: 164702044160
A48: 53 | B48: Linde plc | C48: Specialty Chemicals | D48: 0.12425 | E48: 0.141 | F48: 318.74 | G48: 0.745 | H48: 0.04058 | I48: 31.265 | J48: 0.08326 | K48: LIN | L48: 5.309 | M48: 16.107 | N48: 3.6859207 | P48: 30.885658 | Q48: 163371778048
A49: 54 | B49: Bristol-Myers Squibb Company | C49: Drug Manufacturers—General | D49: 0.15078 | E49: 0.083 | F49: 73.28 | G49: 1.521 | H49: 0.0539 | I49: 126.634 | J49: 0.18985 | K49: BMY | L49: 3.79 | M49: 8.542 | N49: 4.3710113 | O49: 1.39 | P49: 9.346938 | Q49: 162655223808
A50: 55 | B50: T-Mobile US, Inc. | C50: Telecom Services | D50: 0.03774 | E50: 0.022 | F50: 124.29 | G50: 0.889 | H50: 0.03071 | I50: 157.473 | J50: 0.04498 | K50: TMUS | L50: 3.197 | M50: 9.711 | N50: 2.268728 | O50: 1.15 | P50: 38.36111 | Q50: 155244429312
A51: 56 | B51: Raytheon Technologies Corporati | C51: Aerospace & Defense | D51: 0.051960003 | E51: 0.099 | F51: 102.43 | G51: 1.23 | H51: 0.02508 | I51: 44.935 | J51: 0.05017 | K51: RTX | L51: 2.538 | M51: 14.698 | N51: 2.1516647 | O51: 0.94 | P51: 20.527056 | Q51: 153315180544
A52: 57 | B52: Lowe's Companies, Inc. | C52: Home Improvement Retail | D52: 0.08625 | E52: 0.027 | F52: 212.92 | G52: 1.193 | H52: 0.16221 | I52: 0 | J52: 6.57829 | K52: LOW | L52: 2.093 | M52: 13.427 | O52: 1.3 | P52: 16.505426 | Q52: 143454208000
A53: 58 | B53: Advanced Micro Devices, Inc. | C53: Semiconductors | D53: 0.19240999 | E53: 0.488 | F53: 119.67 | G53: 2.024 | H53: 0.21327 | I53: 9.764 | J53: 0.47428 | K53: AMD | L53: 8.085 | M53: 32.765 | N53: 20.324389 | O53: 1.55 | P53: 35.82934 | Q53: 144514678784
A54: 60 | B54: Philip Morris International Inc | C54: Tobacco | D54: 0.29247 | E54: 0.091 | F54: 93.45 | G54: 0.998 | H54: 0.2024 | I54: 0 | K54: PM | L54: 5.741 | M54: 12.554 | O54: 1.44 | P54: 14.533437 | Q54: 145485758464
A55: 61 | B55: Medtronic plc. | C55: Medical Devices | D55: 0.14793 | E55: 0.026 | F55: 108.46 | G55: 2.913 | H55: 0.045879997 | I55: 49.125 | J55: 0.09233 | K55: MDT | L55: 4.958 | M55: 16.428 | N55: 2.8055563 | O55: 1.63 | P55: 17.607143 | Q55: 145830969344
A56: 62 | B56: CVS Health Corporation | C56: Healthcare Plans | D56: 0.02668 | E56: 0.1 | F56: 108.56 | G56: 0.94 | H56: 0.03551 | I56: 105.414 | J56: 0.10556 | K56: CVS | L56: 0.718 | M56: 11.439 | N56: 1.9299213 | O56: 2.27 | P56: 13.126964 | Q56: 143305719808
A57: 63 | B57: S&P Global Inc. | C57: Financial Data & Stock Exchanges | D57: 0.36446998 | E57: 0.118 | F57: 413.47 | G57: 2.309 | H57: 0.20552999 | I57: 89.812 | J57: 0.73425 | K57: SPGI | L57: 11.443 | M57: 20.158 | N57: 54.00601 | O57: 3.61 | P57: 28.261791 | Q57: 99646267392
A58: 64 | B58: ConocoPhillips | C58: Oil & Gas E&P | D58: 0.17315 | E58: 1.771 | F58: 107.5 | G58: 1.335 | H58: 0.10439 | I58: 45.371 | J58: 0.21471001 | K58: COP | L58: 2.744 | M58: 6.395 | N58: 3.2140403 | O58: -7.27 | P58: 13.782051 | Q58: 141787119616
A59: 65 | B59: PayPal Holdings, Inc. | C59: Credit Services | D59: 0.20086001 | E59: 0.132 | F59: 113.76 | G59: 1.298 | H59: 0.038110003 | I59: 43.902 | J59: 0.24299999 | K59: PYPL | L59: 8.994 | M59: 42.578 | N59: 6.0459185 | O59: 2.02 | P59: 21.586338 | Q59: 133660041216
A60: 66 | B60: Honeywell International Inc. | C60: Conglomerates | D60: 0.15802 | E60: 0.087 | F60: 197.79 | G60: 1.288 | H60: 0.073860005 | I60: 122.846 | J60: 0.30444 | K60: HON | L60: 4.455 | M60: 17.673 | N60: 7.63167 | O60: 2.27 | P60: 22.025614 | Q60: 136163172352
A61: 67 | B61: Amgen Inc. | C61: Drug Manufacturers—General | D61: 0.21767999 | E61: 0.044 | F61: 238.79 | G61: 1.643 | H61: 0.08696 | I61: 457.332 | J61: 0.585 | K61: AMGN | L61: 6.068 | M61: 12.738 | N61: 16.419582 | O61: 2.28 | P61: 13.303063 | Q61: 134502277120
A62: 68 | B62: Deere & Company | C62: Farm & Heavy Construction Machinery | D62: 0.13566 | E62: 0.16 | F62: 436.45 | G62: 2.192 | H62: 0.06355 | I62: 264.864 | J62: 0.3802 | K62: DE | L62: 3.673 | M62: 17.86 | N62: 7.2950797 | O62: 1.34 | P62: 17.374601 | Q62: 134167789568
A63: 69 | B63: Intuit Inc. | C63: Software—Application | D63: 0.20277001 | E63: 0.517 | F63: 459.35 | G63: 2.099 | H63: 0.12802 | I63: 25.758 | J63: 0.27934 | K63: INTU | L63: 16.899 | M63: 60.327 | N63: 12.894759 | O63: 3.04 | P63: 33.676685 | Q63: 130072764416
A64: 70 | B64: Applied Materials, Inc. | C64: Semiconductor Equipment & Materials | D64: 0.25530002 | E64: 0.306 | F64: 137.06 | G64: 2.539 | H64: 0.18829 | I64: 46.975 | J64: 0.51593 | K64: AMAT | L64: 5.936 | M64: 17.892 | N64: 9.98252 | O64: 1.17 | P64: 15.487004 | Q64: 121779593216
A65: 71 | B65: Anthem, Inc. | C65: Healthcare Plans | D65: 0.041220002 | E65: 0.15 | F65: 480.76 | G65: 1.476 | H65: 0.05371 | I65: 66.276 | J65: 0.15835 | K65: ANTM | L65: 0.755 | M65: 11.545 | N65: 3.2669647 | O65: 1.31 | P65: 16.780455 | Q65: 116687667200
A66: 72 | B66: Lockheed Martin Corporation | C66: Aerospace & Defense | D66: 0.094189994 | E66: 0.041 | F66: 453.66 | G66: 1.416 | H66: 0.09624 | I66: 119.555 | J66: 0.74307 | K66: LMT | L66: 2.035 | M66: 15.144 | N66: 12.906401 | O66: 3.22 | P66: 17.262556 | Q66: 125113073664
... A71: 79 | B71: BlackRock, Inc. | C71: Asset Management | D71: 0.30972 | E71: 0.156 | F71: 741.04 | G71: 1.427 | H71: 0.02727 | I71: 21.949 | J71: 0.16974 | K71: BLK | L71: 7.583 | M71: 18.433 | N71: 3.0591655 | O71: 1.8 | P71: 17.539408 | Q71: 112576561152
A72: 80 | B72: Boeing Company (The) | C72: Aerospace & Defense | D72: -0.06746 | E72: -0.033 | F72: 188.95 | G72: 1.325 | H72: -0.00217 | I72: 0 | K72: BA | L72: 2.683 | M72: 101.952 | O72: -5.13 | P72: 39.695377 | Q72: 111045722112
A73: 81 | B73: American Tower Corporation (REI | C73: REIT—Specialty | D73: 0.27445 | E73: 0.219 | F73: 240.69 | G73: 0.773 | H73: 0.04348 | I73: 434.983 | J73: 0.34478 | K73: AMT | L73: 19.03 | M73: 30.07 | N73: 20.256691 | O73: 2.96 | P73: 44.082417 | Q73: 109613596672
A74: 82 | B74: Charter Communications, Inc. | C74: Entertainment | D74: 0.08396 | E74: 0.092 | F74: 558.26 | G74: 0.286 | H74: 0.04602 | I74: 417.43 | J74: 0.17694001 | K74: CHTR | L74: 4.03 | M74: 10.281 | N74: 5.877349 | O74: 0.77 | P74: 17.852894 | Q74: 100091002880
A75: 83 | B75: General Electric Company | C75: Specialty Industrial Machinery | D75: -0.00052 | E75: -0.005 | F75: 94.02 | G75: 1.796 | H75: 0.00451 | I75: 169.123 | J75: 0.048779998 | K75: GE | L75: 1.98 | M75: 21.542 | N75: 2.7554069 | O75: 6.96 | P75: 23.68262 | Q75: 103247118336
A76: 84 | B76: Intuitive Surgical, Inc. | C76: Medical Instruments & Supplies | D76: 0.29852 | E76: 0.167 | F76: 286.87 | G76: 5.083 | H76: 0.09207 | I76: 0.728 | J76: 0.15919 | K76: ISRG | L76: 17.62 | M76: 47.272 | N76: 8.980122 | O76: 4.15 | P76: 51.50269 | Q76: 102480576512
A77: 85 | B77: Target Corporation | C77: Discount Stores | D77: 0.06562 | E77: 0.133 | F77: 218.61 | G77: 0.967 | H77: 0.10204001 | I77: 112.287 | J77: 0.50011003 | K77: TGT | L77: 0.982 | M77: 9.091 | N77: 7.6165423 | O77: 1.19 | P77: 16.338566 | Q77: 104741298176
A78: 86 | B78: Starbucks Corporation | C78: Restaurants | D78: 0.14468999 | E78: 0.193 | F78: 87.45 | G78: 0.813 | H78: 0.10477 | I78: 0 | K78: SBUX | L78: 4.06 | M78: 19.108
A79: 87 | B79: Estee Lauder Companies, Inc. (T | C79: Household & Personal Products | D79: 0.17829001 | E79: 0.233 | F79: 274.89 | G79: 1.783 | H79: 0.10375 | I79: 114.934 | J79: 0.53243 | K79: EL | L79: 8.138 | M79: 35.074 | N79: 16.303305 | O79: 3.39 | P79: 32.22626 | Q79: 98945835008
A80: 88 | B80: Stryker Corporation | C80: Medical Devices | D80: 0.11398 | E80: 0.113 | F80: 266 | G80: 2.126 | H80: 0.06885 | I80: 92.093 | J80: 0.13989 | K80: SYK | L80: 6.911 | M80: 24.861 | N80: 7.07748 | O80: 2.29 | P80: 26.15536 | Q80: 100345839616
A81: 89 | B81: Altria Group, Inc. | C81: Tobacco | D81: 0.13164 | E81: -0.026 | F81: 53.62 | G81: 0.742 | H81: 0.17232001 | I81: 0 | J81: 2.7119799 | K81: MO | L81: 5.593 | M81: 9.712 | O81: 2.06 | P81: 11.101449 | Q81: 98499395584
A82: 90 | B82: Booking Holdings Inc. Common St | C82: Travel Services | D82: 0.04145 | E82: 0.771 | F82: 2247.93 | G82: 2.483 | H82: 0.04375 | I82: 208.007 | J82: 0.07305 | K82: BKNG | L82: 10.916 | M82: 49.575 | N82: 16.647017 | O82: 0.27 | P82: 22.394201 | Q82: 92299550720
A83: 91 | B83: Automatic Data Processing, Inc. | C83: Staffing & Employment Services | D83: 0.1748 | E83: 0.089 | F83: 219.04 | G83: 1.041 | H83: 0.04133 | I83: 68.328 | J83: 0.50117 | K83: ADP | L83: 5.671 | M83: 21.742 | N83: 17.27581 | O83: 2.58 | P83: 29.322624 | Q83: 92299952128
A84: 92 | B84: Chubb Limited | C84: Insurance—Property & Casualty | D84: 0.21836 | E84: 0.14 | F84: 217.78 | G84: 0.342 | H84: 0.025390001 | I84: 32.666 | J84: 0.15235 | K84: CB | L84: 2.567 | M84: 12.719 | N84: 1.5819217 | O84: 0.52 | P84: 15.071281 | Q84: 93806772224
A85: 93 | B85: Zoetis Inc. | C85: Drug Manufacturers—Specialty & Generic | D85: 0.26196 | E85: 0.089 | F85: 189.43 | G85: 3.856 | H85: 0.12773 | I85: 149.472 | J85: 0.48911998 | K85: ZTS | L85: 12.371 | M85: 29.996 | N85: 19.165318 | O85: 3.84 | P85: 36.499035 | Q85: 89624256512
A86: 94 | B86: CME Group Inc. | C86: Financial Data & Stock Exchanges | D86: 0.52596 | E86: 0.028 | F86: 247.72 | G86: 1.008 | H86: 0.01026 | I86: 14.81 | J86: 0.08975001 | K86: CME | L86: 18.054 | M86: 28.089 | N86: 3.255875 | O86: 6.61 | P86: 33.79536 | Q86: 89030320128
A87: 95 | B87: Micron Technology, Inc. | C87: Semiconductors | D87: 0.24861999 | E87: 0.332 | F87: 78.1 | G87: 3.101 | H87: 0.093430005 | I87: 16.561 | J87: 0.17163 | K87: MU | L87: 2.795 | M87: 5.523 | N87: 1.9036708 | O87: 0.45 | P87: 6.7854037 | Q87: 87485276160
A88: 96 | B88: Analog Devices, Inc. | C88: Semiconductors | D88: 0.18999 | E88: 0.533 | F88: 165.63 | G88: 1.941 | H88: 0.03004 | I88: 18.736 | J88: 0.055630002 | K88: ADI | L88: 12.89 | M88: 33.122 | N88: 2.2902062 | O88: 1.57 | P88: 19.462984 | Q88: 87010574336
A89: 97 | B89: Mondelez International, Inc. | C89: Confectioners | D89: 0.15702 | E89: 0.078 | F89: 61.52 | G89: 0.733 | H89: 0.047280002 | I89: 73.834 | J89: 0.16312 | K89: MDLZ | L89: 3.873 | M89: 17.739 | N89: 3.0981517 | O89: 2.62 | P89: 19.845161 | Q89: 85818556416
A90: 99 | B90: 3M Company | C90: Conglomerates | D90: 0.16764 | E90: 0.071 | F90: 150.46 | G90: 1.705 | H90: 0.10945 | I90: 130.812 | J90: 0.44799998 | K90: MMM | L90: 3.318 | M90: 11.595 | N90: 5.9960947 | O90: 2.37 | P90: 14.509162 | Q90: 86703030272
A91: 100 | B91: Duke Energy Corporation (Holdin | C91: Utilities—Regulated Electric | D91: 0.12795 | E91: 0.034 | F91: 109.13 | G91: 0.607 | H91: 0.02219 | I91: 128.981 | J91: 0.05598 | K91: DUK | L91: 6.151 | M91: 13.043 | N91: 1.7725405 | O91: 7.89 | P91: 19.95064 | Q91: 83958398976
A92: 102 | B92: Marsh & McLennan Companies, Inc | C92: Insurance Brokers | D92: 0.15858 | E92: 0.163 | F92: 166.11 | G92: 1.242 | H92: 0.08808 | I92: 117.287 | J92: 0.30993 | K92: MMC | L92: 4.437 | M92: 15.993 | N92: 8.625955 | O92: 2.11 | P92: 24.68202 | Q92: 83868106752
A93: 103 | B93: CSX Corporation | C93: Railroads | D93: 0.3026 | E93: 0.243 | F93: 36.92 | G93: 1.718 | H93: 0.080369994 | I93: 128.113 | J93: 0.27854002 | K93: CSX | L93: 8.2 | M93: 14.985 | N93: 6.220724 | O93: 1.38 | P93: 20.741571 | Q93: 81887813632
A94: 105 | B94: HCA Healthcare, Inc. | C94: Medical Care Facilities | D94: 0.11328 | E94: 0.148 | F94: 260.08 | G94: 1.377 | H94: 0.12033 | I94: 1866.301 | J94: 4.74392 | K94: HCA | L94: 2.007 | M94: 9.334 | O94: 0.93 | P94: 13.90802 | Q94: 80890863616
A95: 106 | B95: Lam Research Corporation | C95: Semiconductor Equipment & Materials | D95: 0.27072 | E95: 0.355 | F95: 554.82 | G95: 3.269 | H95: 0.19974001 | I95: 85.83 | J95: 0.7589 | K95: LRCX | L95: 6.388 | M95: 19.325 | N95: 13.423497 | O95: 1.28 | P95: 15.138335 | Q95: 78118109184
A96: 107 | B96: Cigna Corporation | C96: Healthcare Plans | D96: 0.049200002 | E96: 0.082 | F96: 243.58 | G96: 0.7 | H96: 0.03285 | I96: 73.536 | J96: 0.17627001 | K96: CI | L96: 0.624 | M96: 10.478 | N96: 1.7024637 | O96: 1.04 | P96: 10.845058 | Q96: 80729235456
A97: 108 | B97: Intercontinental Exchange Inc. | C97: Financial Data & Stock Exchanges | D97: 0.43815 | E97: 0.277 | F97: 135.26 | G97: 1.006 | H97: 0.0153 | I97: 66.88 | J97: 0.1503 | K97: ICE | L97: 12.733 | M97: 20.967 | N97: 3.5259767 | O97: 2.3 | P97: 24.37117 | Q97: 76206022656
A98: 109 | B98: Crown Castle International Corp | C98: REIT—Specialty | D98: 0.17287001 | E98: 0.108 | F98: 177.58 | G98: 0.619 | H98: 0.0325 | I98: 327.065 | J98: 0.13071 | K98: CCI | L98: 16.202 | M98: 28.43 | N98: 9.012383 | O98: 4.34 | P98: 53.649548 | Q98: 76750610432
A99: 110 | B99: Becton, Dickinson and Company | C99: Medical Instruments & Supplies | D99: 0.10331999 | E99: 0.073 | F99: 265.67 | G99: 1.334 | H99: 0.03904 | I99: 76.361 | J99: 0.088190004 | K99: BDX | L99: 4.479 | M99: 16.073 | N99: 3.1922667 | O99: 2.23 | P99: 19.420322 | Q99: 75727380480
A100: 111 | B100: Freeport-McMoRan, Inc. | C100: Copper | D100: 0.18849 | E100: 0.371 | F100: 51.93 | G100: 2.517 | H100: 0.11497 | I100: 42.439 | J100: 0.25739 | K100: FCX | L100: 3.455 | M100: 7.512 | N100: 5.709103 | O100: 0.48 | P100: 14.628169 | Q100: 76257648640
A101: 112 | B101: Gilead Sciences, Inc. | C101: Drug Manufacturers—General | D101: 0.26905 | E101: 0.128 | F101: 58.91 | G101: 1.366 | H101: 0.12683 | I101: 128.946 | J101: 0.37846002 | K101: GILD | L101: 4.063 | M101: 7.48 | N101: 3.4434183 | O101: 6.77 | P101: 8.663235 | Q101: 73895526400
A102: 113 | B102: Southern Company (The) | C102: Utilities—Regulated Electric | D102: 0.10353 | E102: 0.127 | F102: 70.93 | G102: 0.821 | H102: 0.020380002 | I102: 170.415 | J102: 0.07048 | K102: SO | L102: 5.626 | M102: 16.143 | N102: 2.6202438 | O102: 3.18 | P102: 20.036724 | Q102: 75171610624
A103: 114 | B103: Moderna, Inc. | C103: Biotechnology | D103: 0.5968 | E103: 30.65 | F103: 165.92 | G103: 1.348 | H103: 0.372 | I103: 5.758 | J103: 1.09609 | K103: MRNA | L103: 7.283 | M103: 11.087 | N103: 6.637331 | O103: 0.54 | P103: 6.268228 | Q103: 67272261632
A104: 115 | B104: Regeneron Pharmaceuticals, Inc. | C104: Biotechnology | D104: 0.50245 | E104: 1.044 | F104: 680.03 | G104: 3.564 | H104: 0.26253 | I104: 14.384 | J104: 0.54207003 | K104: REGN | L104: 3.922 | M104: 6.828 | N104: 4.1586456 | O104: 0.67 | P104: 14.223594 | Q104: 73132466176
...

Sheet Industry_Benchmark
A1: Row Labels | B1: Average of Profit Margin | C1: Average of Revenue Growth | D1: Average of Current Ratio | E1: Average of ROA | F1: Average of Debt-to-Equity | G1: Average of ROE
A2: Aerospace & Defense | B2: 0.086845711 | C2: -0.0055714286 | D2: 1.9 | E2: 0.055819999 | F2: 56.095714 | G2: 0.332018
A3: Agricultural Inputs | B3: 0.10668001 | C3: 0.273 | D3: 1.812 | E3: 0.013890001 | F3: 9.9 | G3: 0.071609996
A4: Apparel Retail | B4: 0.05846 | C4: 0.239 | D4: 1.287 | E4: 0.07801 | F4: 198.942 | G4: 0.44426
A5: Asset Management | B5: 0.30562332 | C5: 0.156 | D5: 2.0716667 | E5: 0.081486663 | F5: 31.016667 | G5: 0.32167
A6: Auto Manufacturers | B6: 0.094826665 | C6: 0.17033333 | D6: 1.2296667 | E6: 0.036796667 | F6: 163.52167 | G6: 0.25986001
A7: Beverages—Non-Alcoholic | B7: 0.20897 | C7: 0.13633333 | D7: 2.3876667 | E7: 0.10935333 | F7: 143.72033 | G7: 0.41078666
A8: Beverages—Wineries & Distilleries | B8: -0.0061000003 | C8: -0.048 | D8: 1.502 | E8: 0.06876 | F8: 90.09 | G8: -0.0011100001
A9: Biotechnology | B9: 0.46816001 | C9: 10.661333 | D9: 3.179 | E9: 0.25766333 | F9: 9.7806667 | G9: 0.62818334
A10: Building Products & Equipment | B10: 0.08071999 | C10: 0.117 | D10: 1.721 | E10: 0.06261 | F10: 145.94 | G10: 0.24882999
A11: Chemicals | B11: 0.11325 | C11: 0.528 | D11: 1.594 | E11: 0.07396 | F11: 97.457 | G11: 0.39372003
A12: Communication Equipment | B12: 0.1895 | C12: 0.1045 | D12: 1.4995 | E12: 0.099320003 | F12: 12.516 | G12: 0.28190002
A13: Computer Hardware | B13: 0.19272 | C13: 0.165 | D13: 2.913 | E13: 0.103835 | F13: 0.797 | G13: 0.22579001
... A83: Grand Total | B83: 0.16991376 | C83: 0.35693805 | D83: 1.5702377 | E83: 0.079556592 | F83: 139.95073 | G83: 0.51881474

Sheet Company_Scoring
A1: Company | B1: Stock ticker | C1: Industry | D1: Profit Margin | E1: Industry Avg Profit Margin | F1: Profit Margin Difference | G1: Profit Score | H1: Revenue Growth | I1: Industry Avg Revenue Growth | J1: Revenue Growth Difference | K1: Growth Score | L1: Current Ratio | M1: Industry Avg Current Ratio | N1: Current Ratio Difference | O1: Liquidity Score | P1: ROA | Q1: Industry Avg ROA | R1: ROA Difference | S1: ROA Score | T1: Debt-to-Equity | U1: Industry Avg Debt-to-Equity | V1: Debt Difference | W1: Leverage Score | X1: ROE | Y1: Industry Avg ROE | Z1: ROE Difference | AA1: ROE Score | AB1: Financial Health Score | AC1: Financial Health % | AD1: Financial Health Rating
A2: Verizon Communications Inc. | B2: VZ | C2: Telecom Services | D2: 0.16419001 | E2: =_xlfn.XLOOKUP(C2,Industry_Benchmark!$A$2:$A$82,Industry_Benchmark!$B$2:$B$82,"") -> 0.06952667 | F2: =D2-E2 -> 0.09466334 | G2: =IF(F2>0,1,0) -> 1 | H2: 0.043 | I2: =_xlfn.XLOOKUP(C2,Industry_Benchmark!$A$2:$A$82,Industry_Benchmark!$C$2:$C$82,"") -> 0.0026666667 | J2: =H2-I2 -> 0.040333333 | K2: =IF(J2>0,1,0) -> 1 | L2: 0.974 | M2: =_xlfn.XLOOKUP(C2,Industry_Benchmark!$A$2:$A$82,Industry_Benchmark!$D$2:$D$82,"") -> 0.85466667 | N2: =L2-M2 -> 0.11933333 | O2: =IF(N2>0,1,0) -> 1 | P2: 0.06523 | Q2: =_xlfn.XLOOKUP(C2,Industry_Benchmark!$A$2:$A$82,Industry_Benchmark!$E$2:$E$82,"") -> 0.044393333 | R2: =P2-Q2 -> 0.020836667 | S2: =IF(R2>0,1,0) -> 1 | T2: 228.038 | U2: =_xlfn.XLOOKUP(C2,Industry_Benchmark!$A$2:$A$82,Industry_Benchmark!$F$2:$F$82,"") -> 167.02767 | V2: =T2-U2 -> 61.010333 | W2: =IF(V2>0,1,0) -> 1 | X2: 0.31167 | Y2: =_xlfn.XLOOKUP(C2,Industry_Benchmark!$A$2:$A$82,Industry_Benchmark!$G$2:$G$82,"") -> 0.12344333 | Z2: =X2-Y2 -> 0.18822667 | AA2: =IF(Z2>0,1,0) -> 1 | AB2: =SUM(G2,K2,O2,S2,W2,AA2) -> 6 | AC2: =AB2/6 -> 1 | AD2: {=_xlfn.IFS( AB2=6,"Excellent", AB2=5,"Strong", AB2=4,"Good", AB2=3,"Average", AB2<=2,"Weak" )} -> Excellent
A3: Illinois Tool Works Inc. | B3: ITW | C3: Specialty Industrial Machinery | D3: 0.19135 | E3: =_xlfn.XLOOKUP(C3,Industry_Benchmark!$A$2:$A$82,Industry_Benchmark!$B$2:$B$82,"") -> 0.12041 | F3: =D3-E3 -> 0.070939999 | G3: =IF(F3>0,1,0) -> 1 | H3: 0.075 | I3: =_xlfn.XLOOKUP(C3,Industry_Benchmark!$A$2:$A$82,Industry_Benchmark!$C$2:$C$82,"") -> 0.070857143 | J3: =H3-I3 -> 0.0041428571 | K3: =IF(J3>0,1,0) -> 1 | L3: 2.195 | M3: =_xlfn.XLOOKUP(C3,Industry_Benchmark!$A$2:$A$82,Industry_Benchmark!$D$2:$D$82,"") -> 1.469 | N3: =L3-M3 -> 0.726 | O3: =IF(N3>0,1,0) -> 1 | P3: 0.14562 | Q3: =_xlfn.XLOOKUP(C3,Industry_Benchmark!$A$2:$A$82,Industry_Benchmark!$E$2:$E$82,"") -> 0.066908572 | R3: =P3-Q3 -> 0.078711428 | S3: =IF(R3>0,1,0) -> 1 | T3: 216.175 | U3: =_xlfn.XLOOKUP(C3,Industry_Benchmark!$A$2:$A$82,Industry_Benchmark!$F$2:$F$82,"") -> 107.70214 | V3: =T3-U3 -> 108.47286 | W3: =IF(V3>0,1,0) -> 1 | X3: 0.8811 | Y3: =_xlfn.XLOOKUP(C3,Industry_Benchmark!$A$2:$A$82,Industry_Benchmark!$G$2:$G$82,"") -> 0.26455857 | Z3: =X3-Y3 -> 0.61654143 | AA3: =IF(Z3>0,1,0) -> 1 | AB3: =SUM(G3,K3,O3,S3,W3,AA3) -> 6 | AC3: =AB3/6 -> 1 | AD3: {=_xlfn.IFS( AB3=6,"Excellent", AB3=5,"Strong", AB3=4,"Good", AB3=3,"Average", AB3<=2,"Weak" )} -> Excellent
A4: Public Storage | B4: PSA | C4: REIT—Industrial | D4: 0.50629 | E4: =_xlfn.XLOOKUP(C4,Industry_Benchmark!$A$2:$A$82,Industry_Benchmark!$B$2:$B$82,"") -> 0.454235 | F4: =D4-E4 -> 0.052055 | G4: =IF(F4>0,1,0) -> 1 | H4: 0.228 | I4: =_xlfn.XLOOKUP(C4,Industry_Benchmark!$A$2:$A$82,Industry_Benchmark!$C$2:$C$82,"") -> 0.165 | J4: =H4-I4 -> 0.063 | K4: =IF(J4>0,1,0) -> 1 | L4: 2.075 | M4: =_xlfn.XLOOKUP(C4,Industry_Benchmark!$A$2:$A$82,Industry_Benchmark!$D$2:$D$82,"") -> 1.4615 | N4: =L4-M4 -> 0.6135 | O4: =IF(N4>0,1,0) -> 1 | P4: 0.0798 | Q4: =_xlfn.XLOOKUP(C4,Industry_Benchmark!$A$2:$A$82,Industry_Benchmark!$E$2:$E$82,"") -> 0.04979 | R4: =P4-Q4 -> 0.03001 | S4: =IF(R4>0,1,0) -> 1 | T4: 63.882 | U4: =_xlfn.XLOOKUP(C4,Industry_Benchmark!$A$2:$A$82,Industry_Benchmark!$F$2:$F$82,"") -> 55.8205 | V4: =T4-U4 -> 8.0615 | W4: =IF(V4>0,1,0) -> 1 | X4: 0.19327 | Y4: =_xlfn.XLOOKUP(C4,Industry_Benchmark!$A$2:$A$82,Industry_Benchmark!$G$2:$G$82,"") -> 0.126065 | Z4: =X4-Y4 -> 0.067205 | AA4: =IF(Z4>0,1,0) -> 1 | AB4: =SUM(G4,K4,O4,S4,W4,AA4) -> 6 | AC4: =AB4/6 -> 1 | AD4: {=_xlfn.IFS( AB4=6,"Excellent", AB4=5,"Strong", AB4=4,"Good", AB4=3,"Average", AB4<=2,"Weak" )} -> Excellent
A5: Microsoft Corporation | B5: MSFT | C5: Software—Infrastructure | D5: 0.38498002 | E5: =_xlfn.XLOOKUP(C5,Industry_Benchmark!$A$2:$A$82,Industry_Benchmark!$B$2:$B$82,"") -> 0.263494 | F5: =D5-E5 -> 0.12148602 | G5: =IF(F5>0,1,0) -> 1 | H5: 0.201 | I5: =_xlfn.XLOOKUP(C5,Industry_Benchmark!$A$2:$A$82,Industry_Benchmark!$C$2:$C$82,"") -> 0.2198 | J5: =H5-I5 -> -0.0188 | K5: =IF(J5>0,1,0) -> 0 | L5: 2.247 | M5: =_xlfn.XLOOKUP(C5,Industry_Benchmark!$A$2:$A$82,Industry_Benchmark!$D$2:$D$82,"") -> 1.6274 | N5: =L5-M5 -> 0.6196 | O5: =IF(N5>0,1,0) -> 1 | P5: 0.15248999 | Q5: =_xlfn.XLOOKUP(C5,Industry_Benchmark!$A$2:$A$82,Industry_Benchmark!$E$2:$E$82,"") -> 0.107218 | R5: =P5-Q5 -> 0.045271992 | S5: =IF(R5>0,1,0) -> 1 | T5: 50.217 | U5: =_xlfn.XLOOKUP(C5,Industry_Benchmark!$A$2:$A$82,Industry_Benchmark!$F$2:$F$82,"") -> 37.3778 | V5: =T5-U5 -> 12.8392 | W5: =IF(V5>0,1,0) -> 1 | X5: 0.49051 | Y5: =_xlfn.XLOOKUP(C5,Industry_Benchmark!$A$2:$A$82,Industry_Benchmark!$G$2:$G$82,"") -> 0.40269749 | Z5: =X5-Y5 -> 0.08781251 | AA5: =IF(Z5>0,1,0) -> 1 | AB5: =SUM(G5,K5,O5,S5,W5,AA5) -> 5 | AC5: =AB5/6 -> 0.83333333 | AD5: {=_xlfn.IFS( AB5=6,"Excellent", AB5=5,"Strong", AB5=4,"Good", AB5=3,"Average", AB5<=2,"Weak" )} -> Strong
A6: NVIDIA Corporation | B6: NVDA | C6: Semiconductors | D6: 0.33806 | E6: =_xlfn.XLOOKUP(C6,Industry_Benchmark!$A$2:$A$82,Industry_Benchmark!$B$2:$B$82,"") -> 0.246593 | F6: =D6-E6 -> 0.091467 | G6: =IF(F6>0,1,0) -> 1 | H6: 0.503 | I6: =_xlfn.XLOOKUP(C6,Industry_Benchmark!$A$2:$A$82,Industry_Benchmark!$C$2:$C$82,"") -> 0.3076 | J6: =H6-I6 -> 0.1954 | K6: =IF(J6>0,1,0) -> 1 | L6: 7.145 | M6: =_xlfn.XLOOKUP(C6,Industry_Benchmark!$A$2:$A$82,Industry_Benchmark!$D$2:$D$82,"") -> 2.9108 | N6: =L6-M6 -> 4.2342 | O6: =IF(N6>0,1,0) -> 1 | P6: 0.15934 | Q6: =_xlfn.XLOOKUP(C6,Industry_Benchmark!$A$2:$A$82,Industry_Benchmark!$E$2:$E$82,"") -> 0.121556 | R6: =P6-Q6 -> 0.037783998 | S6: =IF(R6>0,1,0) -> 1 | T6: 49.697 | U6: =_xlfn.XLOOKUP(C6,Industry_Benchmark!$A$2:$A$82,Industry_Benchmark!$F$2:$F$82,"") -> 77.0734 | V6: =T6-U6 -> -27.3764 | W6: =IF(V6>0,1,0) -> 0 | X6: 0.41939998 | Y6: =_xlfn.XLOOKUP(C6,Industry_Benchmark!$A$2:$A$82,Industry_Benchmark!$G$2:$G$82,"") -> 0.375412 | Z6: =X6-Y6 -> 0.043987982 | AA6: =IF(Z6>0,1,0) -> 1 | AB6: =SUM(G6,K6,O6,S6,W6,AA6) -> 5 | AC6: =AB6/6 -> 0.83333333 | AD6: {=_xlfn.IFS( AB6=6,"Excellent", AB6=5,"Strong", AB6=4,"Good", AB6=3,"Average", AB6<=2,"Weak" )} -> Strong
A7: Mastercard Incorporated | B7: MA | C7: Credit Services | D7: 0.46001998 | E7: =_xlfn.XLOOKUP(C7,Industry_Benchmark!$A$2:$A$82,Industry_Benchmark!$B$2:$B$82,"") -> 0.39226666 | F7: =D7-E7 -> 0.067753317 | G7: =IF(F7>0,1,0) -> 1 | H7: 0.266 | I7: =_xlfn.XLOOKUP(C7,Industry_Benchmark!$A$2:$A$82,Industry_Benchmark!$C$2:$C$82,"") -> 0.213 | J7: =H7-I7 -> 0.053 | K7: =IF(J7>0,1,0) -> 1 | L7: 1.288 | M7: =_xlfn.XLOOKUP(C7,Industry_Benchmark!$A$2:$A$82,Industry_Benchmark!$D$2:$D$82,"") -> 1.327 | N7: =L7-M7 -> -0.039 | O7: =IF(N7>0,1,0) -> 0 | P7: 0.18013 | Q7: =_xlfn.XLOOKUP(C7,Industry_Benchmark!$A$2:$A$82,Industry_Benchmark!$E$2:$E$82,"") -> 0.11619667 | R7: =P7-Q7 -> 0.063933332 | S7: =IF(R7>0,1,0) -> 1 | T7: 197.963 | U7: =_xlfn.XLOOKUP(C7,Industry_Benchmark!$A$2:$A$82,Industry_Benchmark!$F$2:$F$82,"") -> 99.888333 | V7: =T7-U7 -> 98.074667 | W7: =IF(V7>0,1,0) -> 1 | X7: 1.2473301 | Y7: =_xlfn.XLOOKUP(C7,Industry_Benchmark!$A$2:$A$82,Industry_Benchmark!$G$2:$G$82,"") -> 0.61539336 | Z7: =X7-Y7 -> 0.63193674 | AA7: =IF(Z7>0,1,0) -> 1 | AB7: =SUM(G7,K7,O7,S7,W7,AA7) -> 5 | AC7: =AB7/6 -> 0.83333333 | AD7: {=_xlfn.IFS( AB7=6,"Excellent", AB7=5,"Strong", AB7=4,"Good", AB7=3,"Average", AB7<=2,"Weak" )} -> Strong
A8: Home Depot, Inc. (The) | B8: HD | C8: Home Improvement Retail | D8: 0.10791001 | E8: =_xlfn.XLOOKUP(C8,Industry_Benchmark!$A$2:$A$82,Industry_Benchmark!$B$2:$B$82,"") -> 0.097080005 | F8: =D8-E8 -> 0.010830005 | G8: =IF(F8>0,1,0) -> 1 | H8: 0.098 | I8: =_xlfn.XLOOKUP(C8,Industry_Benchmark!$A$2:$A$82,Industry_Benchmark!$C$2:$C$82,"") -> 0.0625 | J8: =H8-I8 -> 0.0355 | K8: =IF(J8>0,1,0) -> 1 | L8: 1.132 | M8: =_xlfn.XLOOKUP(C8,Industry_Benchmark!$A$2:$A$82,Industry_Benchmark!$D$2:$D$82,"") -> 1.1625 | N8: =L8-M8 -> -0.0305 | O8: =IF(N8>0,1,0) -> 0 | P8: 0.20454 | Q8: =_xlfn.XLOOKUP(C8,Industry_Benchmark!$A$2:$A$82,Industry_Benchmark!$E$2:$E$82,"") -> 0.183375 | R8: =P8-Q8 -> 0.021165 | S8: =IF(R8>0,1,0) -> 1 | T8: 4373.43 | U8: =_xlfn.XLOOKUP(C8,Industry_Benchmark!$A$2:$A$82,Industry_Benchmark!$F$2:$F$82,"") -> 2186.715 | V8: =T8-U8 -> 2186.715 | W8: =IF(V8>0,1,0) -> 1 | X8: 12.403111 | Y8: =_xlfn.XLOOKUP(C8,Industry_Benchmark!$A$2:$A$82,Industry_Benchmark!$G$2:$G$82,"") -> 9.4907002 | Z8: =X8-Y8 -> 2.9124103 | AA8: =IF(Z8>0,1,0) -> 1 | AB8: =SUM(G8,K8,O8,S8,W8,AA8) -> 5 | AC8: =AB8/6 -> 0.83333333 | AD8: {=_xlfn.IFS( AB8=6,"Excellent", AB8=5,"Strong", AB8=4,"Good", AB8=3,"Average", AB8<=2,"Weak" )} -> Strong
A9: Accenture plc | B9: ACN | C9: Information Technology Services | D9: 0.11533 | E9: =_xlfn.XLOOKUP(C9,Industry_Benchmark!$A$2:$A$82,Industry_Benchmark!$B$2:$B$82,"") -> 0.08144 | F9: =D9-E9 -> 0.03389 | G9: =IF(F9>0,1,0) -> 1 | H9: 0.272 | I9: =_xlfn.XLOOKUP(C9,Industry_Benchmark!$A$2:$A$82,Industry_Benchmark!$C$2:$C$82,"") -> 0.1248 | J9: =H9-I9 -> 0.1472 | K9: =IF(J9>0,1,0) -> 1 | L9: 1.223 | M9: =_xlfn.XLOOKUP(C9,Industry_Benchmark!$A$2:$A$82,Industry_Benchmark!$D$2:$D$82,"") -> 1.1856 | N9: =L9-M9 -> 0.0374 | O9: =IF(N9>0,1,0) -> 1 | P9: 0.12456001 | Q9: =_xlfn.XLOOKUP(C9,Industry_Benchmark!$A$2:$A$82,Industry_Benchmark!$E$2:$E$82,"") -> 0.058694001 | R9: =P9-Q9 -> 0.065866005 | S9: =IF(R9>0,1,0) -> 1 | T9: 16.607 | U9: =_xlfn.XLOOKUP(C9,Industry_Benchmark!$A$2:$A$82,Industry_Benchmark!$F$2:$F$82,"") -> 80.5094 | V9: =T9-U9 -> -63.9024 | W9: =IF(V9>0,1,0) -> 0 | X9: 0.31948 | Y9: =_xlfn.XLOOKUP(C9,Industry_Benchmark!$A$2:$A$82,Industry_Benchmark!$G$2:$G$82,"") -> 0.15424 | Z9: =X9-Y9 -> 0.16524 | AA9: =IF(Z9>0,1,0) -> 1 | AB9: =SUM(G9,K9,O9,S9,W9,AA9) -> 5 | AC9: =AB9/6 -> 0.83333333 | AD9: {=_xlfn.IFS( AB9=6,"Excellent", AB9=5,"Strong", AB9=4,"Good", AB9=3,"Average", AB9<=2,"Weak" )} -> Strong
A10: Anthem, Inc. | B10: ANTM | C10: Healthcare Plans | D10: 0.041220002 | E10: =_xlfn.XLOOKUP(C10,Industry_Benchmark!$A$2:$A$82,Industry_Benchmark!$B$2:$B$82,"") -> 0.036041667 | F10: =D10-E10 -> 0.0051783347 | G10: =IF(F10>0,1,0) -> 1 | H10: 0.15 | I10: =_xlfn.XLOOKUP(C10,Industry_Benchmark!$A$2:$A$82,Industry_Benchmark!$C$2:$C$82,"") -> 0.11366667 | J10: =H10-I10 -> 0.036333333 | K10: =IF(J10>0,1,0) -> 1 | L10: 1.476 | M10: =_xlfn.XLOOKUP(C10,Industry_Benchmark!$A$2:$A$82,Industry_Benchmark!$D$2:$D$82,"") -> 1.11 | N10: =L10-M10 -> 0.366 | O10: =IF(N10>0,1,0) -> 1 | P10: 0.05371 | Q10: =_xlfn.XLOOKUP(C10,Industry_Benchmark!$A$2:$A$82,Industry_Benchmark!$E$2:$E$82,"") -> 0.046496666 | R10: =P10-Q10 -> 0.0072133338 | S10: =IF(R10>0,1,0) -> 1 | T10: 66.276 | U10: =_xlfn.XLOOKUP(C10,Industry_Benchmark!$A$2:$A$82,Industry_Benchmark!$F$2:$F$82,"") -> 78.132333 | V10: =T10-U10 -> -11.856333 | W10: =IF(V10>0,1,0) -> 0 | X10: 0.15835 | Y10: =_xlfn.XLOOKUP(C10,Industry_Benchmark!$A$2:$A$82,Industry_Benchmark!$G$2:$G$82,"") -> 0.14621 | Z10: =X10-Y10 -> 0.012139998 | AA10: =IF(Z10>0,1,0) -> 1 | AB10: =SUM(G10,K10,O10,S10,W10,AA10) -> 5 | AC10: =AB10/6 -> 0.83333333 | AD10: {=_xlfn.IFS( AB10=6,"Excellent", AB10=5,"Strong", AB10=4,"Good", AB10=3,"Average", AB10<=2,"Weak" )} -> Strong
A11: Lockheed Martin Corporation | B11: LMT | C11: Aerospace & Defense | D11: 0.094189994 | E11: =_xlfn.XLOOKUP(C11,Industry_Benchmark!$A$2:$A$82,Industry_Benchmark!$B$2:$B$82,"") -> 0.086845711 | F11: =D11-E11 -> 0.007344283 | G11: =IF(F11>0,1,0) -> 1 | H11: 0.041 | I11: =_xlfn.XLOOKUP(C11,Industry_Benchmark!$A$2:$A$82,Industry_Benchmark!$C$2:$C$82,"") -> -0.0055714286 | J11: =H11-I11 -> 0.046571429 | K11: =IF(J11>0,1,0) -> 1 | L11: 1.416 | M11: =_xlfn.XLOOKUP(C11,Industry_Benchmark!$A$2:$A$82,Industry_Benchmark!$D$2:$D$82,"") -> 1.9 | N11: =L11-M11 -> -0.484 | O11: =IF(N11>0,1,0) -> 0 | P11: 0.09624 | Q11: =_xlfn.XLOOKUP(C11,Industry_Benchmark!$A$2:$A$82,Industry_Benchmark!$E$2:$E$82,"") -> 0.055819999 | R11: =P11-Q11 -> 0.040420001 | S11: =IF(R11>0,1,0) -> 1 | T11: 119.555 | U11: =_xlfn.XLOOKUP(C11,Industry_Benchmark!$A$2:$A$82,Industry_Benchmark!$F$2:$F$82,"") -> 56.095714 | V11: =T11-U11 -> 63.459286 | W11: =IF(V11>0,1,0) -> 1 | X11: 0.74307 | Y11: =_xlfn.XLOOKUP(C11,Industry_Benchmark!$A$2:$A$82,Industry_Benchmark!$G$2:$G$82,"") -> 0.332018 | Z11: =X11-Y11 -> 0.411052 | AA11: =IF(Z11>0,1,0) -> 1 | AB11: =SUM(G11,K11,O11,S11,W11,AA11) -> 5 | AC11: =AB11/6 -> 0.83333333 | AD11: {=_xlfn.IFS( AB11=6,"Excellent", AB11=5,"Strong", AB11=4,"Good", AB11=3,"Average", AB11<=2,"Weak" )} -> Strong
A12: American Tower Corporation (REI | B12: AMT | C12: REIT—Specialty | D12: 0.27445 | E12: =_xlfn.XLOOKUP(C12,Industry_Benchmark!$A$2:$A$82,Industry_Benchmark!$B$2:$B$82,"") -> 0.1609075 | F12: =D12-E12 -> 0.1135425 | G12: =IF(F12>0,1,0) -> 1 | H12: 0.219 | I12: =_xlfn.XLOOKUP(C12,Industry_Benchmark!$A$2:$A$82,Industry_Benchmark!$C$2:$C$82,"") -> 0.1415 | J12: =H12-I12 -> 0.0775 | K12: =IF(J12>0,1,0) -> 1 | L12: 0.773 | M12: =_xlfn.XLOOKUP(C12,Industry_Benchmark!$A$2:$A$82,Industry_Benchmark!$D$2:$D$82,"") -> 0.9255 | N12: =L12-M12 -> -0.1525 | O12: =IF(N12>0,1,0) -> 0 | P12: 0.04348 | Q12: =_xlfn.XLOOKUP(C12,Industry_Benchmark!$A$2:$A$82,Industry_Benchmark!$E$2:$E$82,"") -> 0.03869 | R12: =P12-Q12 -> 0.00479 | S12: =IF(R12>0,1,0) -> 1 | T12: 434.983 | U12: =_xlfn.XLOOKUP(C12,Industry_Benchmark!$A$2:$A$82,Industry_Benchmark!$F$2:$F$82,"") -> 226.1405 | V12: =T12-U12 -> 208.8425 | W12: =IF(V12>0,1,0) -> 1 | X12: 0.34478 | Y12: =_xlfn.XLOOKUP(C12,Industry_Benchmark!$A$2:$A$82,Industry_Benchmark!$G$2:$G$82,"") -> 0.17199 | Z12: =X12-Y12 -> 0.17279 | AA12: =IF(Z12>0,1,0) -> 1 | AB12: =SUM(G12,K12,O12,S12,W12,AA12) -> 5 | AC12: =AB12/6 -> 0.83333333 | AD12: {=_xlfn.IFS( AB12=6,"Excellent", AB12=5,"Strong", AB12=4,"Good", AB12=3,"Average", AB12<=2,"Weak" )} -> Strong
A13: Intuitive Surgical, Inc. | B13: ISRG | C13: Medical Instruments & Supplies | D13: 0.29852 | E13: =_xlfn.XLOOKUP(C13,Industry_Benchmark!$A$2:$A$82,Industry_Benchmark!$B$2:$B$82,"") -> 0.1621425 | F13: =D13-E13 -> 0.1363775 | G13: =IF(F13>0,1,0) -> 1 | H13: 0.167 | I13: =_xlfn.XLOOKUP(C13,Industry_Benchmark!$A$2:$A$82,Industry_Benchmark!$C$2:$C$82,"") -> 0.13175 | J13: =H13-I13 -> 0.03525 | K13: =IF(J13>0,1,0) -> 1 | L13: 5.083 | M13: =_xlfn.XLOOKUP(C13,Industry_Benchmark!$A$2:$A$82,Industry_Benchmark!$D$2:$D$82,"") -> 2.83275 | N13: =L13-M13 -> 2.25025 | O13: =IF(N13>0,1,0) -> 1 | P13: 0.09207 | Q13: =_xlfn.XLOOKUP(C13,Industry_Benchmark!$A$2:$A$82,Industry_Benchmark!$E$2:$E$82,"") -> 0.08048 | R13: =P13-Q13 -> 0.01159 | S13: =IF(R13>0,1,0) -> 1 | T13: 0.728 | U13: =_xlfn.XLOOKUP(C13,Industry_Benchmark!$A$2:$A$82,Industry_Benchmark!$F$2:$F$82,"") -> 45.386 | V13: =T13-U13 -> -44.658 | W13: =IF(V13>0,1,0) -> 0 | X13: 0.15919 | Y13: =_xlfn.XLOOKUP(C13,Industry_Benchmark!$A$2:$A$82,Industry_Benchmark!$G$2:$G$82,"") -> 0.1407825 | Z13: =X13-Y13 -> 0.018407499 | AA13: =IF(Z13>0,1,0) -> 1 | AB13: =SUM(G13,K13,O13,S13,W13,AA13) -> 5 | AC13: =AB13/6 -> 0.83333333 | AD13: {=_xlfn.IFS( AB13=6,"Excellent", AB13=5,"Strong", AB13=4,"Good", AB13=3,"Average", AB13<=2,"Weak" )} -> Strong
... A39: Netflix, Inc. | B39: NFLX | C39: Entertainment | D39: 0.17639999 | E39: =_xlfn.XLOOKUP(C39,Industry_Benchmark!$A$2:$A$82,Industry_Benchmark!$B$2:$B$82,"") -> 0.104315 | F39: =D39-E39 -> 0.072084992 | G39: =IF(F39>0,1,0) -> 1 | H39: 0.163 | I39: =_xlfn.XLOOKUP(C39,Industry_Benchmark!$A$2:$A$82,Industry_Benchmark!$C$2:$C$82,"") -> 0.1755 | J39: =H39-I39 -> -0.0125 | K39: =IF(J39>0,1,0) -> 0 | L39: 1.17 | M39: =_xlfn.XLOOKUP(C39,Industry_Benchmark!$A$2:$A$82,Industry_Benchmark!$D$2:$D$82,"") -> 0.89125 | N39: =L39-M39 -> 0.27875 | O39: =IF(N39>0,1,0) -> 1 | P39: 0.10012 | Q39: =_xlfn.XLOOKUP(C39,Industry_Benchmark!$A$2:$A$82,Industry_Benchmark!$E$2:$E$82,"") -> 0.050625 | R39: =P39-Q39 -> 0.049495 | S39: =IF(R39>0,1,0) -> 1 | T39: 117.578 | U39: =_xlfn.XLOOKUP(C39,Industry_Benchmark!$A$2:$A$82,Industry_Benchmark!$F$2:$F$82,"") -> 174.17825 | V39: =T39-U39 -> -56.60025 | W39: =IF(V39>0,1,0) -> 0 | X39: 0.39387 | Y39: =_xlfn.XLOOKUP(C39,Industry_Benchmark!$A$2:$A$82,Industry_Benchmark!$G$2:$G$82,"") -> 0.18733 | Z39: =X39-Y39 -> 0.20654 | AA39: =IF(Z39>0,1,0) -> 1 | AB39: =SUM(G39,K39,O39,S39,W39,AA39) -> 4 | AC39: =AB39/6 -> 0.66666667 | AD39: {=_xlfn.IFS( AB39=6,"Excellent", AB39=5,"Strong", AB39=4,"Good", AB39=3,"Average", AB39<=2,"Weak" )} -> Good
A40: Philip Morris International Inc | B40: PM | C40: Tobacco | D40: 0.29247 | E40: =_xlfn.XLOOKUP(C40,Industry_Benchmark!$A$2:$A$82,Industry_Benchmark!$B$2:$B$82,"") -> 0.212055 | F40: =D40-E40 -> 0.080415 | G40: =IF(F40>0,1,0) -> 1 | H40: 0.091 | I40: =_xlfn.XLOOKUP(C40,Industry_Benchmark!$A$2:$A$82,Industry_Benchmark!$C$2:$C$82,"") -> 0.0325 | J40: =H40-I40 -> 0.0585 | K40: =IF(J40>0,1,0) -> 1 | L40: 0.998 | M40: =_xlfn.XLOOKUP(C40,Industry_Benchmark!$A$2:$A$82,Industry_Benchmark!$D$2:$D$82,"") -> 0.87 | N40: =L40-M40 -> 0.128 | O40: =IF(N40>0,1,0) -> 1 | P40: 0.2024 | Q40: =_xlfn.XLOOKUP(C40,Industry_Benchmark!$A$2:$A$82,Industry_Benchmark!$E$2:$E$82,"") -> 0.18736 | R40: =P40-Q40 -> 0.015039995 | S40: =IF(R40>0,1,0) -> 1 | T40: 0 | U40: =_xlfn.XLOOKUP(C40,Industry_Benchmark!$A$2:$A$82,Industry_Benchmark!$F$2:$F$82,"") -> 0 | V40: =T40-U40 -> 0 | W40: =IF(V40>0,1,0) -> 0 | Y40: =_xlfn.XLOOKUP(C40,Industry_Benchmark!$A$2:$A$82,Industry_Benchmark!$G$2:$G$82,"") -> 2.7119799 | Z40: =X40-Y40 -> -2.7119799 | AA40: =IF(Z40>0,1,0) -> 0 | AB40: =SUM(G40,K40,O40,S40,W40,AA40) -> 4 | AC40: =AB40/6 -> 0.66666667 | AD40: {=_xlfn.IFS( AB40=6,"Excellent", AB40=5,"Strong", AB40=4,"Good", AB40=3,"Average", AB40<=2,"Weak" )} -> Good
A41: ConocoPhillips | B41: COP | C41: Oil & Gas E&P | D41: 0.17315 | E41: =_xlfn.XLOOKUP(C41,Industry_Benchmark!$A$2:$A$82,Industry_Benchmark!$B$2:$B$82,"") -> 0.114568 | F41: =D41-E41 -> 0.058582 | G41: =IF(F41>0,1,0) -> 1 | H41: 1.771 | I41: =_xlfn.XLOOKUP(C41,Industry_Benchmark!$A$2:$A$82,Industry_Benchmark!$C$2:$C$82,"") -> 1.5186 | J41: =H41-I41 -> 0.2524 | K41: =IF(J41>0,1,0) -> 1 | L41: 1.335 | M41: =_xlfn.XLOOKUP(C41,Industry_Benchmark!$A$2:$A$82,Industry_Benchmark!$D$2:$D$82,"") -> 1.4502 | N41: =L41-M41 -> -0.1152 | O41: =IF(N41>0,1,0) -> 0 | P41: 0.10439 | Q41: =_xlfn.XLOOKUP(C41,Industry_Benchmark!$A$2:$A$82,Industry_Benchmark!$E$2:$E$82,"") -> 0.091554 | R41: =P41-Q41 -> 0.012836 | S41: =IF(R41>0,1,0) -> 1 | T41: 45.371 | U41: =_xlfn.XLOOKUP(C41,Industry_Benchmark!$A$2:$A$82,Industry_Benchmark!$F$2:$F$82,"") -> 71.0882 | V41: =T41-U41 -> -25.7172 | W41: =IF(V41>0,1,0) -> 0 | X41: 0.21471001 | Y41: =_xlfn.XLOOKUP(C41,Industry_Benchmark!$A$2:$A$82,Industry_Benchmark!$G$2:$G$82,"") -> 0.138068 | Z41: =X41-Y41 -> 0.076642008 | AA41: =IF(Z41>0,1,0) -> 1 | AB41: =SUM(G41,K41,O41,S41,W41,AA41) -> 4 | AC41: =AB41/6 -> 0.66666667 | AD41: {=_xlfn.IFS( AB41=6,"Excellent", AB41=5,"Strong", AB41=4,"Good", AB41=3,"Average", AB41<=2,"Weak" )} -> Good
A42: Amgen Inc. | B42: AMGN | C42: Drug Manufacturers—General | D42: 0.21767999 | E42: =_xlfn.XLOOKUP(C42,Industry_Benchmark!$A$2:$A$82,Industry_Benchmark!$B$2:$B$82,"") -> 0.21304125 | F42: =D42-E42 -> 0.00463874 | G42: =IF(F42>0,1,0) -> 1 | H42: 0.044 | I42: =_xlfn.XLOOKUP(C42,Industry_Benchmark!$A$2:$A$82,Industry_Benchmark!$C$2:$C$82,"") -> 0.270125 | J42: =H42-I42 -> -0.226125 | K42: =IF(J42>0,1,0) -> 0 | L42: 1.643 | M42: =_xlfn.XLOOKUP(C42,Industry_Benchmark!$A$2:$A$82,Industry_Benchmark!$D$2:$D$82,"") -> 1.4105714 | N42: =L42-M42 -> 0.23242857 | O42: =IF(N42>0,1,0) -> 1 | P42: 0.08696 | Q42: =_xlfn.XLOOKUP(C42,Industry_Benchmark!$A$2:$A$82,Industry_Benchmark!$E$2:$E$82,"") -> 0.095184286 | R42: =P42-Q42 -> -0.0082242857 | S42: =IF(R42>0,1,0) -> 0 | T42: 457.332 | U42: =_xlfn.XLOOKUP(C42,Industry_Benchmark!$A$2:$A$82,Industry_Benchmark!$F$2:$F$82,"") -> 212.024 | V42: =T42-U42 -> 245.308 | W42: =IF(V42>0,1,0) -> 1 | X42: 0.585 | Y42: =_xlfn.XLOOKUP(C42,Industry_Benchmark!$A$2:$A$82,Industry_Benchmark!$G$2:$G$82,"") -> 0.47294626 | Z42: =X42-Y42 -> 0.11205374 | AA42: =IF(Z42>0,1,0) -> 1 | AB42: =SUM(G42,K42,O42,S42,W42,AA42) -> 4 | AC42: =AB42/6 -> 0.66666667 | AD42: {=_xlfn.IFS( AB42=6,"Excellent", AB42=5,"Strong", AB42=4,"Good", AB42=3,"Average", AB42<=2,"Weak" )} -> Good
A43: Deere & Company | B43: DE | C43: Farm & Heavy Construction Machinery | D43: 0.13566 | E43: =_xlfn.XLOOKUP(C43,Industry_Benchmark!$A$2:$A$82,Industry_Benchmark!$B$2:$B$82,"") -> 0.131485 | F43: =D43-E43 -> 0.004175 | G43: =IF(F43>0,1,0) -> 1 | H43: 0.16 | I43: =_xlfn.XLOOKUP(C43,Industry_Benchmark!$A$2:$A$82,Industry_Benchmark!$C$2:$C$82,"") -> 0.194 | J43: =H43-I43 -> -0.034 | K43: =IF(J43>0,1,0) -> 0 | L43: 2.192 | M43: =_xlfn.XLOOKUP(C43,Industry_Benchmark!$A$2:$A$82,Industry_Benchmark!$D$2:$D$82,"") -> 1.824 | N43: =L43-M43 -> 0.368 | O43: =IF(N43>0,1,0) -> 1 | P43: 0.06355 | Q43: =_xlfn.XLOOKUP(C43,Industry_Benchmark!$A$2:$A$82,Industry_Benchmark!$E$2:$E$82,"") -> 0.058455 | R43: =P43-Q43 -> 0.005095 | S43: =IF(R43>0,1,0) -> 1 | T43: 264.864 | U43: =_xlfn.XLOOKUP(C43,Industry_Benchmark!$A$2:$A$82,Industry_Benchmark!$F$2:$F$82,"") -> 246.833 | V43: =T43-U43 -> 18.031 | W43: =IF(V43>0,1,0) -> 1 | X43: 0.3802 | Y43: =_xlfn.XLOOKUP(C43,Industry_Benchmark!$A$2:$A$82,Industry_Benchmark!$G$2:$G$82,"") -> 0.39367999 | Z43: =X43-Y43 -> -0.01347999 | AA43: =IF(Z43>0,1,0) -> 0 | AB43: =SUM(G43,K43,O43,S43,W43,AA43) -> 4 | AC43: =AB43/6 -> 0.66666667 | AD43: {=_xlfn.IFS( AB43=6,"Excellent", AB43=5,"Strong", AB43=4,"Good", AB43=3,"Average", AB43<=2,"Weak" )} -> Good
A44: Intuit Inc. | B44: INTU | C44: Software—Application | D44: 0.20277001 | E44: =_xlfn.XLOOKUP(C44,Industry_Benchmark!$A$2:$A$82,Industry_Benchmark!$B$2:$B$82,"") -> 0.171652 | F44: =D44-E44 -> 0.031118006 | G44: =IF(F44>0,1,0) -> 1 | H44: 0.517 | I44: =_xlfn.XLOOKUP(C44,Industry_Benchmark!$A$2:$A$82,Industry_Benchmark!$C$2:$C$82,"") -> 0.2806 | J44: =H44-I44 -> 0.2364 | K44: =IF(J44>0,1,0) -> 1 | L44: 2.099 | M44: =_xlfn.XLOOKUP(C44,Industry_Benchmark!$A$2:$A$82,Industry_Benchmark!$D$2:$D$82,"") -> 1.3602 | N44: =L44-M44 -> 0.7388 | O44: =IF(N44>0,1,0) -> 1 | P44: 0.12802 | Q44: =_xlfn.XLOOKUP(C44,Industry_Benchmark!$A$2:$A$82,Industry_Benchmark!$E$2:$E$82,"") -> 0.065944 | R44: =P44-Q44 -> 0.062076 | S44: =IF(R44>0,1,0) -> 1 | T44: 25.758 | U44: =_xlfn.XLOOKUP(C44,Industry_Benchmark!$A$2:$A$82,Industry_Benchmark!$F$2:$F$82,"") -> 73.0736 | V44: =T44-U44 -> -47.3156 | W44: =IF(V44>0,1,0) -> 0 | X44: 0.27934 | Y44: =_xlfn.XLOOKUP(C44,Industry_Benchmark!$A$2:$A$82,Industry_Benchmark!$G$2:$G$82,"") -> 0.52347798 | Z44: =X44-Y44 -> -0.24413798 | AA44: =IF(Z44>0,1,0) -> 0 | AB44: =SUM(G44,K44,O44,S44,W44,AA44) -> 4 | AC44: =AB44/6 -> 0.66666667 | AD44: {=_xlfn.IFS( AB44=6,"Excellent", AB44=5,"Strong", AB44=4,"Good", AB44=3,"Average", AB44<=2,"Weak" )} -> Good
A45: Target Corporation | B45: TGT | C45: Discount Stores | D45: 0.06562 | E45: =_xlfn.XLOOKUP(C45,Industry_Benchmark!$A$2:$A$82,Industry_Benchmark!$B$2:$B$82,"") -> 0.047956 | F45: =D45-E45 -> 0.017664 | G45: =IF(F45>0,1,0) -> 1 | H45: 0.133 | I45: =_xlfn.XLOOKUP(C45,Industry_Benchmark!$A$2:$A$82,Industry_Benchmark!$C$2:$C$82,"") -> 0.0764 | J45: =H45-I45 -> 0.0566 | K45: =IF(J45>0,1,0) -> 1 | L45: 0.967 | M45: =_xlfn.XLOOKUP(C45,Industry_Benchmark!$A$2:$A$82,Industry_Benchmark!$D$2:$D$82,"") -> 1.0478 | N45: =L45-M45 -> -0.0808 | O45: =IF(N45>0,1,0) -> 0 | P45: 0.10204001 | Q45: =_xlfn.XLOOKUP(C45,Industry_Benchmark!$A$2:$A$82,Industry_Benchmark!$E$2:$E$82,"") -> 0.076300002 | R45: =P45-Q45 -> 0.025740008 | S45: =IF(R45>0,1,0) -> 1 | T45: 112.287 | U45: =_xlfn.XLOOKUP(C45,Industry_Benchmark!$A$2:$A$82,Industry_Benchmark!$F$2:$F$82,"") -> 118.0908 | V45: =T45-U45 -> -5.8038 | W45: =IF(V45>0,1,0) -> 0 | X45: 0.50011003 | Y45: =_xlfn.XLOOKUP(C45,Industry_Benchmark!$A$2:$A$82,Industry_Benchmark!$G$2:$G$82,"") -> 0.305202 | Z45: =X45-Y45 -> 0.19490803 | AA45: =IF(Z45>0,1,0) -> 1 | AB45: =SUM(G45,K45,O45,S45,W45,AA45) -> 4 | AC45: =AB45/6 -> 0.66666667 | AD45: {=_xlfn.IFS( AB45=6,"Excellent", AB45=5,"Strong", AB45=4,"Good", AB45=3,"Average", AB45<=2,"Weak" )} -> Good
A46: Moderna, Inc. | B46: MRNA | C46: Biotechnology | D46: 0.5968 | E46: =_xlfn.XLOOKUP(C46,Industry_Benchmark!$A$2:$A$82,Industry_Benchmark!$B$2:$B$82,"") -> 0.46816001 | F46: =D46-E46 -> 0.12863999 | G46: =IF(F46>0,1,0) -> 1 | H46: 30.65 | I46: =_xlfn.XLOOKUP(C46,Industry_Benchmark!$A$2:$A$82,Industry_Benchmark!$C$2:$C$82,"") -> 10.661333 | J46: =H46-I46 -> 19.988667 | K46: =IF(J46>0,1,0) -> 1 | L46: 1.348 | M46: =_xlfn.XLOOKUP(C46,Industry_Benchmark!$A$2:$A$82,Industry_Benchmark!$D$2:$D$82,"") -> 3.179 | N46: =L46-M46 -> -1.831 | O46: =IF(N46>0,1,0) -> 0 | P46: 0.372 | Q46: =_xlfn.XLOOKUP(C46,Industry_Benchmark!$A$2:$A$82,Industry_Benchmark!$E$2:$E$82,"") -> 0.25766333 | R46: =P46-Q46 -> 0.11433667 | S46: =IF(R46>0,1,0) -> 1 | T46: 5.758 | U46: =_xlfn.XLOOKUP(C46,Industry_Benchmark!$A$2:$A$82,Industry_Benchmark!$F$2:$F$82,"") -> 9.7806667 | V46: =T46-U46 -> -4.0226667 | W46: =IF(V46>0,1,0) -> 0 | X46: 1.09609 | Y46: =_xlfn.XLOOKUP(C46,Industry_Benchmark!$A$2:$A$82,Industry_Benchmark!$G$2:$G$82,"") -> 0.62818334 | Z46: =X46-Y46 -> 0.46790666 | AA46: =IF(Z46>0,1,0) -> 1 | AB46: =SUM(G46,K46,O46,S46,W46,AA46) -> 4 | AC46: =AB46/6 -> 0.66666667 | AD46: {=_xlfn.IFS( AB46=6,"Excellent", AB46=5,"Strong", AB46=4,"Good", AB46=3,"Average", AB46<=2,"Weak" )} -> Good
A47: Regeneron Pharmaceuticals, Inc. | B47: REGN | C47: Biotechnology | D47: 0.50245 | E47: =_xlfn.XLOOKUP(C47,Industry_Benchmark!$A$2:$A$82,Industry_Benchmark!$B$2:$B$82,"") -> 0.46816001 | F47: =D47-E47 -> 0.034289993 | G47: =IF(F47>0,1,0) -> 1 | H47: 1.044 | I47: =_xlfn.XLOOKUP(C47,Industry_Benchmark!$A$2:$A$82,Industry_Benchmark!$C$2:$C$82,"") -> 10.661333 | J47: =H47-I47 -> -9.6173333 | K47: =IF(J47>0,1,0) -> 0 | L47: 3.564 | M47: =_xlfn.XLOOKUP(C47,Industry_Benchmark!$A$2:$A$82,Industry_Benchmark!$D$2:$D$82,"") -> 3.179 | N47: =L47-M47 -> 0.385 | O47: =IF(N47>0,1,0) -> 1 | P47: 0.26253 | Q47: =_xlfn.XLOOKUP(C47,Industry_Benchmark!$A$2:$A$82,Industry_Benchmark!$E$2:$E$82,"") -> 0.25766333 | R47: =P47-Q47 -> 0.0048666667 | S47: =IF(R47>0,1,0) -> 1 | T47: 14.384 | U47: =_xlfn.XLOOKUP(C47,Industry_Benchmark!$A$2:$A$82,Industry_Benchmark!$F$2:$F$82,"") -> 9.7806667 | V47: =T47-U47 -> 4.6033333 | W47: =IF(V47>0,1,0) -> 1 | X47: 0.54207003 | Y47: =_xlfn.XLOOKUP(C47,Industry_Benchmark!$A$2:$A$82,Industry_Benchmark!$G$2:$G$82,"") -> 0.62818334 | Z47: =X47-Y47 -> -0.086113313 | AA47: =IF(Z47>0,1,0) -> 0 | AB47: =SUM(G47,K47,O47,S47,W47,AA47) -> 4 | AC47: =AB47/6 -> 0.66666667 | AD47: {=_xlfn.IFS( AB47=6,"Excellent", AB47=5,"Strong", AB47=4,"Good", AB47=3,"Average", AB47<=2,"Weak" )} -> Good
A48: Northrop Grumman Corporation | B48: NOC | C48: Aerospace & Defense | D48: 0.19639999 | E48: =_xlfn.XLOOKUP(C48,Industry_Benchmark!$A$2:$A$82,Industry_Benchmark!$B$2:$B$82,"") -> 0.086845711 | F48: =D48-E48 -> 0.10955428 | G48: =IF(F48>0,1,0) -> 1 | H48: -0.154 | I48: =_xlfn.XLOOKUP(C48,Industry_Benchmark!$A$2:$A$82,Industry_Benchmark!$C$2:$C$82,"") -> -0.0055714286 | J48: =H48-I48 -> -0.14842857 | K48: =IF(J48>0,1,0) -> 0 | L48: 1.304 | M48: =_xlfn.XLOOKUP(C48,Industry_Benchmark!$A$2:$A$82,Industry_Benchmark!$D$2:$D$82,"") -> 1.9 | N48: =L48-M48 -> -0.596 | O48: =IF(N48>0,1,0) -> 0 | P48: 0.10762999 | Q48: =_xlfn.XLOOKUP(C48,Industry_Benchmark!$A$2:$A$82,Industry_Benchmark!$E$2:$E$82,"") -> 0.055819999 | R48: =P48-Q48 -> 0.051809991 | S48: =IF(R48>0,1,0) -> 1 | T48: 113.392 | U48: =_xlfn.XLOOKUP(C48,Industry_Benchmark!$A$2:$A$82,Industry_Benchmark!$F$2:$F$82,"") -> 56.095714 | V48: =T48-U48 -> 57.296286 | W48: =IF(V48>0,1,0) -> 1 | X48: 0.59604 | Y48: =_xlfn.XLOOKUP(C48,Industry_Benchmark!$A$2:$A$82,Industry_Benchmark!$G$2:$G$82,"") -> 0.332018 | Z48: =X48-Y48 -> 0.264022 | AA48: =IF(Z48>0,1,0) -> 1 | AB48: =SUM(G48,K48,O48,S48,W48,AA48) -> 4 | AC48: =AB48/6 -> 0.66666667 | AD48: {=_xlfn.IFS( AB48=6,"Excellent", AB48=5,"Strong", AB48=4,"Good", AB48=3,"Average", AB48<=2,"Weak" )} -> Good
A49: Edwards Lifesciences Corporatio | B49: EW | C49: Medical Devices | D49: 0.28726 | E49: =_xlfn.XLOOKUP(C49,Industry_Benchmark!$A$2:$A$82,Industry_Benchmark!$B$2:$B$82,"") -> 0.17781714 | F49: =D49-E49 -> 0.10944286 | G49: =IF(F49>0,1,0) -> 1 | H49: 0.116 | I49: =_xlfn.XLOOKUP(C49,Industry_Benchmark!$A$2:$A$82,Industry_Benchmark!$C$2:$C$82,"") -> 0.16085714 | J49: =H49-I49 -> -0.044857143 | K49: =IF(J49>0,1,0) -> 0 | L49: 3.081 | M49: =_xlfn.XLOOKUP(C49,Industry_Benchmark!$A$2:$A$82,Industry_Benchmark!$D$2:$D$82,"") -> 2.538 | N49: =L49-M49 -> 0.543 | O49: =IF(N49>0,1,0) -> 1 | P49: 0.126 | Q49: =_xlfn.XLOOKUP(C49,Industry_Benchmark!$A$2:$A$82,Industry_Benchmark!$E$2:$E$82,"") -> 0.074927142 | R49: =P49-Q49 -> 0.051072858 | S49: =IF(R49>0,1,0) -> 1 | T49: 11.829 | U49: =_xlfn.XLOOKUP(C49,Industry_Benchmark!$A$2:$A$82,Industry_Benchmark!$F$2:$F$82,"") -> 50.663714 | V49: =T49-U49 -> -38.834714 | W49: =IF(V49>0,1,0) -> 0 | X49: 0.28877002 | Y49: =_xlfn.XLOOKUP(C49,Industry_Benchmark!$A$2:$A$82,Industry_Benchmark!$G$2:$G$82,"") -> 0.18974 | Z49: =X49-Y49 -> 0.09903002 | AA49: =IF(Z49>0,1,0) -> 1 | AB49: =SUM(G49,K49,O49,S49,W49,AA49) -> 4 | AC49: =AB49/6 -> 0.66666667 | AD49: {=_xlfn.IFS( AB49=6,"Excellent", AB49=5,"Strong", AB49=4,"Good", AB49=3,"Average", AB49<=2,"Weak" )} -> Good
A50: Dominion Energy, Inc. | B50: D | C50: Utilities—Regulated Electric | D50: 0.19323999 | E50: =_xlfn.XLOOKUP(C50,Industry_Benchmark!$A$2:$A$82,Industry_Benchmark!$B$2:$B$82,"") -> 0.1392 | F50: =D50-E50 -> 0.054039992 | G50: =IF(F50>0,1,0) -> 1 | H50: -0.119 | I50: =_xlfn.XLOOKUP(C50,Industry_Benchmark!$A$2:$A$82,Industry_Benchmark!$C$2:$C$82,"") -> 0.030333333 | J50: =H50-I50 -> -0.14933333 | K50: =IF(J50>0,1,0) -> 0 | L50: 0.703 | M50: =_xlfn.XLOOKUP(C50,Industry_Benchmark!$A$2:$A$82,Industry_Benchmark!$D$2:$D$82,"") -> 0.65966667 | N50: =L50-M50 -> 0.043333333 | O50: =IF(N50>0,1,0) -> 1 | P50: 0.02123 | Q50: =_xlfn.XLOOKUP(C50,Industry_Benchmark!$A$2:$A$82,Industry_Benchmark!$E$2:$E$82,"") -> 0.021278334 | R50: =P50-Q50 -> -4.833375e-05 | S50: =IF(R50>0,1,0) -> 0 | T50: 152.622 | U50: =_xlfn.XLOOKUP(C50,Industry_Benchmark!$A$2:$A$82,Industry_Benchmark!$F$2:$F$82,"") -> 151.27917 | V50: =T50-U50 -> 1.3428333 | W50: =IF(V50>0,1,0) -> 1 | X50: 0.09639 | Y50: =_xlfn.XLOOKUP(C50,Industry_Benchmark!$A$2:$A$82,Industry_Benchmark!$G$2:$G$82,"") -> 0.080088333 | Z50: =X50-Y50 -> 0.016301667 | AA50: =IF(Z50>0,1,0) -> 1 | AB50: =SUM(G50,K50,O50,S50,W50,AA50) -> 4 | AC50: =AB50/6 -> 0.66666667 | AD50: {=_xlfn.IFS( AB50=6,"Excellent", AB50=5,"Strong", AB50=4,"Good", AB50=3,"Average", AB50<=2,"Weak" )} -> Good
A51: Activision Blizzard, Inc | B51: ATVI | C51: Electronic Gaming & Multimedia | D51: 0.29209 | E51: =_xlfn.XLOOKUP(C51,Industry_Benchmark!$A$2:$A$82,Industry_Benchmark!$B$2:$B$82,"") -> 0.20741 | F51: =D51-E51 -> 0.084680003 | G51: =IF(F51>0,1,0) -> 1 | H51: 0.059 | I51: =_xlfn.XLOOKUP(C51,Industry_Benchmark!$A$2:$A$82,Industry_Benchmark!$C$2:$C$82,"") -> 0.3225 | J51: =H51-I51 -> -0.2635 | K51: =IF(J51>0,1,0) -> 0 | L51: 5.561 | M51: =_xlfn.XLOOKUP(C51,Industry_Benchmark!$A$2:$A$82,Industry_Benchmark!$D$2:$D$82,"") -> 3.438 | N51: =L51-M51 -> 2.123 | O51: =IF(N51>0,1,0) -> 1 | P51: 0.08984 | Q51: =_xlfn.XLOOKUP(C51,Industry_Benchmark!$A$2:$A$82,Industry_Benchmark!$E$2:$E$82,"") -> 0.07348 | R51: =P51-Q51 -> 0.01636 | S51: =IF(R51>0,1,0) -> 1 | T51: 21.28 | U51: =_xlfn.XLOOKUP(C51,Industry_Benchmark!$A$2:$A$82,Industry_Benchmark!$F$2:$F$82,"") -> 24.61 | V51: =T51-U51 -> -3.33 | W51: =IF(V51>0,1,0) -> 0 | X51: 0.16877002 | Y51: =_xlfn.XLOOKUP(C51,Industry_Benchmark!$A$2:$A$82,Industry_Benchmark!$G$2:$G$82,"") -> 0.13366 | Z51: =X51-Y51 -> 0.035110015 | AA51: =IF(Z51>0,1,0) -> 1 | AB51: =SUM(G51,K51,O51,S51,W51,AA51) -> 4 | AC51: =AB51/6 -> 0.66666667 | AD51: {=_xlfn.IFS( AB51=6,"Excellent", AB51=5,"Strong", AB51=4,"Good", AB51=3,"Average", AB51<=2,"Weak" )} -> Good
A52: Pioneer Natural Resources Compa | B52: PXD | C52: Oil & Gas E&P | D52: 0.11852 | E52: =_xlfn.XLOOKUP(C52,Industry_Benchmark!$A$2:$A$82,Industry_Benchmark!$B$2:$B$82,"") -> 0.114568 | F52: =D52-E52 -> 0.0039520002 | G52: =IF(F52>0,1,0) -> 1 | H52: 1.763 | I52: =_xlfn.XLOOKUP(C52,Industry_Benchmark!$A$2:$A$82,Industry_Benchmark!$C$2:$C$82,"") -> 1.5186 | J52: =H52-I52 -> 0.2444 | K52: =IF(J52>0,1,0) -> 1 | L52: 1.516 | M52: =_xlfn.XLOOKUP(C52,Industry_Benchmark!$A$2:$A$82,Industry_Benchmark!$D$2:$D$82,"") -> 1.4502 | N52: =L52-M52 -> 0.0658 | O52: =IF(N52>0,1,0) -> 1 | P52: 0.09395 | Q52: =_xlfn.XLOOKUP(C52,Industry_Benchmark!$A$2:$A$82,Industry_Benchmark!$E$2:$E$82,"") -> 0.091554 | R52: =P52-Q52 -> 0.0023960002 | S52: =IF(R52>0,1,0) -> 1 | T52: 34.308 | U52: =_xlfn.XLOOKUP(C52,Industry_Benchmark!$A$2:$A$82,Industry_Benchmark!$F$2:$F$82,"") -> 71.0882 | V52: =T52-U52 -> -36.7802 | W52: =IF(V52>0,1,0) -> 0 | X52: 0.12312 | Y52: =_xlfn.XLOOKUP(C52,Industry_Benchmark!$A$2:$A$82,Industry_Benchmark!$G$2:$G$82,"") -> 0.138068 | Z52: =X52-Y52 -> -0.014948002 | AA52: =IF(Z52>0,1,0) -> 0 | AB52: =SUM(G52,K52,O52,S52,W52,AA52) -> 4 | AC52: =AB52/6 -> 0.66666667 | AD52: {=_xlfn.IFS( AB52=6,"Excellent", AB52=5,"Strong", AB52=4,"Good", AB52=3,"Average", AB52<=2,"Weak" )} -> Good
... A61: Valero Energy Corporation | B61: VLO | C61: Oil & Gas Refining & Marketing | D61: 0.00858 | E61: =_xlfn.XLOOKUP(C61,Industry_Benchmark!$A$2:$A$82,Industry_Benchmark!$B$2:$B$82,"") -> 0.033746667 | F61: =D61-E61 -> -0.025166667 | G61: =IF(F61>0,1,0) -> 0 | H61: 1.249 | I61: =_xlfn.XLOOKUP(C61,Industry_Benchmark!$A$2:$A$82,Industry_Benchmark!$C$2:$C$82,"") -> 1.0683333 | J61: =H61-I61 -> 0.18066667 | K61: =IF(J61>0,1,0) -> 1 | L61: 1.256 | M61: =_xlfn.XLOOKUP(C61,Industry_Benchmark!$A$2:$A$82,Industry_Benchmark!$D$2:$D$82,"") -> 1.202 | N61: =L61-M61 -> 0.054 | O61: =IF(N61>0,1,0) -> 1 | P61: 0.02548 | Q61: =_xlfn.XLOOKUP(C61,Industry_Benchmark!$A$2:$A$82,Industry_Benchmark!$E$2:$E$82,"") -> 0.016325 | R61: =P61-Q61 -> 0.009155 | S61: =IF(R61>0,1,0) -> 1 | T61: 76.323 | U61: =_xlfn.XLOOKUP(C61,Industry_Benchmark!$A$2:$A$82,Industry_Benchmark!$F$2:$F$82,"") -> 76.002333 | V61: =T61-U61 -> 0.32066667 | W61: =IF(V61>0,1,0) -> 1 | X61: 0.06528 | Y61: =_xlfn.XLOOKUP(C61,Industry_Benchmark!$A$2:$A$82,Industry_Benchmark!$G$2:$G$82,"") -> 0.072096668 | Z61: =X61-Y61 -> -0.0068166683 | AA61: =IF(Z61>0,1,0) -> 0 | AB61: =SUM(G61,K61,O61,S61,W61,AA61) -> 4 | AC61: =AB61/6 -> 0.66666667 | AD61: {=_xlfn.IFS( AB61=6,"Excellent", AB61=5,"Strong", AB61=4,"Good", AB61=3,"Average", AB61<=2,"Weak" )} -> Good
A62: Transdigm Group Incorporated | B62: TDG | C62: Aerospace & Defense | D62: 0.16237 | E62: =_xlfn.XLOOKUP(C62,Industry_Benchmark!$A$2:$A$82,Industry_Benchmark!$B$2:$B$82,"") -> 0.086845711 | F62: =D62-E62 -> 0.075524289 | G62: =IF(F62>0,1,0) -> 1 | H62: 0.078 | I62: =_xlfn.XLOOKUP(C62,Industry_Benchmark!$A$2:$A$82,Industry_Benchmark!$C$2:$C$82,"") -> -0.0055714286 | J62: =H62-I62 -> 0.083571429 | K62: =IF(J62>0,1,0) -> 1 | L62: 5.059 | M62: =_xlfn.XLOOKUP(C62,Industry_Benchmark!$A$2:$A$82,Industry_Benchmark!$D$2:$D$82,"") -> 1.9 | N62: =L62-M62 -> 3.159 | O62: =IF(N62>0,1,0) -> 1 | P62: 0.06267 | Q62: =_xlfn.XLOOKUP(C62,Industry_Benchmark!$A$2:$A$82,Industry_Benchmark!$E$2:$E$82,"") -> 0.055819999 | R62: =P62-Q62 -> 0.0068500009 | S62: =IF(R62>0,1,0) -> 1 | T62: 0 | U62: =_xlfn.XLOOKUP(C62,Industry_Benchmark!$A$2:$A$82,Industry_Benchmark!$F$2:$F$82,"") -> 56.095714 | V62: =T62-U62 -> -56.095714 | W62: =IF(V62>0,1,0) -> 0 | Y62: =_xlfn.XLOOKUP(C62,Industry_Benchmark!$A$2:$A$82,Industry_Benchmark!$G$2:$G$82,"") -> 0.332018 | Z62: =X62-Y62 -> -0.332018 | AA62: =IF(Z62>0,1,0) -> 0 | AB62: =SUM(G62,K62,O62,S62,W62,AA62) -> 4 | AC62: =AB62/6 -> 0.66666667 | AD62: {=_xlfn.IFS( AB62=6,"Excellent", AB62=5,"Strong", AB62=4,"Good", AB62=3,"Average", AB62<=2,"Weak" )} -> Good
A63: LyondellBasell Industries NV | B63: LYB | C63: Specialty Chemicals | D63: 0.12149999 | E63: =_xlfn.XLOOKUP(C63,Industry_Benchmark!$A$2:$A$82,Industry_Benchmark!$B$2:$B$82,"") -> 0.15536 | F63: =D63-E63 -> -0.033860013 | G63: =IF(F63>0,1,0) -> 0 | H63: 0.616 | I63: =_xlfn.XLOOKUP(C63,Industry_Benchmark!$A$2:$A$82,Industry_Benchmark!$C$2:$C$82,"") -> 0.21066667 | J63: =H63-I63 -> 0.40533333 | K63: =IF(J63>0,1,0) -> 1 | L63: 1.69 | M63: =_xlfn.XLOOKUP(C63,Industry_Benchmark!$A$2:$A$82,Industry_Benchmark!$D$2:$D$82,"") -> 1.6655 | N63: =L63-M63 -> 0.0245 | O63: =IF(N63>0,1,0) -> 1 | P63: 0.12806 | Q63: =_xlfn.XLOOKUP(C63,Industry_Benchmark!$A$2:$A$82,Industry_Benchmark!$E$2:$E$82,"") -> 0.067101667 | R63: =P63-Q63 -> 0.060958333 | S63: =IF(R63>0,1,0) -> 1 | T63: 115.799 | U63: =_xlfn.XLOOKUP(C63,Industry_Benchmark!$A$2:$A$82,Industry_Benchmark!$F$2:$F$82,"") -> 123.15567 | V63: =T63-U63 -> -7.3566667 | W63: =IF(V63>0,1,0) -> 0 | X63: 0.55903 | Y63: =_xlfn.XLOOKUP(C63,Industry_Benchmark!$A$2:$A$82,Industry_Benchmark!$G$2:$G$82,"") -> 0.26484833 | Z63: =X63-Y63 -> 0.29418167 | AA63: =IF(Z63>0,1,0) -> 1 | AB63: =SUM(G63,K63,O63,S63,W63,AA63) -> 4 | AC63: =AB63/6 -> 0.66666667 | AD63: {=_xlfn.IFS( AB63=6,"Excellent", AB63=5,"Strong", AB63=4,"Good", AB63=3,"Average", AB63<=2,"Weak" )} -> Good
A64: Ameriprise Financial, Inc. | B64: AMP | C64: Asset Management | D64: 0.20531 | E64: =_xlfn.XLOOKUP(C64,Industry_Benchmark!$A$2:$A$82,Industry_Benchmark!$B$2:$B$82,"") -> 0.30562332 | F64: =D64-E64 -> -0.10031332 | G64: =IF(F64>0,1,0) -> 0 | H64: 0.18 | I64: =_xlfn.XLOOKUP(C64,Industry_Benchmark!$A$2:$A$82,Industry_Benchmark!$C$2:$C$82,"") -> 0.156 | J64: =H64-I64 -> 0.024 | K64: =IF(J64>0,1,0) -> 1 | L64: 3.219 | M64: =_xlfn.XLOOKUP(C64,Industry_Benchmark!$A$2:$A$82,Industry_Benchmark!$D$2:$D$82,"") -> 2.0716667 | N64: =L64-M64 -> 1.1473333 | O64: =IF(N64>0,1,0) -> 1 | P64: 0.0153 | Q64: =_xlfn.XLOOKUP(C64,Industry_Benchmark!$A$2:$A$82,Industry_Benchmark!$E$2:$E$82,"") -> 0.081486663 | R64: =P64-Q64 -> -0.066186663 | S64: =IF(R64>0,1,0) -> 0 | T64: 67.564 | U64: =_xlfn.XLOOKUP(C64,Industry_Benchmark!$A$2:$A$82,Industry_Benchmark!$F$2:$F$82,"") -> 31.016667 | V64: =T64-U64 -> 36.547333 | W64: =IF(V64>0,1,0) -> 1 | X64: 0.47784 | Y64: =_xlfn.XLOOKUP(C64,Industry_Benchmark!$A$2:$A$82,Industry_Benchmark!$G$2:$G$82,"") -> 0.32167 | Z64: =X64-Y64 -> 0.15617 | AA64: =IF(Z64>0,1,0) -> 1 | AB64: =SUM(G64,K64,O64,S64,W64,AA64) -> 4 | AC64: =AB64/6 -> 0.66666667 | AD64: {=_xlfn.IFS( AB64=6,"Excellent", AB64=5,"Strong", AB64=4,"Good", AB64=3,"Average", AB64<=2,"Weak" )} -> Good
A65: Align Technology, Inc. | B65: ALGN | C65: Medical Devices | D65: 0.19532 | E65: =_xlfn.XLOOKUP(C65,Industry_Benchmark!$A$2:$A$82,Industry_Benchmark!$B$2:$B$82,"") -> 0.17781714 | F65: =D65-E65 -> 0.017502858 | G65: =IF(F65>0,1,0) -> 1 | H65: 0.236 | I65: =_xlfn.XLOOKUP(C65,Industry_Benchmark!$A$2:$A$82,Industry_Benchmark!$C$2:$C$82,"") -> 0.16085714 | J65: =H65-I65 -> 0.075142857 | K65: =IF(J65>0,1,0) -> 1 | L65: 1.296 | M65: =_xlfn.XLOOKUP(C65,Industry_Benchmark!$A$2:$A$82,Industry_Benchmark!$D$2:$D$82,"") -> 2.538 | N65: =L65-M65 -> -1.242 | O65: =IF(N65>0,1,0) -> 0 | P65: 0.11331 | Q65: =_xlfn.XLOOKUP(C65,Industry_Benchmark!$A$2:$A$82,Industry_Benchmark!$E$2:$E$82,"") -> 0.074927142 | R65: =P65-Q65 -> 0.038382858 | S65: =IF(R65>0,1,0) -> 1 | T65: 2.834 | U65: =_xlfn.XLOOKUP(C65,Industry_Benchmark!$A$2:$A$82,Industry_Benchmark!$F$2:$F$82,"") -> 50.663714 | V65: =T65-U65 -> -47.829714 | W65: =IF(V65>0,1,0) -> 0 | X65: 0.22518998 | Y65: =_xlfn.XLOOKUP(C65,Industry_Benchmark!$A$2:$A$82,Industry_Benchmark!$G$2:$G$82,"") -> 0.18974 | Z65: =X65-Y65 -> 0.03544998 | AA65: =IF(Z65>0,1,0) -> 1 | AB65: =SUM(G65,K65,O65,S65,W65,AA65) -> 4 | AC65: =AB65/6 -> 0.66666667 | AD65: {=_xlfn.IFS( AB65=6,"Excellent", AB65=5,"Strong", AB65=4,"Good", AB65=3,"Average", AB65<=2,"Weak" )} -> Good
A66: Halliburton Company | B66: HAL | C66: Oil & Gas Equipment & Services | D66: 0.02792 | E66: =_xlfn.XLOOKUP(C66,Industry_Benchmark!$A$2:$A$82,Industry_Benchmark!$B$2:$B$82,"") -> 0.038926668 | F66: =D66-E66 -> -0.011006668 | G66: =IF(F66>0,1,0) -> 0 | H66: 0.297 | I66: =_xlfn.XLOOKUP(C66,Industry_Benchmark!$A$2:$A$82,Industry_Benchmark!$C$2:$C$82,"") -> 0.14366667 | J66: =H66-I66 -> 0.15333333 | K66: =IF(J66>0,1,0) -> 1 | L66: 2.39 | M66: =_xlfn.XLOOKUP(C66,Industry_Benchmark!$A$2:$A$82,Industry_Benchmark!$D$2:$D$82,"") -> 1.7346667 | N66: =L66-M66 -> 0.65533333 | O66: =IF(N66>0,1,0) -> 1 | P66: 0.04335 | Q66: =_xlfn.XLOOKUP(C66,Industry_Benchmark!$A$2:$A$82,Industry_Benchmark!$E$2:$E$82,"") -> 0.03826 | R66: =P66-Q66 -> 0.00509 | S66: =IF(R66>0,1,0) -> 1 | T66: 180.941 | U66: =_xlfn.XLOOKUP(C66,Industry_Benchmark!$A$2:$A$82,Industry_Benchmark!$F$2:$F$82,"") -> 106.27767 | V66: =T66-U66 -> 74.663333 | W66: =IF(V66>0,1,0) -> 1 | X66: 0.07599 | Y66: =_xlfn.XLOOKUP(C66,Industry_Benchmark!$A$2:$A$82,Industry_Benchmark!$G$2:$G$82,"") -> 0.07715 | Z66: =X66-Y66 -> -0.00116 | AA66: =IF(Z66>0,1,0) -> 0 | AB66: =SUM(G66,K66,O66,S66,W66,AA66) -> 4 | AC66: =AB66/6 -> 0.66666667 | AD66: {=_xlfn.IFS( AB66=6,"Excellent", AB66=5,"Strong", AB66=4,"Good", AB66=3,"Average", AB66<=2,"Weak" )} -> Good
A67: eBay Inc. | B67: EBAY | C67: Internet Retail | D67: 1.07049 | E67: =_xlfn.XLOOKUP(C67,Industry_Benchmark!$A$2:$A$82,Industry_Benchmark!$B$2:$B$82,"") -> 0.57075 | F67: =D67-E67 -> 0.49974 | G67: =IF(F67>0,1,0) -> 1 | H67: 0.108 | I67: =_xlfn.XLOOKUP(C67,Industry_Benchmark!$A$2:$A$82,Industry_Benchmark!$C$2:$C$82,"") -> 0.101 | J67: =H67-I67 -> 0.007 | K67: =IF(J67>0,1,0) -> 1 | L67: 3.353 | M67: =_xlfn.XLOOKUP(C67,Industry_Benchmark!$A$2:$A$82,Industry_Benchmark!$D$2:$D$82,"") -> 2.2445 | N67: =L67-M67 -> 1.1085 | O67: =IF(N67>0,1,0) -> 1 | P67: 0.07703 | Q67: =_xlfn.XLOOKUP(C67,Industry_Benchmark!$A$2:$A$82,Industry_Benchmark!$E$2:$E$82,"") -> 0.059479999 | R67: =P67-Q67 -> 0.017550001 | S67: =IF(R67>0,1,0) -> 1 | T67: 85.034 | U67: =_xlfn.XLOOKUP(C67,Industry_Benchmark!$A$2:$A$82,Industry_Benchmark!$F$2:$F$82,"") -> 92.949 | V67: =T67-U67 -> -7.915 | W67: =IF(V67>0,1,0) -> 0 | X67: 0.28445998 | Y67: =_xlfn.XLOOKUP(C67,Industry_Benchmark!$A$2:$A$82,Industry_Benchmark!$G$2:$G$82,"") -> 0.28625999 | Z67: =X67-Y67 -> -0.00180001 | AA67: =IF(Z67>0,1,0) -> 0 | AB67: =SUM(G67,K67,O67,S67,W67,AA67) -> 4 | AC67: =AB67/6 -> 0.66666667 | AD67: {=_xlfn.IFS( AB67=6,"Excellent", AB67=5,"Strong", AB67=4,"Good", AB67=3,"Average", AB67<=2,"Weak" )} -> Good
A68: Tesla, Inc. | B68: TSLA | C68: Auto Manufacturers | D68: 0.07403 | E68: =_xlfn.XLOOKUP(C68,Industry_Benchmark!$A$2:$A$82,Industry_Benchmark!$B$2:$B$82,"") -> 0.094826665 | F68: =D68-E68 -> -0.020796665 | G68: =IF(F68>0,1,0) -> 0 | H68: 0.568 | I68: =_xlfn.XLOOKUP(C68,Industry_Benchmark!$A$2:$A$82,Industry_Benchmark!$C$2:$C$82,"") -> 0.17033333 | J68: =H68-I68 -> 0.39766667 | K68: =IF(J68>0,1,0) -> 1 | L68: 1.385 | M68: =_xlfn.XLOOKUP(C68,Industry_Benchmark!$A$2:$A$82,Industry_Benchmark!$D$2:$D$82,"") -> 1.2296667 | N68: =L68-M68 -> 0.15533333 | O68: =IF(N68>0,1,0) -> 1 | P68: 0.055370003 | Q68: =_xlfn.XLOOKUP(C68,Industry_Benchmark!$A$2:$A$82,Industry_Benchmark!$E$2:$E$82,"") -> 0.036796667 | R68: =P68-Q68 -> 0.018573336 | S68: =IF(R68>0,1,0) -> 1 | T68: 35.65 | U68: =_xlfn.XLOOKUP(C68,Industry_Benchmark!$A$2:$A$82,Industry_Benchmark!$F$2:$F$82,"") -> 163.52167 | V68: =T68-U68 -> -127.87167 | W68: =IF(V68>0,1,0) -> 0 | X68: 0.15641 | Y68: =_xlfn.XLOOKUP(C68,Industry_Benchmark!$A$2:$A$82,Industry_Benchmark!$G$2:$G$82,"") -> 0.25986001 | Z68: =X68-Y68 -> -0.10345001 | AA68: =IF(Z68>0,1,0) -> 0 | AB68: =SUM(G68,K68,O68,S68,W68,AA68) -> 3 | AC68: =AB68/6 -> 0.5 | AD68: {=_xlfn.IFS( AB68=6,"Excellent", AB68=5,"Strong", AB68=4,"Good", AB68=3,"Average", AB68<=2,"Weak" )} -> Average
A69: UnitedHealth Group Incorporated | B69: UNH | C69: Healthcare Plans | D69: 0.05523 | E69: =_xlfn.XLOOKUP(C69,Industry_Benchmark!$A$2:$A$82,Industry_Benchmark!$B$2:$B$82,"") -> 0.036041667 | F69: =D69-E69 -> 0.019188333 | G69: =IF(F69>0,1,0) -> 1 | H69: 0.111 | I69: =_xlfn.XLOOKUP(C69,Industry_Benchmark!$A$2:$A$82,Industry_Benchmark!$C$2:$C$82,"") -> 0.11366667 | J69: =H69-I69 -> -0.0026666667 | K69: =IF(J69>0,1,0) -> 0 | L69: 0.72 | M69: =_xlfn.XLOOKUP(C69,Industry_Benchmark!$A$2:$A$82,Industry_Benchmark!$D$2:$D$82,"") -> 1.11 | N69: =L69-M69 -> -0.39 | O69: =IF(N69>0,1,0) -> 0 | P69: 0.0679 | Q69: =_xlfn.XLOOKUP(C69,Industry_Benchmark!$A$2:$A$82,Industry_Benchmark!$E$2:$E$82,"") -> 0.046496666 | R69: =P69-Q69 -> 0.021403334 | S69: =IF(R69>0,1,0) -> 1 | T69: 62.929 | U69: =_xlfn.XLOOKUP(C69,Industry_Benchmark!$A$2:$A$82,Industry_Benchmark!$F$2:$F$82,"") -> 78.132333 | V69: =T69-U69 -> -15.203333 | W69: =IF(V69>0,1,0) -> 0 | X69: 0.21985 | Y69: =_xlfn.XLOOKUP(C69,Industry_Benchmark!$A$2:$A$82,Industry_Benchmark!$G$2:$G$82,"") -> 0.14621 | Z69: =X69-Y69 -> 0.073639998 | AA69: =IF(Z69>0,1,0) -> 1 | AB69: =SUM(G69,K69,O69,S69,W69,AA69) -> 3 | AC69: =AB69/6 -> 0.5 | AD69: {=_xlfn.IFS( AB69=6,"Excellent", AB69=5,"Strong", AB69=4,"Good", AB69=3,"Average", AB69<=2,"Weak" )} -> Average
A70: Coca-Cola Company (The) | B70: KO | C70: Beverages—Non-Alcoholic | D70: 0.23313999 | E70: =_xlfn.XLOOKUP(C70,Industry_Benchmark!$A$2:$A$82,Industry_Benchmark!$B$2:$B$82,"") -> 0.20897 | F70: =D70-E70 -> 0.024169993 | G70: =IF(F70>0,1,0) -> 1 | H70: 0.161 | I70: =_xlfn.XLOOKUP(C70,Industry_Benchmark!$A$2:$A$82,Industry_Benchmark!$C$2:$C$82,"") -> 0.13633333 | J70: =H70-I70 -> 0.024666667 | K70: =IF(J70>0,1,0) -> 1 | L70: 1.516 | M70: =_xlfn.XLOOKUP(C70,Industry_Benchmark!$A$2:$A$82,Industry_Benchmark!$D$2:$D$82,"") -> 2.3876667 | N70: =L70-M70 -> -0.87166667 | O70: =IF(N70>0,1,0) -> 0 | P70: 0.07831 | Q70: =_xlfn.XLOOKUP(C70,Industry_Benchmark!$A$2:$A$82,Industry_Benchmark!$E$2:$E$82,"") -> 0.10935333 | R70: =P70-Q70 -> -0.031043335 | S70: =IF(R70>0,1,0) -> 0 | T70: 172.826 | U70: =_xlfn.XLOOKUP(C70,Industry_Benchmark!$A$2:$A$82,Industry_Benchmark!$F$2:$F$82,"") -> 143.72033 | V70: =T70-U70 -> 29.105667 | W70: =IF(V70>0,1,0) -> 1 | X70: 0.39722002 | Y70: =_xlfn.XLOOKUP(C70,Industry_Benchmark!$A$2:$A$82,Industry_Benchmark!$G$2:$G$82,"") -> 0.41078666 | Z70: =X70-Y70 -> -0.01356664 | AA70: =IF(Z70>0,1,0) -> 0 | AB70: =SUM(G70,K70,O70,S70,W70,AA70) -> 3 | AC70: =AB70/6 -> 0.5 | AD70: {=_xlfn.IFS( AB70=6,"Excellent", AB70=5,"Strong", AB70=4,"Good", AB70=3,"Average", AB70<=2,"Weak" )} -> Average
A71: Costco Wholesale Corporation | B71: COST | C71: Discount Stores | D71: 0.02543 | E71: =_xlfn.XLOOKUP(C71,Industry_Benchmark!$A$2:$A$82,Industry_Benchmark!$B$2:$B$82,"") -> 0.047956 | F71: =D71-E71 -> -0.022526 | G71: =IF(F71>0,1,0) -> 0 | H71: 0.166 | I71: =_xlfn.XLOOKUP(C71,Industry_Benchmark!$A$2:$A$82,Industry_Benchmark!$C$2:$C$82,"") -> 0.0764 | J71: =H71-I71 -> 0.0896 | K71: =IF(J71>0,1,0) -> 1 | L71: 1.015 | M71: =_xlfn.XLOOKUP(C71,Industry_Benchmark!$A$2:$A$82,Industry_Benchmark!$D$2:$D$82,"") -> 1.0478 | N71: =L71-M71 -> -0.0328 | O71: =IF(N71>0,1,0) -> 0 | P71: 0.07643 | Q71: =_xlfn.XLOOKUP(C71,Industry_Benchmark!$A$2:$A$82,Industry_Benchmark!$E$2:$E$82,"") -> 0.076300002 | R71: =P71-Q71 -> 0.000129998 | S71: =IF(R71>0,1,0) -> 1 | T71: 53.237 | U71: =_xlfn.XLOOKUP(C71,Industry_Benchmark!$A$2:$A$82,Industry_Benchmark!$F$2:$F$82,"") -> 118.0908 | V71: =T71-U71 -> -64.8538 | W71: =IF(V71>0,1,0) -> 0 | X71: 0.30563 | Y71: =_xlfn.XLOOKUP(C71,Industry_Benchmark!$A$2:$A$82,Industry_Benchmark!$G$2:$G$82,"") -> 0.305202 | Z71: =X71-Y71 -> 0.000427996 | AA71: =IF(Z71>0,1,0) -> 1 | AB71: =SUM(G71,K71,O71,S71,W71,AA71) -> 3 | AC71: =AB71/6 -> 0.5 | AD71: {=_xlfn.IFS( AB71=6,"Excellent", AB71=5,"Strong", AB71=4,"Good", AB71=3,"Average", AB71<=2,"Weak" )} -> Average
A72: Cisco Systems, Inc. | B72: CSCO | C72: Communication Equipment | D72: 0.2244 | E72: =_xlfn.XLOOKUP(C72,Industry_Benchmark!$A$2:$A$82,Industry_Benchmark!$B$2:$B$82,"") -> 0.1895 | F72: =D72-E72 -> 0.0349 | G72: =IF(F72>0,1,0) -> 1 | H72: 0.081 | I72: =_xlfn.XLOOKUP(C72,Industry_Benchmark!$A$2:$A$82,Industry_Benchmark!$C$2:$C$82,"") -> 0.1045 | J72: =H72-I72 -> -0.0235 | K72: =IF(J72>0,1,0) -> 0 | L72: 1.618 | M72: =_xlfn.XLOOKUP(C72,Industry_Benchmark!$A$2:$A$82,Industry_Benchmark!$D$2:$D$82,"") -> 1.4995 | N72: =L72-M72 -> 0.1185 | O72: =IF(N72>0,1,0) -> 1 | P72: 0.09196 | Q72: =_xlfn.XLOOKUP(C72,Industry_Benchmark!$A$2:$A$82,Industry_Benchmark!$E$2:$E$82,"") -> 0.099320003 | R72: =P72-Q72 -> -0.007360003 | S72: =IF(R72>0,1,0) -> 0 | T72: 25.032 | U72: =_xlfn.XLOOKUP(C72,Industry_Benchmark!$A$2:$A$82,Industry_Benchmark!$F$2:$F$82,"") -> 12.516 | V72: =T72-U72 -> 12.516 | W72: =IF(V72>0,1,0) -> 1 | X72: 0.28190002 | Y72: =_xlfn.XLOOKUP(C72,Industry_Benchmark!$A$2:$A$82,Industry_Benchmark!$G$2:$G$82,"") -> 0.28190002 | Z72: =X72-Y72 -> 0 | AA72: =IF(Z72>0,1,0) -> 0 | AB72: =SUM(G72,K72,O72,S72,W72,AA72) -> 3 | AC72: =AB72/6 -> 0.5 | AD72: {=_xlfn.IFS( AB72=6,"Excellent", AB72=5,"Strong", AB72=4,"Good", AB72=3,"Average", AB72<=2,"Weak" )} -> Average
A73: Comcast Corporation | B73: CMCSA | C73: Entertainment | D73: 0.12731 | E73: =_xlfn.XLOOKUP(C73,Industry_Benchmark!$A$2:$A$82,Industry_Benchmark!$B$2:$B$82,"") -> 0.104315 | F73: =D73-E73 -> 0.022995002 | G73: =IF(F73>0,1,0) -> 1 | H73: 0.187 | I73: =_xlfn.XLOOKUP(C73,Industry_Benchmark!$A$2:$A$82,Industry_Benchmark!$C$2:$C$82,"") -> 0.1755 | J73: =H73-I73 -> 0.0115 | K73: =IF(J73>0,1,0) -> 1 | L73: 1.026 | M73: =_xlfn.XLOOKUP(C73,Industry_Benchmark!$A$2:$A$82,Industry_Benchmark!$D$2:$D$82,"") -> 0.89125 | N73: =L73-M73 -> 0.13475 | O73: =IF(N73>0,1,0) -> 1 | P73: 0.04559 | Q73: =_xlfn.XLOOKUP(C73,Industry_Benchmark!$A$2:$A$82,Industry_Benchmark!$E$2:$E$82,"") -> 0.050625 | R73: =P73-Q73 -> -0.0050350001 | S73: =IF(R73>0,1,0) -> 0 | T73: 104.661 | U73: =_xlfn.XLOOKUP(C73,Industry_Benchmark!$A$2:$A$82,Industry_Benchmark!$F$2:$F$82,"") -> 174.17825 | V73: =T73-U73 -> -69.51725 | W73: =IF(V73>0,1,0) -> 0 | X73: 0.15312 | Y73: =_xlfn.XLOOKUP(C73,Industry_Benchmark!$A$2:$A$82,Industry_Benchmark!$G$2:$G$82,"") -> 0.18733 | Z73: =X73-Y73 -> -0.034210003 | AA73: =IF(Z73>0,1,0) -> 0 | AB73: =SUM(G73,K73,O73,S73,W73,AA73) -> 3 | AC73: =AB73/6 -> 0.5 | AD73: {=_xlfn.IFS( AB73=6,"Excellent", AB73=5,"Strong", AB73=4,"Good", AB73=3,"Average", AB73<=2,"Weak" )} -> Average
A74: Advanced Micro Devices, Inc. | B74: AMD | C74: Semiconductors | D74: 0.19240999 | E74: =_xlfn.XLOOKUP(C74,Industry_Benchmark!$A$2:$A$82,Industry_Benchmark!$B$2:$B$82,"") -> 0.246593 | F74: =D74-E74 -> -0.05418301 | G74: =IF(F74>0,1,0) -> 0 | H74: 0.488 | I74: =_xlfn.XLOOKUP(C74,Industry_Benchmark!$A$2:$A$82,Industry_Benchmark!$C$2:$C$82,"") -> 0.3076 | J74: =H74-I74 -> 0.1804 | K74: =IF(J74>0,1,0) -> 1 | L74: 2.024 | M74: =_xlfn.XLOOKUP(C74,Industry_Benchmark!$A$2:$A$82,Industry_Benchmark!$D$2:$D$82,"") -> 2.9108 | N74: =L74-M74 -> -0.8868 | O74: =IF(N74>0,1,0) -> 0 | P74: 0.21327 | Q74: =_xlfn.XLOOKUP(C74,Industry_Benchmark!$A$2:$A$82,Industry_Benchmark!$E$2:$E$82,"") -> 0.121556 | R74: =P74-Q74 -> 0.091713998 | S74: =IF(R74>0,1,0) -> 1 | T74: 9.764 | U74: =_xlfn.XLOOKUP(C74,Industry_Benchmark!$A$2:$A$82,Industry_Benchmark!$F$2:$F$82,"") -> 77.0734 | V74: =T74-U74 -> -67.3094 | W74: =IF(V74>0,1,0) -> 0 | X74: 0.47428 | Y74: =_xlfn.XLOOKUP(C74,Industry_Benchmark!$A$2:$A$82,Industry_Benchmark!$G$2:$G$82,"") -> 0.375412 | Z74: =X74-Y74 -> 0.098868002 | AA74: =IF(Z74>0,1,0) -> 1 | AB74: =SUM(G74,K74,O74,S74,W74,AA74) -> 3 | AC74: =AB74/6 -> 0.5 | AD74: {=_xlfn.IFS( AB74=6,"Excellent", AB74=5,"Strong", AB74=4,"Good", AB74=3,"Average", AB74<=2,"Weak" )} -> Average
... A91: Autodesk, Inc. | B91: ADSK | C91: Software—Application | D91: 0.31305 | E91: =_xlfn.XLOOKUP(C91,Industry_Benchmark!$A$2:$A$82,Industry_Benchmark!$B$2:$B$82,"") -> 0.171652 | F91: =D91-E91 -> 0.141398 | G91: =IF(F91>0,1,0) -> 1 | H91: 0.182 | I91: =_xlfn.XLOOKUP(C91,Industry_Benchmark!$A$2:$A$82,Industry_Benchmark!$C$2:$C$82,"") -> 0.2806 | J91: =H91-I91 -> -0.0986 | K91: =IF(J91>0,1,0) -> 0 | L91: 0.809 | M91: =_xlfn.XLOOKUP(C91,Industry_Benchmark!$A$2:$A$82,Industry_Benchmark!$D$2:$D$82,"") -> 1.3602 | N91: =L91-M91 -> -0.5512 | O91: =IF(N91>0,1,0) -> 0 | P91: 0.05957 | Q91: =_xlfn.XLOOKUP(C91,Industry_Benchmark!$A$2:$A$82,Industry_Benchmark!$E$2:$E$82,"") -> 0.065944 | R91: =P91-Q91 -> -0.006374 | S91: =IF(R91>0,1,0) -> 0 | T91: 238.261 | U91: =_xlfn.XLOOKUP(C91,Industry_Benchmark!$A$2:$A$82,Industry_Benchmark!$F$2:$F$82,"") -> 73.0736 | V91: =T91-U91 -> 165.1874 | W91: =IF(V91>0,1,0) -> 1 | X91: 1.9555299 | Y91: =_xlfn.XLOOKUP(C91,Industry_Benchmark!$A$2:$A$82,Industry_Benchmark!$G$2:$G$82,"") -> 0.52347798 | Z91: =X91-Y91 -> 1.4320519 | AA91: =IF(Z91>0,1,0) -> 1 | AB91: =SUM(G91,K91,O91,S91,W91,AA91) -> 3 | AC91: =AB91/6 -> 0.5 | AD91: {=_xlfn.IFS( AB91=6,"Excellent", AB91=5,"Strong", AB91=4,"Good", AB91=3,"Average", AB91<=2,"Weak" )} -> Average
A92: Marathon Petroleum Corporation | B92: MPC | C92: Oil & Gas Refining & Marketing | D92: 0.08085 | E92: =_xlfn.XLOOKUP(C92,Industry_Benchmark!$A$2:$A$82,Industry_Benchmark!$B$2:$B$82,"") -> 0.033746667 | F92: =D92-E92 -> 0.047103333 | G92: =IF(F92>0,1,0) -> 1 | H92: 0.967 | I92: =_xlfn.XLOOKUP(C92,Industry_Benchmark!$A$2:$A$82,Industry_Benchmark!$C$2:$C$82,"") -> 1.0683333 | J92: =H92-I92 -> -0.10133333 | K92: =IF(J92>0,1,0) -> 0 | M92: =_xlfn.XLOOKUP(C92,Industry_Benchmark!$A$2:$A$82,Industry_Benchmark!$D$2:$D$82,"") -> 1.202 | N92: =L92-M92 -> -1.202 | O92: =IF(N92>0,1,0) -> 0 | Q92: =_xlfn.XLOOKUP(C92,Industry_Benchmark!$A$2:$A$82,Industry_Benchmark!$E$2:$E$82,"") -> 0.016325 | R92: =P92-Q92 -> -0.016325 | S92: =IF(R92>0,1,0) -> 0 | T92: 79.974 | U92: =_xlfn.XLOOKUP(C92,Industry_Benchmark!$A$2:$A$82,Industry_Benchmark!$F$2:$F$82,"") -> 76.002333 | V92: =T92-U92 -> 3.9716667 | W92: =IF(V92>0,1,0) -> 1 | X92: 0.07715 | Y92: =_xlfn.XLOOKUP(C92,Industry_Benchmark!$A$2:$A$82,Industry_Benchmark!$G$2:$G$82,"") -> 0.072096668 | Z92: =X92-Y92 -> 0.0050533317 | AA92: =IF(Z92>0,1,0) -> 1 | AB92: =SUM(G92,K92,O92,S92,W92,AA92) -> 3 | AC92: =AB92/6 -> 0.5 | AD92: {=_xlfn.IFS( AB92=6,"Excellent", AB92=5,"Strong", AB92=4,"Good", AB92=3,"Average", AB92<=2,"Weak" )} -> Average
A93: Cadence Design Systems, Inc. | B93: CDNS | C93: Software—Application | D93: 0.23297001 | E93: =_xlfn.XLOOKUP(C93,Industry_Benchmark!$A$2:$A$82,Industry_Benchmark!$B$2:$B$82,"") -> 0.171652 | F93: =D93-E93 -> 0.061318006 | G93: =IF(F93>0,1,0) -> 1 | H93: 0.126 | I93: =_xlfn.XLOOKUP(C93,Industry_Benchmark!$A$2:$A$82,Industry_Benchmark!$C$2:$C$82,"") -> 0.2806 | J93: =H93-I93 -> -0.1546 | K93: =IF(J93>0,1,0) -> 0 | L93: 1.701 | M93: =_xlfn.XLOOKUP(C93,Industry_Benchmark!$A$2:$A$82,Industry_Benchmark!$D$2:$D$82,"") -> 1.3602 | N93: =L93-M93 -> 0.3408 | O93: =IF(N93>0,1,0) -> 1 | P93: 0.1164 | Q93: =_xlfn.XLOOKUP(C93,Industry_Benchmark!$A$2:$A$82,Industry_Benchmark!$E$2:$E$82,"") -> 0.065944 | R93: =P93-Q93 -> 0.050456 | S93: =IF(R93>0,1,0) -> 1 | T93: 13.202 | U93: =_xlfn.XLOOKUP(C93,Industry_Benchmark!$A$2:$A$82,Industry_Benchmark!$F$2:$F$82,"") -> 73.0736 | V93: =T93-U93 -> -59.8716 | W93: =IF(V93>0,1,0) -> 0 | X93: 0.27576 | Y93: =_xlfn.XLOOKUP(C93,Industry_Benchmark!$A$2:$A$82,Industry_Benchmark!$G$2:$G$82,"") -> 0.52347798 | Z93: =X93-Y93 -> -0.24771798 | AA93: =IF(Z93>0,1,0) -> 0 | AB93: =SUM(G93,K93,O93,S93,W93,AA93) -> 3 | AC93: =AB93/6 -> 0.5 | AD93: {=_xlfn.IFS( AB93=6,"Excellent", AB93=5,"Strong", AB93=4,"Good", AB93=3,"Average", AB93<=2,"Weak" )} -> Average
A94: Chipotle Mexican Grill, Inc. | B94: CMG | C94: Restaurants | D94: 0.08652 | E94: =_xlfn.XLOOKUP(C94,Industry_Benchmark!$A$2:$A$82,Industry_Benchmark!$B$2:$B$82,"") -> 0.19883251 | F94: =D94-E94 -> -0.11231251 | G94: =IF(F94>0,1,0) -> 0 | H94: 0.22 | I94: =_xlfn.XLOOKUP(C94,Industry_Benchmark!$A$2:$A$82,Industry_Benchmark!$C$2:$C$82,"") -> 0.157 | J94: =H94-I94 -> 0.063 | K94: =IF(J94>0,1,0) -> 1 | L94: 1.581 | M94: =_xlfn.XLOOKUP(C94,Industry_Benchmark!$A$2:$A$82,Industry_Benchmark!$D$2:$D$82,"") -> 1.31375 | N94: =L94-M94 -> 0.26725 | O94: =IF(N94>0,1,0) -> 1 | P94: 0.08207 | Q94: =_xlfn.XLOOKUP(C94,Industry_Benchmark!$A$2:$A$82,Industry_Benchmark!$E$2:$E$82,"") -> 0.1321925 | R94: =P94-Q94 -> -0.050122501 | S94: =IF(R94>0,1,0) -> 0 | T94: 153.232 | U94: =_xlfn.XLOOKUP(C94,Industry_Benchmark!$A$2:$A$82,Industry_Benchmark!$F$2:$F$82,"") -> 38.308 | V94: =T94-U94 -> 114.924 | W94: =IF(V94>0,1,0) -> 1 | X94: 0.30247998 | Y94: =_xlfn.XLOOKUP(C94,Industry_Benchmark!$A$2:$A$82,Industry_Benchmark!$G$2:$G$82,"") -> 0.30247998 | Z94: =X94-Y94 -> 0 | AA94: =IF(Z94>0,1,0) -> 0 | AB94: =SUM(G94,K94,O94,S94,W94,AA94) -> 3 | AC94: =AB94/6 -> 0.5 | AD94: {=_xlfn.IFS( AB94=6,"Excellent", AB94=5,"Strong", AB94=4,"Good", AB94=3,"Average", AB94<=2,"Weak" )} -> Average
A95: AFLAC Incorporated | B95: AFL | C95: Insurance—Life | D95: 0.18766001 | E95: =_xlfn.XLOOKUP(C95,Industry_Benchmark!$A$2:$A$82,Industry_Benchmark!$B$2:$B$82,"") -> 0.13010667 | F95: =D95-E95 -> 0.05755334 | G95: =IF(F95>0,1,0) -> 1 | H95: -0.076 | I95: =_xlfn.XLOOKUP(C95,Industry_Benchmark!$A$2:$A$82,Industry_Benchmark!$C$2:$C$82,"") -> -0.043333333 | J95: =H95-I95 -> -0.032666667 | K95: =IF(J95>0,1,0) -> 0 | L95: 0.684 | M95: =_xlfn.XLOOKUP(C95,Industry_Benchmark!$A$2:$A$82,Industry_Benchmark!$D$2:$D$82,"") -> 0.97266667 | N95: =L95-M95 -> -0.28866667 | O95: =IF(N95>0,1,0) -> 0 | P95: 0.02157 | Q95: =_xlfn.XLOOKUP(C95,Industry_Benchmark!$A$2:$A$82,Industry_Benchmark!$E$2:$E$82,"") -> 0.01178 | R95: =P95-Q95 -> 0.00979 | S95: =IF(R95>0,1,0) -> 1 | T95: 32.579 | U95: =_xlfn.XLOOKUP(C95,Industry_Benchmark!$A$2:$A$82,Industry_Benchmark!$F$2:$F$82,"") -> 81.628667 | V95: =T95-U95 -> -49.049667 | W95: =IF(V95>0,1,0) -> 0 | X95: 0.12836 | Y95: =_xlfn.XLOOKUP(C95,Industry_Benchmark!$A$2:$A$82,Industry_Benchmark!$G$2:$G$82,"") -> 0.10791 | Z95: =X95-Y95 -> 0.020449999 | AA95: =IF(Z95>0,1,0) -> 1 | AB95: =SUM(G95,K95,O95,S95,W95,AA95) -> 3 | AC95: =AB95/6 -> 0.5 | AD95: {=_xlfn.IFS( AB95=6,"Excellent", AB95=5,"Strong", AB95=4,"Good", AB95=3,"Average", AB95<=2,"Weak" )} -> Average
A96: Monster Beverage Corporation | B96: MNST | C96: Beverages—Non-Alcoholic | D96: 0.2876 | E96: =_xlfn.XLOOKUP(C96,Industry_Benchmark!$A$2:$A$82,Industry_Benchmark!$B$2:$B$82,"") -> 0.20897 | F96: =D96-E96 -> 0.078630003 | G96: =IF(F96>0,1,0) -> 1 | H96: 0.132 | I96: =_xlfn.XLOOKUP(C96,Industry_Benchmark!$A$2:$A$82,Industry_Benchmark!$C$2:$C$82,"") -> 0.13633333 | J96: =H96-I96 -> -0.0043333333 | K96: =IF(J96>0,1,0) -> 0 | L96: 4.702 | M96: =_xlfn.XLOOKUP(C96,Industry_Benchmark!$A$2:$A$82,Industry_Benchmark!$D$2:$D$82,"") -> 2.3876667 | N96: =L96-M96 -> 2.3143333 | O96: =IF(N96>0,1,0) -> 1 | P96: 0.16991 | Q96: =_xlfn.XLOOKUP(C96,Industry_Benchmark!$A$2:$A$82,Industry_Benchmark!$E$2:$E$82,"") -> 0.10935333 | R96: =P96-Q96 -> 0.060556665 | S96: =IF(R96>0,1,0) -> 1 | T96: 0.318 | U96: =_xlfn.XLOOKUP(C96,Industry_Benchmark!$A$2:$A$82,Industry_Benchmark!$F$2:$F$82,"") -> 143.72033 | V96: =T96-U96 -> -143.40233 | W96: =IF(V96>0,1,0) -> 0 | X96: 0.28101 | Y96: =_xlfn.XLOOKUP(C96,Industry_Benchmark!$A$2:$A$82,Industry_Benchmark!$G$2:$G$82,"") -> 0.41078666 | Z96: =X96-Y96 -> -0.12977666 | AA96: =IF(Z96>0,1,0) -> 0 | AB96: =SUM(G96,K96,O96,S96,W96,AA96) -> 3 | AC96: =AB96/6 -> 0.5 | AD96: {=_xlfn.IFS( AB96=6,"Excellent", AB96=5,"Strong", AB96=4,"Good", AB96=3,"Average", AB96<=2,"Weak" )} -> Average
A97: MSCI Inc | B97: MSCI | C97: Financial Data & Stock Exchanges | D97: 0.35529 | E97: =_xlfn.XLOOKUP(C97,Industry_Benchmark!$A$2:$A$82,Industry_Benchmark!$B$2:$B$82,"") -> 0.407172 | F97: =D97-E97 -> -0.051881996 | G97: =IF(F97>0,1,0) -> 0 | H97: 0.216 | I97: =_xlfn.XLOOKUP(C97,Industry_Benchmark!$A$2:$A$82,Industry_Benchmark!$C$2:$C$82,"") -> 0.1528 | J97: =H97-I97 -> 0.0632 | K97: =IF(J97>0,1,0) -> 1 | L97: 1.817 | M97: =_xlfn.XLOOKUP(C97,Industry_Benchmark!$A$2:$A$82,Industry_Benchmark!$D$2:$D$82,"") -> 1.5326 | N97: =L97-M97 -> 0.2844 | O97: =IF(N97>0,1,0) -> 1 | P97: 0.14132 | Q97: =_xlfn.XLOOKUP(C97,Industry_Benchmark!$A$2:$A$82,Industry_Benchmark!$E$2:$E$82,"") -> 0.101748 | R97: =P97-Q97 -> 0.039572 | S97: =IF(R97>0,1,0) -> 1 | T97: 0 | U97: =_xlfn.XLOOKUP(C97,Industry_Benchmark!$A$2:$A$82,Industry_Benchmark!$F$2:$F$82,"") -> 95.8734 | V97: =T97-U97 -> -95.8734 | W97: =IF(V97>0,1,0) -> 0 | Y97: =_xlfn.XLOOKUP(C97,Industry_Benchmark!$A$2:$A$82,Industry_Benchmark!$G$2:$G$82,"") -> 0.4871975 | Z97: =X97-Y97 -> -0.4871975 | AA97: =IF(Z97>0,1,0) -> 0 | AB97: =SUM(G97,K97,O97,S97,W97,AA97) -> 3 | AC97: =AB97/6 -> 0.5 | AD97: {=_xlfn.IFS( AB97=6,"Excellent", AB97=5,"Strong", AB97=4,"Good", AB97=3,"Average", AB97<=2,"Weak" )} -> Average
A98: Parker-Hannifin Corporation | B98: PH | C98: Specialty Industrial Machinery | D98: 0.1188 | E98: =_xlfn.XLOOKUP(C98,Industry_Benchmark!$A$2:$A$82,Industry_Benchmark!$B$2:$B$82,"") -> 0.12041 | F98: =D98-E98 -> -0.0016100006 | G98: =IF(F98>0,1,0) -> 0 | H98: 0.121 | I98: =_xlfn.XLOOKUP(C98,Industry_Benchmark!$A$2:$A$82,Industry_Benchmark!$C$2:$C$82,"") -> 0.070857143 | J98: =H98-I98 -> 0.050142857 | K98: =IF(J98>0,1,0) -> 1 | L98: 1.504 | M98: =_xlfn.XLOOKUP(C98,Industry_Benchmark!$A$2:$A$82,Industry_Benchmark!$D$2:$D$82,"") -> 1.469 | N98: =L98-M98 -> 0.035 | O98: =IF(N98>0,1,0) -> 1 | P98: 0.080010004 | Q98: =_xlfn.XLOOKUP(C98,Industry_Benchmark!$A$2:$A$82,Industry_Benchmark!$E$2:$E$82,"") -> 0.066908572 | R98: =P98-Q98 -> 0.013101432 | S98: =IF(R98>0,1,0) -> 1 | T98: 96.395 | U98: =_xlfn.XLOOKUP(C98,Industry_Benchmark!$A$2:$A$82,Industry_Benchmark!$F$2:$F$82,"") -> 107.70214 | V98: =T98-U98 -> -11.307143 | W98: =IF(V98>0,1,0) -> 0 | X98: 0.22874 | Y98: =_xlfn.XLOOKUP(C98,Industry_Benchmark!$A$2:$A$82,Industry_Benchmark!$G$2:$G$82,"") -> 0.26455857 | Z98: =X98-Y98 -> -0.03581857 | AA98: =IF(Z98>0,1,0) -> 0 | AB98: =SUM(G98,K98,O98,S98,W98,AA98) -> 3 | AC98: =AB98/6 -> 0.5 | AD98: {=_xlfn.IFS( AB98=6,"Excellent", AB98=5,"Strong", AB98=4,"Good", AB98=3,"Average", AB98<=2,"Weak" )} -> Average
A99: Dollar Tree, Inc. | B99: DLTR | C99: Discount Stores | D99: 0.05293 | E99: =_xlfn.XLOOKUP(C99,Industry_Benchmark!$A$2:$A$82,Industry_Benchmark!$B$2:$B$82,"") -> 0.047956 | F99: =D99-E99 -> 0.004974 | G99: =IF(F99>0,1,0) -> 1 | H99: 0.039 | I99: =_xlfn.XLOOKUP(C99,Industry_Benchmark!$A$2:$A$82,Industry_Benchmark!$C$2:$C$82,"") -> 0.0764 | J99: =H99-I99 -> -0.0374 | K99: =IF(J99>0,1,0) -> 0 | L99: 1.252 | M99: =_xlfn.XLOOKUP(C99,Industry_Benchmark!$A$2:$A$82,Industry_Benchmark!$D$2:$D$82,"") -> 1.0478 | N99: =L99-M99 -> 0.2042 | O99: =IF(N99>0,1,0) -> 1 | P99: 0.05865 | Q99: =_xlfn.XLOOKUP(C99,Industry_Benchmark!$A$2:$A$82,Industry_Benchmark!$E$2:$E$82,"") -> 0.076300002 | R99: =P99-Q99 -> -0.017650002 | S99: =IF(R99>0,1,0) -> 0 | T99: 134.864 | U99: =_xlfn.XLOOKUP(C99,Industry_Benchmark!$A$2:$A$82,Industry_Benchmark!$F$2:$F$82,"") -> 118.0908 | V99: =T99-U99 -> 16.7732 | W99: =IF(V99>0,1,0) -> 1 | X99: 0.19379999 | Y99: =_xlfn.XLOOKUP(C99,Industry_Benchmark!$A$2:$A$82,Industry_Benchmark!$G$2:$G$82,"") -> 0.305202 | Z99: =X99-Y99 -> -0.11140201 | AA99: =IF(Z99>0,1,0) -> 0 | AB99: =SUM(G99,K99,O99,S99,W99,AA99) -> 3 | AC99: =AB99/6 -> 0.5 | AD99: {=_xlfn.IFS( AB99=6,"Excellent", AB99=5,"Strong", AB99=4,"Good", AB99=3,"Average", AB99<=2,"Weak" )} -> Average
A100: ResMed Inc. | B100: RMD | C100: Medical Instruments & Supplies | D100: 0.14923 | E100: =_xlfn.XLOOKUP(C100,Industry_Benchmark!$A$2:$A$82,Industry_Benchmark!$B$2:$B$82,"") -> 0.1621425 | F100: =D100-E100 -> -0.012912499 | G100: =IF(F100>0,1,0) -> 0 | H100: 0.202 | I100: =_xlfn.XLOOKUP(C100,Industry_Benchmark!$A$2:$A$82,Industry_Benchmark!$C$2:$C$82,"") -> 0.13175 | J100: =H100-I100 -> 0.07025 | K100: =IF(J100>0,1,0) -> 1 | L100: 2.541 | M100: =_xlfn.XLOOKUP(C100,Industry_Benchmark!$A$2:$A$82,Industry_Benchmark!$D$2:$D$82,"") -> 2.83275 | N100: =L100-M100 -> -0.29175 | O100: =IF(N100>0,1,0) -> 0 | P100: 0.12869 | Q100: =_xlfn.XLOOKUP(C100,Industry_Benchmark!$A$2:$A$82,Industry_Benchmark!$E$2:$E$82,"") -> 0.08048 | R100: =P100-Q100 -> 0.04821 | S100: =IF(R100>0,1,0) -> 1 | T100: 31.398 | U100: =_xlfn.XLOOKUP(C100,Industry_Benchmark!$A$2:$A$82,Industry_Benchmark!$F$2:$F$82,"") -> 45.386 | V100: =T100-U100 -> -13.988 | W100: =IF(V100>0,1,0) -> 0 | X100: 0.1752 | Y100: =_xlfn.XLOOKUP(C100,Industry_Benchmark!$A$2:$A$82,Industry_Benchmark!$G$2:$G$82,"") -> 0.1407825 | Z100: =X100-Y100 -> 0.034417499 | AA100: =IF(Z100>0,1,0) -> 1 | AB100: =SUM(G100,K100,O100,S100,W100,AA100) -> 3 | AC100: =AB100/6 -> 0.5 | AD100: {=_xlfn.IFS( AB100=6,"Excellent", AB100=5,"Strong", AB100=4,"Good", AB100=3,"Average", AB100<=2,"Weak" )} -> Average
A101: Arthur J. Gallagher & Co. | B101: AJG | C101: Insurance Brokers | D101: 0.12168 | E101: =_xlfn.XLOOKUP(C101,Industry_Benchmark!$A$2:$A$82,Industry_Benchmark!$B$2:$B$82,"") -> 0.1187 | F101: =D101-E101 -> 0.0029799987 | G101: =IF(F101>0,1,0) -> 1 | H101: 0.165 | I101: =_xlfn.XLOOKUP(C101,Industry_Benchmark!$A$2:$A$82,Industry_Benchmark!$C$2:$C$82,"") -> 0.15366667 | J101: =H101-I101 -> 0.011333333 | K101: =IF(J101>0,1,0) -> 1 | L101: 1.298 | M101: =_xlfn.XLOOKUP(C101,Industry_Benchmark!$A$2:$A$82,Industry_Benchmark!$D$2:$D$82,"") -> 1.2033333 | N101: =L101-M101 -> 0.094666667 | O101: =IF(N101>0,1,0) -> 1 | P101: 0.03556 | Q101: =_xlfn.XLOOKUP(C101,Industry_Benchmark!$A$2:$A$82,Industry_Benchmark!$E$2:$E$82,"") -> 0.054233333 | R101: =P101-Q101 -> -0.018673333 | S101: =IF(R101>0,1,0) -> 0 | T101: 68.386 | U101: =_xlfn.XLOOKUP(C101,Industry_Benchmark!$A$2:$A$82,Industry_Benchmark!$F$2:$F$82,"") -> 199.41467 | V101: =T101-U101 -> -131.02867 | W101: =IF(V101>0,1,0) -> 0 | X101: 0.13818 | Y101: =_xlfn.XLOOKUP(C101,Industry_Benchmark!$A$2:$A$82,Industry_Benchmark!$G$2:$G$82,"") -> 0.25839667 | Z101: =X101-Y101 -> -0.12021667 | AA101: =IF(Z101>0,1,0) -> 0 | AB101: =SUM(G101,K101,O101,S101,W101,AA101) -> 3 | AC101: =AB101/6 -> 0.5 | AD101: {=_xlfn.IFS( AB101=6,"Excellent", AB101=5,"Strong", AB101=4,"Good", AB101=3,"Average", AB101<=2,"Weak" )} -> Average
A102: Alphabet Inc. | B102: GOOG | C102: Internet Content & Information | D102: 0.29512 | E102: =_xlfn.XLOOKUP(C102,Industry_Benchmark!$A$2:$A$82,Industry_Benchmark!$B$2:$B$82,"") -> 0.30802666 | F102: =D102-E102 -> -0.01290666 | G102: =IF(F102>0,1,0) -> 0 | H102: 0.324 | I102: =_xlfn.XLOOKUP(C102,Industry_Benchmark!$A$2:$A$82,Industry_Benchmark!$C$2:$C$82,"") -> 0.28233333 | J102: =H102-I102 -> 0.041666667 | K102: =IF(J102>0,1,0) -> 1 | L102: 2.928 | M102: =_xlfn.XLOOKUP(C102,Industry_Benchmark!$A$2:$A$82,Industry_Benchmark!$D$2:$D$82,"") -> 3.0033333 | N102: =L102-M102 -> -0.075333333 | O102: =IF(N102>0,1,0) -> 0 | P102: 0.14493 | Q102: =_xlfn.XLOOKUP(C102,Industry_Benchmark!$A$2:$A$82,Industry_Benchmark!$E$2:$E$82,"") -> 0.15650334 | R102: =P102-Q102 -> -0.011573337 | S102: =IF(R102>0,1,0) -> 0 | T102: 11.329 | U102: =_xlfn.XLOOKUP(C102,Industry_Benchmark!$A$2:$A$82,Industry_Benchmark!$F$2:$F$82,"") -> 11.410667 | V102: =T102-U102 -> -0.081666667 | W102: =IF(V102>0,1,0) -> 0 | X102: 0.32069 | Y102: =_xlfn.XLOOKUP(C102,Industry_Benchmark!$A$2:$A$82,Industry_Benchmark!$G$2:$G$82,"") -> 0.31746667 | Z102: =X102-Y102 -> 0.0032233333 | AA102: =IF(Z102>0,1,0) -> 1 | AB102: =SUM(G102,K102,O102,S102,W102,AA102) -> 2 | AC102: =AB102/6 -> 0.33333333 | AD102: {=_xlfn.IFS( AB102=6,"Excellent", AB102=5,"Strong", AB102=4,"Good", AB102=3,"Average", AB102<=2,"Weak" )} -> Weak
A103: Alphabet Inc. | B103: GOOGL | C103: Internet Content & Information | D103: 0.29512 | E103: =_xlfn.XLOOKUP(C103,Industry_Benchmark!$A$2:$A$82,Industry_Benchmark!$B$2:$B$82,"") -> 0.30802666 | F103: =D103-E103 -> -0.01290666 | G103: =IF(F103>0,1,0) -> 0 | H103: 0.324 | I103: =_xlfn.XLOOKUP(C103,Industry_Benchmark!$A$2:$A$82,Industry_Benchmark!$C$2:$C$82,"") -> 0.28233333 | J103: =H103-I103 -> 0.041666667 | K103: =IF(J103>0,1,0) -> 1 | L103: 2.928 | M103: =_xlfn.XLOOKUP(C103,Industry_Benchmark!$A$2:$A$82,Industry_Benchmark!$D$2:$D$82,"") -> 3.0033333 | N103: =L103-M103 -> -0.075333333 | O103: =IF(N103>0,1,0) -> 0 | P103: 0.14493 | Q103: =_xlfn.XLOOKUP(C103,Industry_Benchmark!$A$2:$A$82,Industry_Benchmark!$E$2:$E$82,"") -> 0.15650334 | R103: =P103-Q103 -> -0.011573337 | S103: =IF(R103>0,1,0) -> 0 | T103: 11.329 | U103: =_xlfn.XLOOKUP(C103,Industry_Benchmark!$A$2:$A$82,Industry_Benchmark!$F$2:$F$82,"") -> 11.410667 | V103: =T103-U103 -> -0.081666667 | W103: =IF(V103>0,1,0) -> 0 | X103: 0.32069 | Y103: =_xlfn.XLOOKUP(C103,Industry_Benchmark!$A$2:$A$82,Industry_Benchmark!$G$2:$G$82,"") -> 0.31746667 | Z103: =X103-Y103 -> 0.0032233333 | AA103: =IF(Z103>0,1,0) -> 1 | AB103: =SUM(G103,K103,O103,S103,W103,AA103) -> 2 | AC103: =AB103/6 -> 0.33333333 | AD103: {=_xlfn.IFS( AB103=6,"Excellent", AB103=5,"Strong", AB103=4,"Good", AB103=3,"Average", AB103<=2,"Weak" )} -> Weak
A104: Amazon.com, Inc. | B104: AMZN | C104: Internet Retail | D104: 0.07101 | E104: =_xlfn.XLOOKUP(C104,Industry_Benchmark!$A$2:$A$82,Industry_Benchmark!$B$2:$B$82,"") -> 0.57075 | F104: =D104-E104 -> -0.49974 | G104: =IF(F104>0,1,0) -> 0 | H104: 0.094 | I104: =_xlfn.XLOOKUP(C104,Industry_Benchmark!$A$2:$A$82,Industry_Benchmark!$C$2:$C$82,"") -> 0.101 | J104: =H104-I104 -> -0.007 | K104: =IF(J104>0,1,0) -> 0 | L104: 1.136 | M104: =_xlfn.XLOOKUP(C104,Industry_Benchmark!$A$2:$A$82,Industry_Benchmark!$D$2:$D$82,"") -> 2.2445 | N104: =L104-M104 -> -1.1085 | O104: =IF(N104>0,1,0) -> 0 | P104: 0.041929998 | Q104: =_xlfn.XLOOKUP(C104,Industry_Benchmark!$A$2:$A$82,Industry_Benchmark!$E$2:$E$82,"") -> 0.059479999 | R104: =P104-Q104 -> -0.017550001 | S104: =IF(R104>0,1,0) -> 0 | T104: 100.864 | U104: =_xlfn.XLOOKUP(C104,Industry_Benchmark!$A$2:$A$82,Industry_Benchmark!$F$2:$F$82,"") -> 92.949 | V104: =T104-U104 -> 7.915 | W104: =IF(V104>0,1,0) -> 1 | X104: 0.28806 | Y104: =_xlfn.XLOOKUP(C104,Industry_Benchmark!$A$2:$A$82,Industry_Benchmark!$G$2:$G$82,"") -> 0.28625999 | Z104: =X104-Y104 -> 0.00180001 | AA104: =IF(Z104>0,1,0) -> 1 | AB104: =SUM(G104,K104,O104,S104,W104,AA104) -> 2 | AC104: =AB104/6 -> 0.33333333 | AD104: {=_xlfn.IFS( AB104=6,"Excellent", AB104=5,"Strong", AB104=4,"Good", AB104=3,"Average", AB104<=2,"Weak" )} -> Weak
A105: Exxon Mobil Corporation | B105: XOM | C105: Oil & Gas Integrated | D105: 0.08259 | E105: =_xlfn.XLOOKUP(C105,Industry_Benchmark!$A$2:$A$82,Industry_Benchmark!$B$2:$B$82,"") -> 0.091500005 | F105: =D105-E105 -> -0.008910005 | G105: =IF(F105>0,1,0) -> 0 | H105: 0.794 | I105: =_xlfn.XLOOKUP(C105,Industry_Benchmark!$A$2:$A$82,Industry_Benchmark!$C$2:$C$82,"") -> 0.82 | J105: =H105-I105 -> -0.026 | K105: =IF(J105>0,1,0) -> 0 | L105: 1.044 | M105: =_xlfn.XLOOKUP(C105,Industry_Benchmark!$A$2:$A$82,Industry_Benchmark!$D$2:$D$82,"") -> 1.044 | N105: =L105-M105 -> 0 | O105: =IF(N105>0,1,0) -> 0 | P105: 0.049840003 | Q105: =_xlfn.XLOOKUP(C105,Industry_Benchmark!$A$2:$A$82,Industry_Benchmark!$E$2:$E$82,"") -> 0.049840003 | R105: =P105-Q105 -> 0 | S105: =IF(R105>0,1,0) -> 0 | T105: 30.184 | U105: =_xlfn.XLOOKUP(C105,Industry_Benchmark!$A$2:$A$82,Industry_Benchmark!$F$2:$F$82,"") -> 28.75 | V105: =T105-U105 -> 1.434 | W105: =IF(V105>0,1,0) -> 1 | X105: 0.13889 | Y105: =_xlfn.XLOOKUP(C105,Industry_Benchmark!$A$2:$A$82,Industry_Benchmark!$G$2:$G$82,"") -> 0.12767 | Z105: =X105-Y105 -> 0.011219998 | AA105: =IF(Z105>0,1,0) -> 1 | AB105: =SUM(G105,K105,O105,S105,W105,AA105) -> 2 | AC105: =AB105/6 -> 0.33333333 | AD105: {=_xlfn.IFS( AB105=6,"Excellent", AB105=5,"Strong", AB105=4,"Good", AB105=3,"Average", AB105<=2,"Weak" )} -> Weak
A106: Chevron Corporation | B106: CVX | C106: Oil & Gas Integrated | D106: 0.10041001 | E106: =_xlfn.XLOOKUP(C106,Industry_Benchmark!$A$2:$A$82,Industry_Benchmark!$B$2:$B$82,"") -> 0.091500005 | F106: =D106-E106 -> 0.008910005 | G106: =IF(F106>0,1,0) -> 1 | H106: 0.846 | I106: =_xlfn.XLOOKUP(C106,Industry_Benchmark!$A$2:$A$82,Industry_Benchmark!$C$2:$C$82,"") -> 0.82 | J106: =H106-I106 -> 0.026 | K106: =IF(J106>0,1,0) -> 1 | M106: =_xlfn.XLOOKUP(C106,Industry_Benchmark!$A$2:$A$82,Industry_Benchmark!$D$2:$D$82,"") -> 1.044 | N106: =L106-M106 -> -1.044 | O106: =IF(N106>0,1,0) -> 0 | Q106: =_xlfn.XLOOKUP(C106,Industry_Benchmark!$A$2:$A$82,Industry_Benchmark!$E$2:$E$82,"") -> 0.049840003 | R106: =P106-Q106 -> -0.049840003 | S106: =IF(R106>0,1,0) -> 0 | T106: 27.316 | U106: =_xlfn.XLOOKUP(C106,Industry_Benchmark!$A$2:$A$82,Industry_Benchmark!$F$2:$F$82,"") -> 28.75 | V106: =T106-U106 -> -1.434 | W106: =IF(V106>0,1,0) -> 0 | X106: 0.11645 | Y106: =_xlfn.XLOOKUP(C106,Industry_Benchmark!$A$2:$A$82,Industry_Benchmark!$G$2:$G$82,"") -> 0.12767 | Z106: =X106-Y106 -> -0.011219998 | AA106: =IF(Z106>0,1,0) -> 0 | AB106: =SUM(G106,K106,O106,S106,W106,AA106) -> 2 | AC106: =AB106/6 -> 0.33333333 | AD106: {=_xlfn.IFS( AB106=6,"Excellent", AB106=5,"Strong", AB106=4,"Good", AB106=3,"Average", AB106<=2,"Weak" )} -> Weak
A107: Pfizer, Inc. | B107: PFE | C107: Drug Manufacturers—General | D107: 0.28684 | E107: =_xlfn.XLOOKUP(C107,Industry_Benchmark!$A$2:$A$82,Industry_Benchmark!$B$2:$B$82,"") -> 0.21304125 | F107: =D107-E107 -> 0.07379875 | G107: =IF(F107>0,1,0) -> 1 | H107: 1.344 | I107: =_xlfn.XLOOKUP(C107,Industry_Benchmark!$A$2:$A$82,Industry_Benchmark!$C$2:$C$82,"") -> 0.270125 | J107: =H107-I107 -> 1.073875 | K107: =IF(J107>0,1,0) -> 1 | L107: 1.385 | M107: =_xlfn.XLOOKUP(C107,Industry_Benchmark!$A$2:$A$82,Industry_Benchmark!$D$2:$D$82,"") -> 1.4105714 | N107: =L107-M107 -> -0.025571429 | O107: =IF(N107>0,1,0) -> 0 | P107: 0.07777 | Q107: =_xlfn.XLOOKUP(C107,Industry_Benchmark!$A$2:$A$82,Industry_Benchmark!$E$2:$E$82,"") -> 0.095184286 | R107: =P107-Q107 -> -0.017414286 | S107: =IF(R107>0,1,0) -> 0 | T107: 52.496 | U107: =_xlfn.XLOOKUP(C107,Industry_Benchmark!$A$2:$A$82,Industry_Benchmark!$F$2:$F$82,"") -> 212.024 | V107: =T107-U107 -> -159.528 | W107: =IF(V107>0,1,0) -> 0 | X107: 0.27747 | Y107: =_xlfn.XLOOKUP(C107,Industry_Benchmark!$A$2:$A$82,Industry_Benchmark!$G$2:$G$82,"") -> 0.47294626 | Z107: =X107-Y107 -> -0.19547626 | AA107: =IF(Z107>0,1,0) -> 0 | AB107: =SUM(G107,K107,O107,S107,W107,AA107) -> 2 | AC107: =AB107/6 -> 0.33333333 | AD107: {=_xlfn.IFS( AB107=6,"Excellent", AB107=5,"Strong", AB107=4,"Good", AB107=3,"Average", AB107<=2,"Weak" )} -> Weak
A108: AbbVie Inc. | B108: ABBV | C108: Drug Manufacturers—General | D108: 0.20538001 | E108: =_xlfn.XLOOKUP(C108,Industry_Benchmark!$A$2:$A$82,Industry_Benchmark!$B$2:$B$82,"") -> 0.21304125 | F108: =D108-E108 -> -0.00766124 | G108: =IF(F108>0,1,0) -> 0 | H108: 0.074 | I108: =_xlfn.XLOOKUP(C108,Industry_Benchmark!$A$2:$A$82,Industry_Benchmark!$C$2:$C$82,"") -> 0.270125 | J108: =H108-I108 -> -0.196125 | K108: =IF(J108>0,1,0) -> 0 | M108: =_xlfn.XLOOKUP(C108,Industry_Benchmark!$A$2:$A$82,Industry_Benchmark!$D$2:$D$82,"") -> 1.4105714 | N108: =L108-M108 -> -1.4105714 | O108: =IF(N108>0,1,0) -> 0 | Q108: =_xlfn.XLOOKUP(C108,Industry_Benchmark!$A$2:$A$82,Industry_Benchmark!$E$2:$E$82,"") -> 0.095184286 | R108: =P108-Q108 -> -0.095184286 | S108: =IF(R108>0,1,0) -> 0 | T108: 594.66 | U108: =_xlfn.XLOOKUP(C108,Industry_Benchmark!$A$2:$A$82,Industry_Benchmark!$F$2:$F$82,"") -> 212.024 | V108: =T108-U108 -> 382.636 | W108: =IF(V108>0,1,0) -> 1 | X108: 0.86594003 | Y108: =_xlfn.XLOOKUP(C108,Industry_Benchmark!$A$2:$A$82,Industry_Benchmark!$G$2:$G$82,"") -> 0.47294626 | Z108: =X108-Y108 -> 0.39299377 | AA108: =IF(Z108>0,1,0) -> 1 | AB108: =SUM(G108,K108,O108,S108,W108,AA108) -> 2 | AC108: =AB108/6 -> 0.33333333 | AD108: {=_xlfn.IFS( AB108=6,"Excellent", AB108=5,"Strong", AB108=4,"Good", AB108=3,"Average", AB108<=2,"Weak" )} -> Weak
A109: Walt Disney Company (The) | B109: DIS | C109: Entertainment | D109: 0.029590001 | E109: =_xlfn.XLOOKUP(C109,Industry_Benchmark!$A$2:$A$82,Industry_Benchmark!$B$2:$B$82,"") -> 0.104315 | F109: =D109-E109 -> -0.074724997 | G109: =IF(F109>0,1,0) -> 0 | H109: 0.26 | I109: =_xlfn.XLOOKUP(C109,Industry_Benchmark!$A$2:$A$82,Industry_Benchmark!$C$2:$C$82,"") -> 0.1755 | J109: =H109-I109 -> 0.0845 | K109: =IF(J109>0,1,0) -> 1 | L109: 1.083 | M109: =_xlfn.XLOOKUP(C109,Industry_Benchmark!$A$2:$A$82,Industry_Benchmark!$D$2:$D$82,"") -> 0.89125 | N109: =L109-M109 -> 0.19175 | O109: =IF(N109>0,1,0) -> 1 | P109: 0.01077 | Q109: =_xlfn.XLOOKUP(C109,Industry_Benchmark!$A$2:$A$82,Industry_Benchmark!$E$2:$E$82,"") -> 0.050625 | R109: =P109-Q109 -> -0.039855 | S109: =IF(R109>0,1,0) -> 0 | T109: 57.044 | U109: =_xlfn.XLOOKUP(C109,Industry_Benchmark!$A$2:$A$82,Industry_Benchmark!$F$2:$F$82,"") -> 174.17825 | V109: =T109-U109 -> -117.13425 | W109: =IF(V109>0,1,0) -> 0 | X109: 0.025390001 | Y109: =_xlfn.XLOOKUP(C109,Industry_Benchmark!$A$2:$A$82,Industry_Benchmark!$G$2:$G$82,"") -> 0.18733 | Z109: =X109-Y109 -> -0.16194 | AA109: =IF(Z109>0,1,0) -> 0 | AB109: =SUM(G109,K109,O109,S109,W109,AA109) -> 2 | AC109: =AB109/6 -> 0.33333333 | AD109: {=_xlfn.IFS( AB109=6,"Excellent", AB109=5,"Strong", AB109=4,"Good", AB109=3,"Average", AB109<=2,"Weak" )} -> Weak
A110: Pepsico, Inc. | B110: PEP | C110: Beverages—Non-Alcoholic | D110: 0.10617 | E110: =_xlfn.XLOOKUP(C110,Industry_Benchmark!$A$2:$A$82,Industry_Benchmark!$B$2:$B$82,"") -> 0.20897 | F110: =D110-E110 -> -0.1028 | G110: =IF(F110>0,1,0) -> 0 | H110: 0.116 | I110: =_xlfn.XLOOKUP(C110,Industry_Benchmark!$A$2:$A$82,Industry_Benchmark!$C$2:$C$82,"") -> 0.13633333 | J110: =H110-I110 -> -0.020333333 | K110: =IF(J110>0,1,0) -> 0 | L110: 0.945 | M110: =_xlfn.XLOOKUP(C110,Industry_Benchmark!$A$2:$A$82,Industry_Benchmark!$D$2:$D$82,"") -> 2.3876667 | N110: =L110-M110 -> -1.4426667 | O110: =IF(N110>0,1,0) -> 0 | P110: 0.079840004 | Q110: =_xlfn.XLOOKUP(C110,Industry_Benchmark!$A$2:$A$82,Industry_Benchmark!$E$2:$E$82,"") -> 0.10935333 | R110: =P110-Q110 -> -0.029513331 | S110: =IF(R110>0,1,0) -> 0 | T110: 258.017 | U110: =_xlfn.XLOOKUP(C110,Industry_Benchmark!$A$2:$A$82,Industry_Benchmark!$F$2:$F$82,"") -> 143.72033 | V110: =T110-U110 -> 114.29667 | W110: =IF(V110>0,1,0) -> 1 | X110: 0.55412996 | Y110: =_xlfn.XLOOKUP(C110,Industry_Benchmark!$A$2:$A$82,Industry_Benchmark!$G$2:$G$82,"") -> 0.41078666 | Z110: =X110-Y110 -> 0.1433433 | AA110: =IF(Z110>0,1,0) -> 1 | AB110: =SUM(G110,K110,O110,S110,W110,AA110) -> 2 | AC110: =AB110/6 -> 0.33333333 | AD110: {=_xlfn.IFS( AB110=6,"Excellent", AB110=5,"Strong", AB110=4,"Good", AB110=3,"Average", AB110<=2,"Weak" )} -> Weak
A111: Danaher Corporation | B111: DHR | C111: Diagnostics & Research | D111: 0.21841 | E111: =_xlfn.XLOOKUP(C111,Industry_Benchmark!$A$2:$A$82,Industry_Benchmark!$B$2:$B$82,"") -> 0.18452167 | F111: =D111-E111 -> 0.03388833 | G111: =IF(F111>0,1,0) -> 1 | H111: 0.205 | I111: =_xlfn.XLOOKUP(C111,Industry_Benchmark!$A$2:$A$82,Industry_Benchmark!$C$2:$C$82,"") -> 0.17683333 | J111: =H111-I111 -> 0.028166667 | K111: =IF(J111>0,1,0) -> 1 | L111: 1.431 | M111: =_xlfn.XLOOKUP(C111,Industry_Benchmark!$A$2:$A$82,Industry_Benchmark!$D$2:$D$82,"") -> 1.6713333 | N111: =L111-M111 -> -0.24033333 | O111: =IF(N111>0,1,0) -> 0 | P111: 0.06407 | Q111: =_xlfn.XLOOKUP(C111,Industry_Benchmark!$A$2:$A$82,Industry_Benchmark!$E$2:$E$82,"") -> 0.091146667 | R111: =P111-Q111 -> -0.027076667 | S111: =IF(R111>0,1,0) -> 0 | T111: 51.513 | U111: =_xlfn.XLOOKUP(C111,Industry_Benchmark!$A$2:$A$82,Industry_Benchmark!$F$2:$F$82,"") -> 96.502167 | V111: =T111-U111 -> -44.989167 | W111: =IF(V111>0,1,0) -> 0 | X111: 0.14942001 | Y111: =_xlfn.XLOOKUP(C111,Industry_Benchmark!$A$2:$A$82,Industry_Benchmark!$G$2:$G$82,"") -> 0.32766499 | Z111: =X111-Y111 -> -0.17824498 | AA111: =IF(Z111>0,1,0) -> 0 | AB111: =SUM(G111,K111,O111,S111,W111,AA111) -> 2 | AC111: =AB111/6 -> 0.33333333 | AD111: {=_xlfn.IFS( AB111=6,"Excellent", AB111=5,"Strong", AB111=4,"Good", AB111=3,"Average", AB111<=2,"Weak" )} -> Weak
A112: Adobe Inc. | B112: ADBE | C112: Software—Infrastructure | D112: 0.30548 | E112: =_xlfn.XLOOKUP(C112,Industry_Benchmark!$A$2:$A$82,Industry_Benchmark!$B$2:$B$82,"") -> 0.263494 | F112: =D112-E112 -> 0.041985998 | G112: =IF(F112>0,1,0) -> 1 | H112: 0.2 | I112: =_xlfn.XLOOKUP(C112,Industry_Benchmark!$A$2:$A$82,Industry_Benchmark!$C$2:$C$82,"") -> 0.2198 | J112: =H112-I112 -> -0.0198 | K112: =IF(J112>0,1,0) -> 0 | L112: 1.248 | M112: =_xlfn.XLOOKUP(C112,Industry_Benchmark!$A$2:$A$82,Industry_Benchmark!$D$2:$D$82,"") -> 1.6274 | N112: =L112-M112 -> -0.3794 | O112: =IF(N112>0,1,0) -> 0 | P112: 0.14076 | Q112: =_xlfn.XLOOKUP(C112,Industry_Benchmark!$A$2:$A$82,Industry_Benchmark!$E$2:$E$82,"") -> 0.107218 | R112: =P112-Q112 -> 0.033542002 | S112: =IF(R112>0,1,0) -> 1 | T112: 31.581 | U112: =_xlfn.XLOOKUP(C112,Industry_Benchmark!$A$2:$A$82,Industry_Benchmark!$F$2:$F$82,"") -> 37.3778 | V112: =T112-U112 -> -5.7968 | W112: =IF(V112>0,1,0) -> 0 | X112: 0.34368 | Y112: =_xlfn.XLOOKUP(C112,Industry_Benchmark!$A$2:$A$82,Industry_Benchmark!$G$2:$G$82,"") -> 0.40269749 | Z112: =X112-Y112 -> -0.05901749 | AA112: =IF(Z112>0,1,0) -> 0 | AB112: =SUM(G112,K112,O112,S112,W112,AA112) -> 2 | AC112: =AB112/6 -> 0.33333333 | AD112: {=_xlfn.IFS( AB112=6,"Excellent", AB112=5,"Strong", AB112=4,"Good", AB112=3,"Average", AB112<=2,"Weak" )} -> Weak
A113: McDonald's Corporation | B113: MCD | C113: Restaurants | D113: 0.32490003 | E113: =_xlfn.XLOOKUP(C113,Industry_Benchmark!$A$2:$A$82,Industry_Benchmark!$B$2:$B$82,"") -> 0.19883251 | F113: =D113-E113 -> 0.12606752 | G113: =IF(F113>0,1,0) -> 1 | H113: 0.131 | I113: =_xlfn.XLOOKUP(C113,Industry_Benchmark!$A$2:$A$82,Industry_Benchmark!$C$2:$C$82,"") -> 0.157 | J113: =H113-I113 -> -0.026 | K113: =IF(J113>0,1,0) -> 0 | L113: 1.778 | M113: =_xlfn.XLOOKUP(C113,Industry_Benchmark!$A$2:$A$82,Industry_Benchmark!$D$2:$D$82,"") -> 1.31375 | N113: =L113-M113 -> 0.46425 | O113: =IF(N113>0,1,0) -> 1 | P113: 0.1159 | Q113: =_xlfn.XLOOKUP(C113,Industry_Benchmark!$A$2:$A$82,Industry_Benchmark!$E$2:$E$82,"") -> 0.1321925 | R113: =P113-Q113 -> -0.016292501 | S113: =IF(R113>0,1,0) -> 0 | T113: 0 | U113: =_xlfn.XLOOKUP(C113,Industry_Benchmark!$A$2:$A$82,Industry_Benchmark!$F$2:$F$82,"") -> 38.308 | V113: =T113-U113 -> -38.308 | W113: =IF(V113>0,1,0) -> 0 | Y113: =_xlfn.XLOOKUP(C113,Industry_Benchmark!$A$2:$A$82,Industry_Benchmark!$G$2:$G$82,"") -> 0.30247998 | Z113: =X113-Y113 -> -0.30247998 | AA113: =IF(Z113>0,1,0) -> 0 | AB113: =SUM(G113,K113,O113,S113,W113,AA113) -> 2 | AC113: =AB113/6 -> 0.33333333 | AD113: {=_xlfn.IFS( AB113=6,"Excellent", AB113=5,"Strong", AB113=4,"Good", AB113=3,"Average", AB113<=2,"Weak" )} -> Weak
A114: T-Mobile US, Inc. | B114: TMUS | C114: Telecom Services | D114: 0.03774 | E114: =_xlfn.XLOOKUP(C114,Industry_Benchmark!$A$2:$A$82,Industry_Benchmark!$B$2:$B$82,"") -> 0.06952667 | F114: =D114-E114 -> -0.03178667 | G114: =IF(F114>0,1,0) -> 0 | H114: 0.022 | I114: =_xlfn.XLOOKUP(C114,Industry_Benchmark!$A$2:$A$82,Industry_Benchmark!$C$2:$C$82,"") -> 0.0026666667 | J114: =H114-I114 -> 0.019333333 | K114: =IF(J114>0,1,0) -> 1 | L114: 0.889 | M114: =_xlfn.XLOOKUP(C114,Industry_Benchmark!$A$2:$A$82,Industry_Benchmark!$D$2:$D$82,"") -> 0.85466667 | N114: =L114-M114 -> 0.034333333 | O114: =IF(N114>0,1,0) -> 1 | P114: 0.03071 | Q114: =_xlfn.XLOOKUP(C114,Industry_Benchmark!$A$2:$A$82,Industry_Benchmark!$E$2:$E$82,"") -> 0.044393333 | R114: =P114-Q114 -> -0.013683333 | S114: =IF(R114>0,1,0) -> 0 | T114: 157.473 | U114: =_xlfn.XLOOKUP(C114,Industry_Benchmark!$A$2:$A$82,Industry_Benchmark!$F$2:$F$82,"") -> 167.02767 | V114: =T114-U114 -> -9.5546667 | W114: =IF(V114>0,1,0) -> 0 | X114: 0.04498 | Y114: =_xlfn.XLOOKUP(C114,Industry_Benchmark!$A$2:$A$82,Industry_Benchmark!$G$2:$G$82,"") -> 0.12344333 | Z114: =X114-Y114 -> -0.078463333 | AA114: =IF(Z114>0,1,0) -> 0 | AB114: =SUM(G114,K114,O114,S114,W114,AA114) -> 2 | AC114: =AB114/6 -> 0.33333333 | AD114: {=_xlfn.IFS( AB114=6,"Excellent", AB114=5,"Strong", AB114=4,"Good", AB114=3,"Average", AB114<=2,"Weak" )} -> Weak
A115: Caterpillar, Inc. | B115: CAT | C115: Farm & Heavy Construction Machinery | D115: 0.12731 | E115: =_xlfn.XLOOKUP(C115,Industry_Benchmark!$A$2:$A$82,Industry_Benchmark!$B$2:$B$82,"") -> 0.131485 | F115: =D115-E115 -> -0.004175 | G115: =IF(F115>0,1,0) -> 0 | H115: 0.228 | I115: =_xlfn.XLOOKUP(C115,Industry_Benchmark!$A$2:$A$82,Industry_Benchmark!$C$2:$C$82,"") -> 0.194 | J115: =H115-I115 -> 0.034 | K115: =IF(J115>0,1,0) -> 1 | L115: 1.456 | M115: =_xlfn.XLOOKUP(C115,Industry_Benchmark!$A$2:$A$82,Industry_Benchmark!$D$2:$D$82,"") -> 1.824 | N115: =L115-M115 -> -0.368 | O115: =IF(N115>0,1,0) -> 0 | P115: 0.05336 | Q115: =_xlfn.XLOOKUP(C115,Industry_Benchmark!$A$2:$A$82,Industry_Benchmark!$E$2:$E$82,"") -> 0.058455 | R115: =P115-Q115 -> -0.005095 | S115: =IF(R115>0,1,0) -> 0 | T115: 228.802 | U115: =_xlfn.XLOOKUP(C115,Industry_Benchmark!$A$2:$A$82,Industry_Benchmark!$F$2:$F$82,"") -> 246.833 | V115: =T115-U115 -> -18.031 | W115: =IF(V115>0,1,0) -> 0 | X115: 0.40715998 | Y115: =_xlfn.XLOOKUP(C115,Industry_Benchmark!$A$2:$A$82,Industry_Benchmark!$G$2:$G$82,"") -> 0.39367999 | Z115: =X115-Y115 -> 0.01347999 | AA115: =IF(Z115>0,1,0) -> 1 | AB115: =SUM(G115,K115,O115,S115,W115,AA115) -> 2 | AC115: =AB115/6 -> 0.33333333 | AD115: {=_xlfn.IFS( AB115=6,"Excellent", AB115=5,"Strong", AB115=4,"Good", AB115=3,"Average", AB115<=2,"Weak" )} -> Weak
A116: International Business Machines | B116: IBM | C116: Information Technology Services | D116: 0.06401 | E116: =_xlfn.XLOOKUP(C116,Industry_Benchmark!$A$2:$A$82,Industry_Benchmark!$B$2:$B$82,"") -> 0.08144 | F116: =D116-E116 -> -0.01743 | G116: =IF(F116>0,1,0) -> 0 | H116: 0.003 | I116: =_xlfn.XLOOKUP(C116,Industry_Benchmark!$A$2:$A$82,Industry_Benchmark!$C$2:$C$82,"") -> 0.1248 | J116: =H116-I116 -> -0.1218 | K116: =IF(J116>0,1,0) -> 0 | L116: 0.836 | M116: =_xlfn.XLOOKUP(C116,Industry_Benchmark!$A$2:$A$82,Industry_Benchmark!$D$2:$D$82,"") -> 1.1856 | N116: =L116-M116 -> -0.3496 | O116: =IF(N116>0,1,0) -> 0 | P116: 0.03739 | Q116: =_xlfn.XLOOKUP(C116,Industry_Benchmark!$A$2:$A$82,Industry_Benchmark!$E$2:$E$82,"") -> 0.058694001 | R116: =P116-Q116 -> -0.021304001 | S116: =IF(R116>0,1,0) -> 0 | T116: 263.801 | U116: =_xlfn.XLOOKUP(C116,Industry_Benchmark!$A$2:$A$82,Industry_Benchmark!$F$2:$F$82,"") -> 80.5094 | V116: =T116-U116 -> 183.2916 | W116: =IF(V116>0,1,0) -> 1 | X116: 0.21405001 | Y116: =_xlfn.XLOOKUP(C116,Industry_Benchmark!$A$2:$A$82,Industry_Benchmark!$G$2:$G$82,"") -> 0.15424 | Z116: =X116-Y116 -> 0.05981001 | AA116: =IF(Z116>0,1,0) -> 1 | AB116: =SUM(G116,K116,O116,S116,W116,AA116) -> 2 | AC116: =AB116/6 -> 0.33333333 | AD116: {=_xlfn.IFS( AB116=6,"Excellent", AB116=5,"Strong", AB116=4,"Good", AB116=3,"Average", AB116<=2,"Weak" )} -> Weak
A117: General Electric Company | B117: GE | C117: Specialty Industrial Machinery | D117: -0.00052 | E117: =_xlfn.XLOOKUP(C117,Industry_Benchmark!$A$2:$A$82,Industry_Benchmark!$B$2:$B$82,"") -> 0.12041 | F117: =D117-E117 -> -0.12093 | G117: =IF(F117>0,1,0) -> 0 | H117: -0.005 | I117: =_xlfn.XLOOKUP(C117,Industry_Benchmark!$A$2:$A$82,Industry_Benchmark!$C$2:$C$82,"") -> 0.070857143 | J117: =H117-I117 -> -0.075857143 | K117: =IF(J117>0,1,0) -> 0 | L117: 1.796 | M117: =_xlfn.XLOOKUP(C117,Industry_Benchmark!$A$2:$A$82,Industry_Benchmark!$D$2:$D$82,"") -> 1.469 | N117: =L117-M117 -> 0.327 | O117: =IF(N117>0,1,0) -> 1 | P117: 0.00451 | Q117: =_xlfn.XLOOKUP(C117,Industry_Benchmark!$A$2:$A$82,Industry_Benchmark!$E$2:$E$82,"") -> 0.066908572 | R117: =P117-Q117 -> -0.062398572 | S117: =IF(R117>0,1,0) -> 0 | T117: 169.123 | U117: =_xlfn.XLOOKUP(C117,Industry_Benchmark!$A$2:$A$82,Industry_Benchmark!$F$2:$F$82,"") -> 107.70214 | V117: =T117-U117 -> 61.420857 | W117: =IF(V117>0,1,0) -> 1 | X117: 0.048779998 | Y117: =_xlfn.XLOOKUP(C117,Industry_Benchmark!$A$2:$A$82,Industry_Benchmark!$G$2:$G$82,"") -> 0.26455857 | Z117: =X117-Y117 -> -0.21577857 | AA117: =IF(Z117>0,1,0) -> 0 | AB117: =SUM(G117,K117,O117,S117,W117,AA117) -> 2 | AC117: =AB117/6 -> 0.33333333 | AD117: {=_xlfn.IFS( AB117=6,"Excellent", AB117=5,"Strong", AB117=4,"Good", AB117=3,"Average", AB117<=2,"Weak" )} -> Weak
A118: Automatic Data Processing, Inc. | B118: ADP | C118: Staffing & Employment Services | D118: 0.1748 | E118: =_xlfn.XLOOKUP(C118,Industry_Benchmark!$A$2:$A$82,Industry_Benchmark!$B$2:$B$82,"") -> 0.235035 | F118: =D118-E118 -> -0.060235 | G118: =IF(F118>0,1,0) -> 0 | H118: 0.089 | I118: =_xlfn.XLOOKUP(C118,Industry_Benchmark!$A$2:$A$82,Industry_Benchmark!$C$2:$C$82,"") -> 0.108 | J118: =H118-I118 -> -0.019 | K118: =IF(J118>0,1,0) -> 0 | L118: 1.041 | M118: =_xlfn.XLOOKUP(C118,Industry_Benchmark!$A$2:$A$82,Industry_Benchmark!$D$2:$D$82,"") -> 1.1555 | N118: =L118-M118 -> -0.1145 | O118: =IF(N118>0,1,0) -> 0 | P118: 0.04133 | Q118: =_xlfn.XLOOKUP(C118,Industry_Benchmark!$A$2:$A$82,Industry_Benchmark!$E$2:$E$82,"") -> 0.07807 | R118: =P118-Q118 -> -0.03674 | S118: =IF(R118>0,1,0) -> 0 | T118: 68.328 | U118: =_xlfn.XLOOKUP(C118,Industry_Benchmark!$A$2:$A$82,Industry_Benchmark!$F$2:$F$82,"") -> 48.4775 | V118: =T118-U118 -> 19.8505 | W118: =IF(V118>0,1,0) -> 1 | X118: 0.50117 | Y118: =_xlfn.XLOOKUP(C118,Industry_Benchmark!$A$2:$A$82,Industry_Benchmark!$G$2:$G$82,"") -> 0.46344499 | Z118: =X118-Y118 -> 0.03772501 | AA118: =IF(Z118>0,1,0) -> 1 | AB118: =SUM(G118,K118,O118,S118,W118,AA118) -> 2 | AC118: =AB118/6 -> 0.33333333 | AD118: {=_xlfn.IFS( AB118=6,"Excellent", AB118=5,"Strong", AB118=4,"Good", AB118=3,"Average", AB118<=2,"Weak" )} -> Weak
A119: Duke Energy Corporation (Holdin | B119: DUK | C119: Utilities—Regulated Electric | D119: 0.12795 | E119: =_xlfn.XLOOKUP(C119,Industry_Benchmark!$A$2:$A$82,Industry_Benchmark!$B$2:$B$82,"") -> 0.1392 | F119: =D119-E119 -> -0.011249998 | G119: =IF(F119>0,1,0) -> 0 | H119: 0.034 | I119: =_xlfn.XLOOKUP(C119,Industry_Benchmark!$A$2:$A$82,Industry_Benchmark!$C$2:$C$82,"") -> 0.030333333 | J119: =H119-I119 -> 0.0036666667 | K119: =IF(J119>0,1,0) -> 1 | L119: 0.607 | M119: =_xlfn.XLOOKUP(C119,Industry_Benchmark!$A$2:$A$82,Industry_Benchmark!$D$2:$D$82,"") -> 0.65966667 | N119: =L119-M119 -> -0.052666667 | O119: =IF(N119>0,1,0) -> 0 | P119: 0.02219 | Q119: =_xlfn.XLOOKUP(C119,Industry_Benchmark!$A$2:$A$82,Industry_Benchmark!$E$2:$E$82,"") -> 0.021278334 | R119: =P119-Q119 -> 0.00091166625 | S119: =IF(R119>0,1,0) -> 1 | T119: 128.981 | U119: =_xlfn.XLOOKUP(C119,Industry_Benchmark!$A$2:$A$82,Industry_Benchmark!$F$2:$F$82,"") -> 151.27917 | V119: =T119-U119 -> -22.298167 | W119: =IF(V119>0,1,0) -> 0 | X119: 0.05598 | Y119: =_xlfn.XLOOKUP(C119,Industry_Benchmark!$A$2:$A$82,Industry_Benchmark!$G$2:$G$82,"") -> 0.080088333 | Z119: =X119-Y119 -> -0.024108333 | AA119: =IF(Z119>0,1,0) -> 0 | AB119: =SUM(G119,K119,O119,S119,W119,AA119) -> 2 | AC119: =AB119/6 -> 0.33333333 | AD119: {=_xlfn.IFS( AB119=6,"Excellent", AB119=5,"Strong", AB119=4,"Good", AB119=3,"Average", AB119<=2,"Weak" )} -> Weak
A120: Cigna Corporation | B120: CI | C120: Healthcare Plans | D120: 0.049200002 | E120: =_xlfn.XLOOKUP(C120,Industry_Benchmark!$A$2:$A$82,Industry_Benchmark!$B$2:$B$82,"") -> 0.036041667 | F120: =D120-E120 -> 0.013158335 | G120: =IF(F120>0,1,0) -> 1 | H120: 0.082 | I120: =_xlfn.XLOOKUP(C120,Industry_Benchmark!$A$2:$A$82,Industry_Benchmark!$C$2:$C$82,"") -> 0.11366667 | J120: =H120-I120 -> -0.031666667 | K120: =IF(J120>0,1,0) -> 0 | L120: 0.7 | M120: =_xlfn.XLOOKUP(C120,Industry_Benchmark!$A$2:$A$82,Industry_Benchmark!$D$2:$D$82,"") -> 1.11 | N120: =L120-M120 -> -0.41 | O120: =IF(N120>0,1,0) -> 0 | P120: 0.03285 | Q120: =_xlfn.XLOOKUP(C120,Industry_Benchmark!$A$2:$A$82,Industry_Benchmark!$E$2:$E$82,"") -> 0.046496666 | R120: =P120-Q120 -> -0.013646666 | S120: =IF(R120>0,1,0) -> 0 | T120: 73.536 | U120: =_xlfn.XLOOKUP(C120,Industry_Benchmark!$A$2:$A$82,Industry_Benchmark!$F$2:$F$82,"") -> 78.132333 | V120: =T120-U120 -> -4.5963333 | W120: =IF(V120>0,1,0) -> 0 | X120: 0.17627001 | Y120: =_xlfn.XLOOKUP(C120,Industry_Benchmark!$A$2:$A$82,Industry_Benchmark!$G$2:$G$82,"") -> 0.14621 | Z120: =X120-Y120 -> 0.030060008 | AA120: =IF(Z120>0,1,0) -> 1 | AB120: =SUM(G120,K120,O120,S120,W120,AA120) -> 2 | AC120: =AB120/6 -> 0.33333333 | AD120: {=_xlfn.IFS( AB120=6,"Excellent", AB120=5,"Strong", AB120=4,"Good", AB120=3,"Average", AB120<=2,"Weak" )} -> Weak
A121: Intercontinental Exchange Inc. | B121: ICE | C121: Financial Data & Stock Exchanges | D121: 0.43815 | E121: =_xlfn.XLOOKUP(C121,Industry_Benchmark!$A$2:$A$82,Industry_Benchmark!$B$2:$B$82,"") -> 0.407172 | F121: =D121-E121 -> 0.030978004 | G121: =IF(F121>0,1,0) -> 1 | H121: 0.277 | I121: =_xlfn.XLOOKUP(C121,Industry_Benchmark!$A$2:$A$82,Industry_Benchmark!$C$2:$C$82,"") -> 0.1528 | J121: =H121-I121 -> 0.1242 | K121: =IF(J121>0,1,0) -> 1 | L121: 1.006 | M121: =_xlfn.XLOOKUP(C121,Industry_Benchmark!$A$2:$A$82,Industry_Benchmark!$D$2:$D$82,"") -> 1.5326 | N121: =L121-M121 -> -0.5266 | O121: =IF(N121>0,1,0) -> 0 | P121: 0.0153 | Q121: =_xlfn.XLOOKUP(C121,Industry_Benchmark!$A$2:$A$82,Industry_Benchmark!$E$2:$E$82,"") -> 0.101748 | R121: =P121-Q121 -> -0.086448 | S121: =IF(R121>0,1,0) -> 0 | T121: 66.88 | U121: =_xlfn.XLOOKUP(C121,Industry_Benchmark!$A$2:$A$82,Industry_Benchmark!$F$2:$F$82,"") -> 95.8734 | V121: =T121-U121 -> -28.9934 | W121: =IF(V121>0,1,0) -> 0 | X121: 0.1503 | Y121: =_xlfn.XLOOKUP(C121,Industry_Benchmark!$A$2:$A$82,Industry_Benchmark!$G$2:$G$82,"") -> 0.4871975 | Z121: =X121-Y121 -> -0.3368975 | AA121: =IF(Z121>0,1,0) -> 0 | AB121: =SUM(G121,K121,O121,S121,W121,AA121) -> 2 | AC121: =AB121/6 -> 0.33333333 | AD121: {=_xlfn.IFS( AB121=6,"Excellent", AB121=5,"Strong", AB121=4,"Good", AB121=3,"Average", AB121<=2,"Weak" )} -> Weak
A122: Crown Castle International Corp | B122: CCI | C122: REIT—Specialty | D122: 0.17287001 | E122: =_xlfn.XLOOKUP(C122,Industry_Benchmark!$A$2:$A$82,Industry_Benchmark!$B$2:$B$82,"") -> 0.1609075 | F122: =D122-E122 -> 0.011962507 | G122: =IF(F122>0,1,0) -> 1 | H122: 0.108 | I122: =_xlfn.XLOOKUP(C122,Industry_Benchmark!$A$2:$A$82,Industry_Benchmark!$C$2:$C$82,"") -> 0.1415 | J122: =H122-I122 -> -0.0335 | K122: =IF(J122>0,1,0) -> 0 | L122: 0.619 | M122: =_xlfn.XLOOKUP(C122,Industry_Benchmark!$A$2:$A$82,Industry_Benchmark!$D$2:$D$82,"") -> 0.9255 | N122: =L122-M122 -> -0.3065 | O122: =IF(N122>0,1,0) -> 0 | P122: 0.0325 | Q122: =_xlfn.XLOOKUP(C122,Industry_Benchmark!$A$2:$A$82,Industry_Benchmark!$E$2:$E$82,"") -> 0.03869 | R122: =P122-Q122 -> -0.00619 | S122: =IF(R122>0,1,0) -> 0 | T122: 327.065 | U122: =_xlfn.XLOOKUP(C122,Industry_Benchmark!$A$2:$A$82,Industry_Benchmark!$F$2:$F$82,"") -> 226.1405 | V122: =T122-U122 -> 100.9245 | W122: =IF(V122>0,1,0) -> 1 | X122: 0.13071 | Y122: =_xlfn.XLOOKUP(C122,Industry_Benchmark!$A$2:$A$82,Industry_Benchmark!$G$2:$G$82,"") -> 0.17199 | Z122: =X122-Y122 -> -0.04128 | AA122: =IF(Z122>0,1,0) -> 0 | AB122: =SUM(G122,K122,O122,S122,W122,AA122) -> 2 | AC122: =AB122/6 -> 0.33333333 | AD122: {=_xlfn.IFS( AB122=6,"Excellent", AB122=5,"Strong", AB122=4,"Good", AB122=3,"Average", AB122<=2,"Weak" )} -> Weak
A123: Gilead Sciences, Inc. | B123: GILD | C123: Drug Manufacturers—General | D123: 0.26905 | E123: =_xlfn.XLOOKUP(C123,Industry_Benchmark!$A$2:$A$82,Industry_Benchmark!$B$2:$B$82,"") -> 0.21304125 | F123: =D123-E123 -> 0.05600875 | G123: =IF(F123>0,1,0) -> 1 | H123: 0.128 | I123: =_xlfn.XLOOKUP(C123,Industry_Benchmark!$A$2:$A$82,Industry_Benchmark!$C$2:$C$82,"") -> 0.270125 | J123: =H123-I123 -> -0.142125 | K123: =IF(J123>0,1,0) -> 0 | L123: 1.366 | M123: =_xlfn.XLOOKUP(C123,Industry_Benchmark!$A$2:$A$82,Industry_Benchmark!$D$2:$D$82,"") -> 1.4105714 | N123: =L123-M123 -> -0.044571429 | O123: =IF(N123>0,1,0) -> 0 | P123: 0.12683 | Q123: =_xlfn.XLOOKUP(C123,Industry_Benchmark!$A$2:$A$82,Industry_Benchmark!$E$2:$E$82,"") -> 0.095184286 | R123: =P123-Q123 -> 0.031645714 | S123: =IF(R123>0,1,0) -> 1 | T123: 128.946 | U123: =_xlfn.XLOOKUP(C123,Industry_Benchmark!$A$2:$A$82,Industry_Benchmark!$F$2:$F$82,"") -> 212.024 | V123: =T123-U123 -> -83.078 | W123: =IF(V123>0,1,0) -> 0 | X123: 0.37846002 | Y123: =_xlfn.XLOOKUP(C123,Industry_Benchmark!$A$2:$A$82,Industry_Benchmark!$G$2:$G$82,"") -> 0.47294626 | Z123: =X123-Y123 -> -0.094486236 | AA123: =IF(Z123>0,1,0) -> 0 | AB123: =SUM(G123,K123,O123,S123,W123,AA123) -> 2 | AC123: =AB123/6 -> 0.33333333 | AD123: {=_xlfn.IFS( AB123=6,"Excellent", AB123=5,"Strong", AB123=4,"Good", AB123=3,"Average", AB123<=2,"Weak" )} -> Weak
A124: Aon plc | B124: AON | C124: Insurance Brokers | D124: 0.075840004 | E124: =_xlfn.XLOOKUP(C124,Industry_Benchmark!$A$2:$A$82,Industry_Benchmark!$B$2:$B$82,"") -> 0.1187 | F124: =D124-E124 -> -0.042859997 | G124: =IF(F124>0,1,0) -> 0 | H124: 0.133 | I124: =_xlfn.XLOOKUP(C124,Industry_Benchmark!$A$2:$A$82,Industry_Benchmark!$C$2:$C$82,"") -> 0.15366667 | J124: =H124-I124 -> -0.020666667 | K124: =IF(J124>0,1,0) -> 0 | L124: 1.07 | M124: =_xlfn.XLOOKUP(C124,Industry_Benchmark!$A$2:$A$82,Industry_Benchmark!$D$2:$D$82,"") -> 1.2033333 | N124: =L124-M124 -> -0.13333333 | O124: =IF(N124>0,1,0) -> 0 | P124: 0.03906 | Q124: =_xlfn.XLOOKUP(C124,Industry_Benchmark!$A$2:$A$82,Industry_Benchmark!$E$2:$E$82,"") -> 0.054233333 | R124: =P124-Q124 -> -0.015173333 | S124: =IF(R124>0,1,0) -> 0 | T124: 412.571 | U124: =_xlfn.XLOOKUP(C124,Industry_Benchmark!$A$2:$A$82,Industry_Benchmark!$F$2:$F$82,"") -> 199.41467 | V124: =T124-U124 -> 213.15633 | W124: =IF(V124>0,1,0) -> 1 | X124: 0.32708 | Y124: =_xlfn.XLOOKUP(C124,Industry_Benchmark!$A$2:$A$82,Industry_Benchmark!$G$2:$G$82,"") -> 0.25839667 | Z124: =X124-Y124 -> 0.068683333 | AA124: =IF(Z124>0,1,0) -> 1 | AB124: =SUM(G124,K124,O124,S124,W124,AA124) -> 2 | AC124: =AB124/6 -> 0.33333333 | AD124: {=_xlfn.IFS( AB124=6,"Excellent", AB124=5,"Strong", AB124=4,"Good", AB124=3,"Average", AB124<=2,"Weak" )} -> Weak
A125: Progressive Corporation (The) | B125: PGR | C125: Insurance—Property & Casualty | D125: 0.07028 | E125: =_xlfn.XLOOKUP(C125,Industry_Benchmark!$A$2:$A$82,Industry_Benchmark!$B$2:$B$82,"") -> 0.1066625 | F125: =D125-E125 -> -0.036382502 | G125: =IF(F125>0,1,0) -> 0 | H125: 0.094 | I125: =_xlfn.XLOOKUP(C125,Industry_Benchmark!$A$2:$A$82,Industry_Benchmark!$C$2:$C$82,"") -> 0.12125 | J125: =H125-I125 -> -0.02725 | K125: =IF(J125>0,1,0) -> 0 | L125: 0.34 | M125: =_xlfn.XLOOKUP(C125,Industry_Benchmark!$A$2:$A$82,Industry_Benchmark!$D$2:$D$82,"") -> 0.36975 | N125: =L125-M125 -> -0.02975 | O125: =IF(N125>0,1,0) -> 0 | P125: 0.04093 | Q125: =_xlfn.XLOOKUP(C125,Industry_Benchmark!$A$2:$A$82,Industry_Benchmark!$E$2:$E$82,"") -> 0.032555001 | R125: =P125-Q125 -> 0.0083749993 | S125: =IF(R125>0,1,0) -> 1 | T125: 27.862 | U125: =_xlfn.XLOOKUP(C125,Industry_Benchmark!$A$2:$A$82,Industry_Benchmark!$F$2:$F$82,"") -> 29.93275 | V125: =T125-U125 -> -2.07075 | W125: =IF(V125>0,1,0) -> 0 | X125: 0.19001 | Y125: =_xlfn.XLOOKUP(C125,Industry_Benchmark!$A$2:$A$82,Industry_Benchmark!$G$2:$G$82,"") -> 0.1645025 | Z125: =X125-Y125 -> 0.025507503 | AA125: =IF(Z125>0,1,0) -> 1 | AB125: =SUM(G125,K125,O125,S125,W125,AA125) -> 2 | AC125: =AB125/6 -> 0.33333333 | AD125: {=_xlfn.IFS( AB125=6,"Excellent", AB125=5,"Strong", AB125=4,"Good", AB125=3,"Average", AB125<=2,"Weak" )} -> Weak
... A135: Kimberly-Clark Corporation | B135: KMB | C135: Household & Personal Products | D135: 0.093310006 | E135: =_xlfn.XLOOKUP(C135,Industry_Benchmark!$A$2:$A$82,Industry_Benchmark!$B$2:$B$82,"") -> 0.1452825 | F135: =D135-E135 -> -0.051972498 | G135: =IF(F135>0,1,0) -> 0 | H135: 0.027 | I135: =_xlfn.XLOOKUP(C135,Industry_Benchmark!$A$2:$A$82,Industry_Benchmark!$C$2:$C$82,"") -> 0.08475 | J135: =H135-I135 -> -0.05775 | K135: =IF(J135>0,1,0) -> 0 | L135: 0.825 | M135: =_xlfn.XLOOKUP(C135,Industry_Benchmark!$A$2:$A$82,Industry_Benchmark!$D$2:$D$82,"") -> 1.09125 | N135: =L135-M135 -> -0.26625 | O135: =IF(N135>0,1,0) -> 0 | P135: 0.1005 | Q135: =_xlfn.XLOOKUP(C135,Industry_Benchmark!$A$2:$A$82,Industry_Benchmark!$E$2:$E$82,"") -> 0.113515 | R135: =P135-Q135 -> -0.013015 | S135: =IF(R135>0,1,0) -> 0 | T135: 1237.856 | U135: =_xlfn.XLOOKUP(C135,Industry_Benchmark!$A$2:$A$82,Industry_Benchmark!$F$2:$F$82,"") -> 560.26625 | V135: =T135-U135 -> 677.58975 | W135: =IF(V135>0,1,0) -> 1 | X135: 2.29639 | Y135: =_xlfn.XLOOKUP(C135,Industry_Benchmark!$A$2:$A$82,Industry_Benchmark!$G$2:$G$82,"") -> 1.349125 | Z135: =X135-Y135 -> 0.947265 | AA135: =IF(Z135>0,1,0) -> 1 | AB135: =SUM(G135,K135,O135,S135,W135,AA135) -> 2 | AC135: =AB135/6 -> 0.33333333 | AD135: {=_xlfn.IFS( AB135=6,"Excellent", AB135=5,"Strong", AB135=4,"Good", AB135=3,"Average", AB135<=2,"Weak" )} -> Weak
A136: AutoZone, Inc. | B136: AZO | C136: Specialty Retail | D136: 0.15076 | E136: =_xlfn.XLOOKUP(C136,Industry_Benchmark!$A$2:$A$82,Industry_Benchmark!$B$2:$B$82,"") -> 0.154615 | F136: =D136-E136 -> -0.003855 | G136: =IF(F136>0,1,0) -> 0 | H136: 0.163 | I136: =_xlfn.XLOOKUP(C136,Industry_Benchmark!$A$2:$A$82,Industry_Benchmark!$C$2:$C$82,"") -> 0.124 | J136: =H136-I136 -> 0.039 | K136: =IF(J136>0,1,0) -> 1 | L136: 0.785 | M136: =_xlfn.XLOOKUP(C136,Industry_Benchmark!$A$2:$A$82,Industry_Benchmark!$D$2:$D$82,"") -> 0.7735 | N136: =L136-M136 -> 0.0115 | O136: =IF(N136>0,1,0) -> 1 | P136: 0.13464 | Q136: =_xlfn.XLOOKUP(C136,Industry_Benchmark!$A$2:$A$82,Industry_Benchmark!$E$2:$E$82,"") -> 0.138815 | R136: =P136-Q136 -> -0.004175 | S136: =IF(R136>0,1,0) -> 0 | T136: 0 | U136: =_xlfn.XLOOKUP(C136,Industry_Benchmark!$A$2:$A$82,Industry_Benchmark!$F$2:$F$82,"") -> 0 | V136: =T136-U136 -> 0 | W136: =IF(V136>0,1,0) -> 0 | Y136: =_xlfn.XLOOKUP(C136,Industry_Benchmark!$A$2:$A$82,Industry_Benchmark!$G$2:$G$82,"") -> 7.17367 | Z136: =X136-Y136 -> -7.17367 | AA136: =IF(Z136>0,1,0) -> 0 | AB136: =SUM(G136,K136,O136,S136,W136,AA136) -> 2 | AC136: =AB136/6 -> 0.33333333 | AD136: {=_xlfn.IFS( AB136=6,"Excellent", AB136=5,"Strong", AB136=4,"Good", AB136=3,"Average", AB136<=2,"Weak" )} -> Weak
A137: Realty Income Corporation | B137: O | C137: REIT—Retail | D137: 0.17267999 | E137: =_xlfn.XLOOKUP(C137,Industry_Benchmark!$A$2:$A$82,Industry_Benchmark!$B$2:$B$82,"") -> 0.29133999 | F137: =D137-E137 -> -0.11866 | G137: =IF(F137>0,1,0) -> 0 | H137: 0.641 | I137: =_xlfn.XLOOKUP(C137,Industry_Benchmark!$A$2:$A$82,Industry_Benchmark!$C$2:$C$82,"") -> 0.4315 | J137: =H137-I137 -> 0.2095 | K137: =IF(J137>0,1,0) -> 1 | L137: 0.428 | M137: =_xlfn.XLOOKUP(C137,Industry_Benchmark!$A$2:$A$82,Industry_Benchmark!$D$2:$D$82,"") -> 0.411 | N137: =L137-M137 -> 0.017 | O137: =IF(N137>0,1,0) -> 1 | P137: 0.01865 | Q137: =_xlfn.XLOOKUP(C137,Industry_Benchmark!$A$2:$A$82,Industry_Benchmark!$E$2:$E$82,"") -> 0.031075 | R137: =P137-Q137 -> -0.012425 | S137: =IF(R137>0,1,0) -> 0 | T137: 61.452 | U137: =_xlfn.XLOOKUP(C137,Industry_Benchmark!$A$2:$A$82,Industry_Benchmark!$F$2:$F$82,"") -> 325.386 | V137: =T137-U137 -> -263.934 | W137: =IF(V137>0,1,0) -> 0 | X137: 0.019960001 | Y137: =_xlfn.XLOOKUP(C137,Industry_Benchmark!$A$2:$A$82,Industry_Benchmark!$G$2:$G$82,"") -> 0.35798998 | Z137: =X137-Y137 -> -0.33802997 | AA137: =IF(Z137>0,1,0) -> 0 | AB137: =SUM(G137,K137,O137,S137,W137,AA137) -> 2 | AC137: =AB137/6 -> 0.33333333 | AD137: {=_xlfn.IFS( AB137=6,"Excellent", AB137=5,"Strong", AB137=4,"Good", AB137=3,"Average", AB137<=2,"Weak" )} -> Weak
A138: DuPont de Nemours, Inc. | B138: DD | C138: Specialty Chemicals | D138: 0.29224002 | E138: =_xlfn.XLOOKUP(C138,Industry_Benchmark!$A$2:$A$82,Industry_Benchmark!$B$2:$B$82,"") -> 0.15536 | F138: =D138-E138 -> 0.13688002 | G138: =IF(F138>0,1,0) -> 1 | H138: 0.177 | I138: =_xlfn.XLOOKUP(C138,Industry_Benchmark!$A$2:$A$82,Industry_Benchmark!$C$2:$C$82,"") -> 0.21066667 | J138: =H138-I138 -> -0.033666667 | K138: =IF(J138>0,1,0) -> 0 | L138: 2.013 | M138: =_xlfn.XLOOKUP(C138,Industry_Benchmark!$A$2:$A$82,Industry_Benchmark!$D$2:$D$82,"") -> 1.6655 | N138: =L138-M138 -> 0.3475 | O138: =IF(N138>0,1,0) -> 1 | P138: 0.026530001 | Q138: =_xlfn.XLOOKUP(C138,Industry_Benchmark!$A$2:$A$82,Industry_Benchmark!$E$2:$E$82,"") -> 0.067101667 | R138: =P138-Q138 -> -0.040571666 | S138: =IF(R138>0,1,0) -> 0 | T138: 40.603 | U138: =_xlfn.XLOOKUP(C138,Industry_Benchmark!$A$2:$A$82,Industry_Benchmark!$F$2:$F$82,"") -> 123.15567 | V138: =T138-U138 -> -82.552667 | W138: =IF(V138>0,1,0) -> 0 | X138: 0.04642 | Y138: =_xlfn.XLOOKUP(C138,Industry_Benchmark!$A$2:$A$82,Industry_Benchmark!$G$2:$G$82,"") -> 0.26484833 | Z138: =X138-Y138 -> -0.21842833 | AA138: =IF(Z138>0,1,0) -> 0 | AB138: =SUM(G138,K138,O138,S138,W138,AA138) -> 2 | AC138: =AB138/6 -> 0.33333333 | AD138: {=_xlfn.IFS( AB138=6,"Excellent", AB138=5,"Strong", AB138=4,"Good", AB138=3,"Average", AB138<=2,"Weak" )} -> Weak
A139: Motorola Solutions, Inc. | B139: MSI | C139: Communication Equipment | D139: 0.1546 | E139: =_xlfn.XLOOKUP(C139,Industry_Benchmark!$A$2:$A$82,Industry_Benchmark!$B$2:$B$82,"") -> 0.1895 | F139: =D139-E139 -> -0.0349 | G139: =IF(F139>0,1,0) -> 0 | H139: 0.128 | I139: =_xlfn.XLOOKUP(C139,Industry_Benchmark!$A$2:$A$82,Industry_Benchmark!$C$2:$C$82,"") -> 0.1045 | J139: =H139-I139 -> 0.0235 | K139: =IF(J139>0,1,0) -> 1 | L139: 1.381 | M139: =_xlfn.XLOOKUP(C139,Industry_Benchmark!$A$2:$A$82,Industry_Benchmark!$D$2:$D$82,"") -> 1.4995 | N139: =L139-M139 -> -0.1185 | O139: =IF(N139>0,1,0) -> 0 | P139: 0.10668001 | Q139: =_xlfn.XLOOKUP(C139,Industry_Benchmark!$A$2:$A$82,Industry_Benchmark!$E$2:$E$82,"") -> 0.099320003 | R139: =P139-Q139 -> 0.007360003 | S139: =IF(R139>0,1,0) -> 1 | T139: 0 | U139: =_xlfn.XLOOKUP(C139,Industry_Benchmark!$A$2:$A$82,Industry_Benchmark!$F$2:$F$82,"") -> 12.516 | V139: =T139-U139 -> -12.516 | W139: =IF(V139>0,1,0) -> 0 | Y139: =_xlfn.XLOOKUP(C139,Industry_Benchmark!$A$2:$A$82,Industry_Benchmark!$G$2:$G$82,"") -> 0.28190002 | Z139: =X139-Y139 -> -0.28190002 | AA139: =IF(Z139>0,1,0) -> 0 | AB139: =SUM(G139,K139,O139,S139,W139,AA139) -> 2 | AC139: =AB139/6 -> 0.33333333 | AD139: {=_xlfn.IFS( AB139=6,"Excellent", AB139=5,"Strong", AB139=4,"Good", AB139=3,"Average", AB139<=2,"Weak" )} -> Weak
A140: Trane Technologies plc | B140: TT | C140: Specialty Industrial Machinery | D140: 0.09823 | E140: =_xlfn.XLOOKUP(C140,Industry_Benchmark!$A$2:$A$82,Industry_Benchmark!$B$2:$B$82,"") -> 0.12041 | F140: =D140-E140 -> -0.022180001 | G140: =IF(F140>0,1,0) -> 0 | H140: 0.064 | I140: =_xlfn.XLOOKUP(C140,Industry_Benchmark!$A$2:$A$82,Industry_Benchmark!$C$2:$C$82,"") -> 0.070857143 | J140: =H140-I140 -> -0.0068571429 | K140: =IF(J140>0,1,0) -> 0 | L140: 1.621 | M140: =_xlfn.XLOOKUP(C140,Industry_Benchmark!$A$2:$A$82,Industry_Benchmark!$D$2:$D$82,"") -> 1.469 | N140: =L140-M140 -> 0.152 | O140: =IF(N140>0,1,0) -> 1 | P140: 0.06885 | Q140: =_xlfn.XLOOKUP(C140,Industry_Benchmark!$A$2:$A$82,Industry_Benchmark!$E$2:$E$82,"") -> 0.066908572 | R140: =P140-Q140 -> 0.0019414277 | S140: =IF(R140>0,1,0) -> 1 | T140: 74.62 | U140: =_xlfn.XLOOKUP(C140,Industry_Benchmark!$A$2:$A$82,Industry_Benchmark!$F$2:$F$82,"") -> 107.70214 | V140: =T140-U140 -> -33.082143 | W140: =IF(V140>0,1,0) -> 0 | X140: 0.21420999 | Y140: =_xlfn.XLOOKUP(C140,Industry_Benchmark!$A$2:$A$82,Industry_Benchmark!$G$2:$G$82,"") -> 0.26455857 | Z140: =X140-Y140 -> -0.05034858 | AA140: =IF(Z140>0,1,0) -> 0 | AB140: =SUM(G140,K140,O140,S140,W140,AA140) -> 2 | AC140: =AB140/6 -> 0.33333333 | AD140: {=_xlfn.IFS( AB140=6,"Excellent", AB140=5,"Strong", AB140=4,"Good", AB140=3,"Average", AB140<=2,"Weak" )} -> Weak
A141: Electronic Arts Inc. | B141: EA | C141: Electronic Gaming & Multimedia | D141: 0.12272999 | E141: =_xlfn.XLOOKUP(C141,Industry_Benchmark!$A$2:$A$82,Industry_Benchmark!$B$2:$B$82,"") -> 0.20741 | F141: =D141-E141 -> -0.084680003 | G141: =IF(F141>0,1,0) -> 0 | H141: 0.586 | I141: =_xlfn.XLOOKUP(C141,Industry_Benchmark!$A$2:$A$82,Industry_Benchmark!$C$2:$C$82,"") -> 0.3225 | J141: =H141-I141 -> 0.2635 | K141: =IF(J141>0,1,0) -> 1 | L141: 1.315 | M141: =_xlfn.XLOOKUP(C141,Industry_Benchmark!$A$2:$A$82,Industry_Benchmark!$D$2:$D$82,"") -> 3.438 | N141: =L141-M141 -> -2.123 | O141: =IF(N141>0,1,0) -> 0 | P141: 0.05712 | Q141: =_xlfn.XLOOKUP(C141,Industry_Benchmark!$A$2:$A$82,Industry_Benchmark!$E$2:$E$82,"") -> 0.07348 | R141: =P141-Q141 -> -0.01636 | S141: =IF(R141>0,1,0) -> 0 | T141: 27.94 | U141: =_xlfn.XLOOKUP(C141,Industry_Benchmark!$A$2:$A$82,Industry_Benchmark!$F$2:$F$82,"") -> 24.61 | V141: =T141-U141 -> 3.33 | W141: =IF(V141>0,1,0) -> 1 | X141: 0.09854999 | Y141: =_xlfn.XLOOKUP(C141,Industry_Benchmark!$A$2:$A$82,Industry_Benchmark!$G$2:$G$82,"") -> 0.13366 | Z141: =X141-Y141 -> -0.035110015 | AA141: =IF(Z141>0,1,0) -> 0 | AB141: =SUM(G141,K141,O141,S141,W141,AA141) -> 2 | AC141: =AB141/6 -> 0.33333333 | AD141: {=_xlfn.IFS( AB141=6,"Excellent", AB141=5,"Strong", AB141=4,"Good", AB141=3,"Average", AB141<=2,"Weak" )} -> Weak
